Workbook

Sheet Comparatif
A1: Comparatif DAC / amplis portables — synthèse personnalisée pour L70 + Cayin N7
A2: Notes 1–10 selon le cahier des charges. Score pondéré compatible Excel/Gnumeric. Rang = appareils portables uniquement ; N7 et L70 sont marqués « Réf. ». Prix = repère européen quand disponible, sinon MSRP/prix de lancement converti en euros. Sources prix dans la feuille dédiée.
A3: PRODUIT & PROFIL | G3: ÉVALUATION PERSONNALISÉE — 1 À 10 | Q3: SCORE | S3: COMPARAISON & USAGE | X3: HEADFONICS | AF3: PRIX | AG3: AVIS MULTI-SOURCES
A4: Marque | B4: Modèle | C4: Type | D4: Profil sonore | E4: Atout principal | F4: Limite principale | G4: Propreté / contrôle | H4: Microdétail | I4: Profondeur avant-arrière | J4: Holographie / 3D | K4: Layering | L4: Matière / timbres | M4: Dynamique / tenue | N4: Puissance / polyvalence | O4: Nomadisme | P4: Complémentarité N7/L70 | Q4: Score perso /10 | R4: Rang | S4: Face au L70 | T4: Face au N7 | U4: Rôle conseillé | V4: Confiance | W4: Origine | X4: Score Headfonics | Y4: Type score HF | Z4: Date review HF | AA4: Page HF (reconstruite) | AB4: Lien Headfonics | AC4: Résumé HF | AD4: Statut BDD | AE4: Rang chrono HF | AF4: Prix moyen / MSRP (≈€) | AG4: Résumé avis (court) | AH4: Tonalité selon avis | AI4: Scène / détail selon avis | AJ4: Limites relevées dans les avis | AK4: Source avis principale | AL4: Nb sources avis | AM4: Confiance avis | AN4: Source avis 2 | AO4: Source avis 3 | AP4: Source avis 4 | AQ4: Statut multi-source | AR4: Types / diversité sources
A5: Cayin | B5: N7 | C5: DAP / référence | D5: Organique, fluide, texturé, très naturel | E5: Volumes, profondeur, continuité des plans, timbres | F5: Moins chirurgical/ferme qu’un ampli desktop très neutre | G5: 9.2 | H5: 9.5 | I5: 9.8 | J5: 9.7 | K5: 9.8 | L5: 10 | M5: 9.3 | N5: 8.5 | O5: 6.5 | P5: 10 | Q5: =IF(COUNT(G5:P5)=10,ROUND((G5*'Pondérations'!$B$5+H5*'Pondérations'!$B$6+I5*'Pondérations'!$B$7+J5*'Pondérations'!$B$8+K5*'Pondérations'!$B$9+L5*'Pondérations'!$B$10+M5*'Pondérations'!$B$11+N5*'Pondérations'!$B$12+O5*'Pondérations'!$B$13+P5*'Pondérations'!$B$14)/'Pondérations'!$B$16,3),"") | R5: Réf. | V5: Élevée | W5: Discussion initiale | AF5: 1757 | AG5: Le N7 est surtout apprécié pour son rendu organique, fluide et volumique. La classe A ajoute chaleur et densité, tandis que l'AB gagne en attaque, contrôle et clarté. | AH5: Organique, naturelle, légèrement chaude en classe A | AI5: Scène large et profonde, image solide, excellent relief et continuité des plans; détail intégré plutôt que sur-accentué. | AJ5: Moins incisif qu'une source très analytique; caractère et dynamique varient sensiblement entre classe A et AB. | AK5: https://www.ecoustics.com/reviews/cayin-n7/ | AL5: 4 | AM5: Élevée — 3+ sources, domaines variés | AN5: https://headfonics.com/cayin-n7-review/ | AO5: https://www.headfonia.com/cayin-n7-review/ | AP5: https://mobileaudiophile.com/daps/cayin-n7-dap-god-of-dynamism/ | AQ5: Objectif atteint | AR5: Review éditoriale: 4
A6: Topping | B6: L70 | C6: Ampli casque desktop / référence | D6: Très propre, neutre, contrôlé, ferme | E6: Fond noir, contrôle, puissance, neutralité | F6: Moins de profondeur holographique et de micro-relief | G6: 10 | H6: 8.8 | I6: 7.2 | J6: 7 | K6: 8 | L6: 8.2 | M6: 9.5 | N6: 10 | O6: 1 | P6: 6.5 | Q6: =IF(COUNT(G6:P6)=10,ROUND((G6*'Pondérations'!$B$5+H6*'Pondérations'!$B$6+I6*'Pondérations'!$B$7+J6*'Pondérations'!$B$8+K6*'Pondérations'!$B$9+L6*'Pondérations'!$B$10+M6*'Pondérations'!$B$11+N6*'Pondérations'!$B$12+O6*'Pondérations'!$B$13+P6*'Pondérations'!$B$14)/'Pondérations'!$B$16,3),"") | R6: Réf. | V6: Élevée | W6: Discussion initiale | AF6: 307 | AG6: Le L70 est décrit comme très propre, puissant et transparent, avec une séparation remarquable. Certains avis lui trouvent néanmoins une présentation plus pleine que strictement clinique. | AH6: Neutre, propre, légèrement plein selon les associations | AI6: Grande largeur, excellente séparation et précision; profondeur correcte mais rendu surtout axé sur contrôle et lisibilité. | AJ6: Peut paraître moins organique/holographique qu'une amplification discrète de caractère; très dépendant du DAC en amont. | AK6: https://primeaudio.org/topping-e70-and-l70-review/ | AL6: 5 | AM6: Élevée — 3+ sources, domaines variés | AN6: https://iiwireviews.com/topping-l70-review-head-amp-with-full-bodied-sound | AO6: https://headfonics.com/topping-l70-review/ | AP6: https://www.headfonia.com/topping-e70-l70-review/ | AQ6: Objectif atteint | AR6: Head-Fi reviews: 1; Review éditoriale: 4
A7: iBasso | B7: DC-Elite | C7: Dongle DAC/amp | D7: Neutre-naturel, très résolvant, incisif sans sécheresse | E7: Microdétail + profondeur + contours + texture | F7: Cher, consommation USB, moins organique que N7 | G7: 9.6 | H7: 9.6 | I7: 9.2 | J7: 9.2 | K7: 9.4 | L7: 9.2 | M7: 9.5 | N7: 7 | O7: 9 | P7: 9.7 | Q7: =IF(COUNT(G7:P7)=10,ROUND((G7*'Pondérations'!$B$5+H7*'Pondérations'!$B$6+I7*'Pondérations'!$B$7+J7*'Pondérations'!$B$8+K7*'Pondérations'!$B$9+L7*'Pondérations'!$B$10+M7*'Pondérations'!$B$11+N7*'Pondérations'!$B$12+O7*'Pondérations'!$B$13+P7*'Pondérations'!$B$14)/'Pondérations'!$B$16,3),"") | R7: =IF(Q7="","",1+COUNTIF($Q$7:$Q$178,">"&Q7)+COUNTIF($Q$7:Q7,Q7)-1) | V7: Élevée | W7: Discussion + Headfonics | X7: 8.6 | Y7: Reader | Z7: 45499 | AA7: 3 | AB7: https://headfonics.com/?s=iBasso+DC-Elite | AC7: Flagship dongle DAC/amp | AD7: Déjà présent | AE7: 51 | AF7: 439 | AG7: Dongle flagship très détaillé, propre et extrêmement dynamique, avec un niveau proche de certains DAP haut de gamme. | AH7: Neutre-naturel, très résolvant. | AI7: Scène franchement holographique, excellente dynamique et très bon contrôle des petits niveaux. | AJ7: Ergonomie du volume perfectible; résultat peut varier selon la source USB/téléphone. | AK7: https://headfonics.com/ibasso-dc-elite-review/ | AL7: 4 | AM7: Élevée — 3+ sources, domaines variés | AN7: https://www.head-fi.org/showcase/ibasso-dc-elite.27762/ | AO7: https://www.headfonia.com/ibasso-dc-elite-review/ | AP7: https://mobileaudiophile.com/dacs/dongle/ibasso-dc-elite-review-magic-box/ | AQ7: Objectif atteint | AR7: Head-Fi reviews: 1; Review éditoriale: 3
A8: Quloos | B8: MUB1 | C8: DAC/amp portable sur batterie | D8: Légèrement chaleureux, dense, transparent | E8: Densité, layering, profondeur verticale, puissance | F8: Un peu plus doux/moins incisif que DC-Elite | G8: 9.3 | H8: 9.1 | I8: 9.2 | J8: 9.1 | K8: 9.3 | L8: 9.4 | M8: 9.1 | N8: 9.5 | O8: 7.8 | P8: 9.5 | Q8: =IF(COUNT(G8:P8)=10,ROUND((G8*'Pondérations'!$B$5+H8*'Pondérations'!$B$6+I8*'Pondérations'!$B$7+J8*'Pondérations'!$B$8+K8*'Pondérations'!$B$9+L8*'Pondérations'!$B$10+M8*'Pondérations'!$B$11+N8*'Pondérations'!$B$12+O8*'Pondérations'!$B$13+P8*'Pondérations'!$B$14)/'Pondérations'!$B$16,3),"") | R8: =IF(Q8="","",1+COUNTIF($Q$7:$Q$178,">"&Q8)+COUNTIF($Q$7:Q8,Q8)-1) | V8: Moyenne à élevée | W8: Discussion initiale | AF8: 439 | AG8: Le MUB1 est régulièrement décrit comme naturel, dense et très propre, avec un grave profond et contrôlé, des médiums riches et un aigu détaillé sans agressivité. | AH8: Équilibrée, naturelle, légèrement chaleureuse | AI8: Scène spacieuse avec vraie profondeur, bon layering et fond noir; image précise sans sonner sèche. | AJ8: Peut sembler un peu moins tranchant qu'un dongle très analytique; le super-gain est moins adapté aux IEM sensibles. | AK8: https://moonstarreviews.net/quloos-mub1-review/ | AL8: 4 | AM8: Élevée — 3+ sources, domaines variés | AN8: https://www.head-fi.org/showcase/qls-hifi-mub1.26725/reviews | AO8: https://theheadphonelist.com/review-quloos-mub1/ | AP8: https://www.head-fi.org/threads/qls-mub-1.969455/ | AQ8: Objectif atteint | AR8: Head-Fi forum: 1; Head-Fi reviews: 1; Review éditoriale: 2
A9: Cayin | B9: RU7 | C9: Dongle DAC/amp R-2R/1-bit | D9: Fluide, organique, doux, spatial | E9: Profondeur naturelle, cohérence des timbres, image 3D | F9: Redondant avec le N7; moins incisif que DC-Elite | G9: 8.8 | H9: 9 | I9: 9.4 | J9: 9.5 | K9: 9.3 | L9: 9.7 | M9: 8.7 | N9: 7.8 | O9: 9.3 | P9: 8 | Q9: =IF(COUNT(G9:P9)=10,ROUND((G9*'Pondérations'!$B$5+H9*'Pondérations'!$B$6+I9*'Pondérations'!$B$7+J9*'Pondérations'!$B$8+K9*'Pondérations'!$B$9+L9*'Pondérations'!$B$10+M9*'Pondérations'!$B$11+N9*'Pondérations'!$B$12+O9*'Pondérations'!$B$13+P9*'Pondérations'!$B$14)/'Pondérations'!$B$16,3),"") | R9: =IF(Q9="","",1+COUNTIF($Q$7:$Q$178,">"&Q9)+COUNTIF($Q$7:Q9,Q9)-1) | V9: Élevée | W9: Discussion + Headfonics | X9: 8.6 | Y9: Reader | Z9: 45143 | AA9: 4 | AB9: https://headfonics.com/?s=Cayin+RU7 | AC9: 1-bit discrete resistor-network dongle DAC/amp | AD9: Déjà présent | AE9: 78 | AF9: 255 | AG9: Très musical et techniquement solide; restitution colorée de façon agréable, avec une excellente puissance et des modes DSD qui modifient réellement le rendu. | AH9: Organique, légèrement chaleureuse | AI9: Immersive et techniquement aboutie; bonne profondeur et cohérence spatiale | AJ9: Consommation/ergonomie dongle; câble Lightning non fourni | AK9: https://headfonics.com/cayin-ru7-review/ | AL9: 4 | AM9: Élevée — 3+ sources, domaines variés | AN9: https://www.head-fi.org/showcase/cayin-ru7.26493/reviews | AO9: https://iiwireviews.com/cayin-ru7-dac-review-fantastic-portable-sound/ | AP9: https://www.ecoustics.com/reviews/cayin-ru7-dongle-dac/ | AQ9: Objectif atteint | AR9: Head-Fi reviews: 1; Review éditoriale: 3
A10: Dethonray | B10: Clarinet | C10: DAC/amp portable sur batterie | D10: Naturel, doux, légèrement sombre, texturé | E10: Grande scène, layering, matière, douceur | F10: Moins neutre et moins incisif; microdétail un peu moins frontal | G10: 8.7 | H10: 8.7 | I10: 9.3 | J10: 9.2 | K10: 9.2 | L10: 9.6 | M10: 8.8 | N10: 8.8 | O10: 7.2 | P10: 8.8 | Q10: =IF(COUNT(G10:P10)=10,ROUND((G10*'Pondérations'!$B$5+H10*'Pondérations'!$B$6+I10*'Pondérations'!$B$7+J10*'Pondérations'!$B$8+K10*'Pondérations'!$B$9+L10*'Pondérations'!$B$10+M10*'Pondérations'!$B$11+N10*'Pondérations'!$B$12+O10*'Pondérations'!$B$13+P10*'Pondérations'!$B$14)/'Pondérations'!$B$16,3),"") | R10: =IF(Q10="","",1+COUNTIF($Q$7:$Q$178,">"&Q10)+COUNTIF($Q$7:Q10,Q10)-1) | V10: Moyenne | W10: Discussion initiale | AF10: 196 | AG10: Le Clarinet privilégie une restitution fluide, musicale et organique avec des médiums très naturels. Il conserve un bon niveau de microdétail malgré sa douceur. | AH10: Neutre-douce, légèrement chaude et organique | AI10: Scène large et ouverte, bonne profondeur et layering, fond noir; spatialisation plus enveloppante que démonstrative. | AJ10: Grave/mid-bass parfois un peu léger; extension d'aigu perfectible face aux meilleurs concurrents. | AK10: https://www.headfonia.com/dethonray-clarinet-review/ | AL10: 4 | AM10: Élevée — 3+ sources, domaines variés | AN10: https://www.head-fi.org/showcase/dethonray-clarinet.27782/reviews | AO10: https://www.audiophile-heaven.com/2025/04/the-canto-master-dethonray-clarinet-dac-headphone-amp.html | AP10: https://www.head-fi.org/threads/dethonray-clarinet-portable-dac-amp-discussion-impression-thread.975231/ | AQ10: Objectif atteint | AR10: Head-Fi forum: 1; Head-Fi reviews: 1; Review éditoriale: 2
A11: Moondrop | B11: Moonriver 3 | C11: Dongle DAC/amp | D11: Neutre, très ouvert, analytique sans être stérile | E11: Résolution, scène large/profonde, séparation | F11: Moins incarné/organique que N7 ou solutions hybrides | G11: 9.4 | H11: 9.3 | I11: 9.1 | J11: 9 | K11: 9.2 | L11: 8.6 | M11: 9.2 | N11: 8.8 | O11: 9 | P11: 9.1 | Q11: =IF(COUNT(G11:P11)=10,ROUND((G11*'Pondérations'!$B$5+H11*'Pondérations'!$B$6+I11*'Pondérations'!$B$7+J11*'Pondérations'!$B$8+K11*'Pondérations'!$B$9+L11*'Pondérations'!$B$10+M11*'Pondérations'!$B$11+N11*'Pondérations'!$B$12+O11*'Pondérations'!$B$13+P11*'Pondérations'!$B$14)/'Pondérations'!$B$16,3),"") | R11: =IF(Q11="","",1+COUNTIF($Q$7:$Q$178,">"&Q11)+COUNTIF($Q$7:Q11,Q11)-1) | V11: Élevée | W11: Discussion + Headfonics | X11: 8.7 | Y11: Award | Z11: 46144 | AA11: 1 | AB11: https://headfonics.com/?s=Moondrop+Moonriver+3 | AC11: Dual CS43198 dongle DAC, DSP, up to 500 mW | AD11: Déjà présent | AE11: 8 | AF11: 229 | AG11: Dongle très dynamique, détaillé et large, avec fond très silencieux et excellente polyvalence. | AH11: Neutre, ouvert et énergique. | AI11: Large scène, très bonne séparation et résolution. | AJ11: Pas de gain physique; plus lourd que la génération précédente. | AK11: https://headfonics.com/moondrop-moonriver-3-review/ | AL11: 3 | AM11: Élevée — 3+ sources, domaines variés | AN11: https://www.hifidaydreaming.com/post/the-future-of-portable-dac-amps-is-here-moondrop-moonriver-3-review | AO11: https://cj.sina.com.cn/articles/view/7879848900/1d5acf3c402702rlle?froms=ggmp | AQ11: Objectif atteint | AR11: Review éditoriale: 3
A12: ONIX | B12: Beta XI2 | C12: DAC/amp portable hybride | D12: Naturel, légèrement chaleureux; tubes plus organiques | E12: Corps, profondeur, double signature | F12: Moins transparent/raffiné que N7; plus encombrant | G12: 8.9 | H12: 8.8 | I12: 9.1 | J12: 9.2 | K12: 9 | L12: 9.5 | M12: 8.8 | N12: 9 | O12: 6.8 | P12: 9 | Q12: =IF(COUNT(G12:P12)=10,ROUND((G12*'Pondérations'!$B$5+H12*'Pondérations'!$B$6+I12*'Pondérations'!$B$7+J12*'Pondérations'!$B$8+K12*'Pondérations'!$B$9+L12*'Pondérations'!$B$10+M12*'Pondérations'!$B$11+N12*'Pondérations'!$B$12+O12*'Pondérations'!$B$13+P12*'Pondérations'!$B$14)/'Pondérations'!$B$16,3),"") | R12: =IF(Q12="","",1+COUNTIF($Q$7:$Q$178,">"&Q12)+COUNTIF($Q$7:Q12,Q12)-1) | V12: Moyenne | W12: Discussion + Headfonics | X12: 8.5 | Y12: Reader | Z12: 45987 | AA12: 1 | AB12: https://headfonics.com/?s=ONIX+Beta+XI2 | AC12: Hybrid solid-state/JAN6418 tube dongle DAC | AD12: Déjà présent | AE12: 16 | AF12: 349 | AG12: Deux signatures utiles : transistor propre et défini, tube plus doux et chaleureux, avec un très faible bruit de fond. | AH12: Naturel; transistor analytique, tube chaleureux. | AI12: Bon layering et placement 3D, largeur supérieure en transistor; profondeur seulement correcte. | AJ12: Accessoires basiques; profondeur pas au niveau des sources haut de gamme. | AK12: https://headfonics.com/onix-beta-xi2-review/ | AL12: 4 | AM12: Élevée — 3+ sources, domaines variés | AN12: https://www.headfonia.com/onix-beta-xi2-review/ | AO12: https://www.audiophile-heaven.com/2025/11/shanling-onix-beta-xi2-tube-usb-dongle-dac-amp-review-dual-dacs-dual-tubes-dual-fun.html | AP12: https://www.ecoustics.com/reviews/onix-beta-xi2/ | AQ12: Objectif atteint | AR12: Review éditoriale: 4
A13: MUSE HiFi | B13: M6 Double | C13: DAC/amp portable hybride | D13: Spacieux, immersif, tubes plus charnels | E13: Effet 3D, profondeur, immersion, choix tube/transistor | F13: Plus coloré, retours indépendants encore limités | G13: 8.8 | H13: 8.9 | I13: 8.9 | J13: 9 | K13: 9.2 | L13: 9.2 | M13: 9 | N13: 8.2 | O13: 6.5 | P13: 8.9 | Q13: =IF(COUNT(G13:P13)=10,ROUND((G13*'Pondérations'!$B$5+H13*'Pondérations'!$B$6+I13*'Pondérations'!$B$7+J13*'Pondérations'!$B$8+K13*'Pondérations'!$B$9+L13*'Pondérations'!$B$10+M13*'Pondérations'!$B$11+N13*'Pondérations'!$B$12+O13*'Pondérations'!$B$13+P13*'Pondérations'!$B$14)/'Pondérations'!$B$16,3),"") | R13: =IF(Q13="","",1+COUNTIF($Q$7:$Q$178,">"&Q13)+COUNTIF($Q$7:Q13,Q13)-1) | V13: Moyenne | W13: Discussion + Headfonics | X13: 8.6 | Y13: Reader | Z13: 45958 | AA13: 1 | AB13: https://headfonics.com/?s=MUSE+HiFi+M6+Double | AC13: Dual-mode transistor/JAN6418 tube portable DAC/amp | AD13: Déjà présent | AE13: 19 | AF13: 449 | AG13: Hybride très doux et musical, encore plus soyeux en mode tube, avec une bonne capacité à alimenter des casques. | AH13: Doux; tube plus lisse que transistor. | AI13: Immersif et agréable, mais la review met plus en avant le caractère que la résolution brute. | AJ13: Puissance pas exceptionnelle vu le gabarit. | AK13: https://headfonics.com/muse-hifi-m6-double-review/ | AL13: 4 | AM13: Élevée — 3+ sources, domaines variés | AN13: https://www.headfonia.com/muse-hifi-m6-double-review/ | AO13: https://www.uni-sonia.com/musehifi-m6-double/ | AP13: https://note.com/sekixyo/n/n1a59c57ce107 | AQ13: Objectif atteint | AR13: Review éditoriale: 4
A14: Questyle | B14: M15i | C14: Dongle DAC/amp | D14: Propre, doux, légèrement charnu, très spatial | E14: Image stable, profondeur naturelle, format compact | F14: Puissance plus limitée avec casques gourmands | G14: 9.3 | H14: 9.1 | I14: 9.1 | J14: 9.2 | K14: 9 | L14: 9 | M14: 8.8 | N14: 6.8 | O14: 9.6 | P14: 9 | Q14: =IF(COUNT(G14:P14)=10,ROUND((G14*'Pondérations'!$B$5+H14*'Pondérations'!$B$6+I14*'Pondérations'!$B$7+J14*'Pondérations'!$B$8+K14*'Pondérations'!$B$9+L14*'Pondérations'!$B$10+M14*'Pondérations'!$B$11+N14*'Pondérations'!$B$12+O14*'Pondérations'!$B$13+P14*'Pondérations'!$B$14)/'Pondérations'!$B$16,3),"") | R14: =IF(Q14="","",1+COUNTIF($Q$7:$Q$178,">"&Q14)+COUNTIF($Q$7:Q14,Q14)-1) | V14: Élevée | W14: Discussion initiale | AF14: 259 | AG14: Le M15i combine une signature neutre avec une légère énergie en V et une amplification très rapide. Les retours insistent sur sa résolution, sa dynamique et son image spatiale. | AH14: Neutre, légèrement vive/énergique | AI14: Imagerie et layering très précis, bonne expansion avant-arrière; sortie 4,4 mm nettement plus convaincante que la 3,5 mm. | AJ14: Peut devenir un peu brillant ou métallique avec des transducteurs déjà lumineux; puissance limitée pour certains casques. | AK14: https://www.audiodiscourse.com/2024/06/questyle-m15i-portable-dacamp-review.html | AL14: 5 | AM14: Élevée — 3+ sources, domaines variés | AN14: https://majorhifi.com/questyle-m15i-review/ | AO14: https://www.head-fi.org/showcase/questyle-m15i-%E2%80%94-mobile-headphone-amp-dac.27064/reviews | AP14: https://www.head-fi.org/threads/questyle-m12i-m15i-usb-dac-review-the-charm-of-current-mode-amplification.974037/ | AQ14: Objectif atteint | AR14: Head-Fi forum: 1; Head-Fi reviews: 1; Review éditoriale: 3
A15: Shanling | B15: UA7 | C15: Dongle DAC/amp hybride | D15: Propre, légèrement chaleureux; tube plus organique | E15: Profondeur modulable, puissance, polyvalence | F15: Moins résolvant que DC-Elite; plus coloré selon mode | G15: 9 | H15: 8.8 | I15: 8.9 | J15: 9 | K15: 8.9 | L15: 9.2 | M15: 8.8 | N15: 9 | O15: 8.5 | P15: 8.6 | Q15: =IF(COUNT(G15:P15)=10,ROUND((G15*'Pondérations'!$B$5+H15*'Pondérations'!$B$6+I15*'Pondérations'!$B$7+J15*'Pondérations'!$B$8+K15*'Pondérations'!$B$9+L15*'Pondérations'!$B$10+M15*'Pondérations'!$B$11+N15*'Pondérations'!$B$12+O15*'Pondérations'!$B$13+P15*'Pondérations'!$B$14)/'Pondérations'!$B$16,3),"") | R15: =IF(Q15="","",1+COUNTIF($Q$7:$Q$178,">"&Q15)+COUNTIF($Q$7:Q15,Q15)-1) | V15: Moyenne à élevée | W15: Discussion + Headfonics | X15: 8.6 | Y15: Award | Z15: 46050 | AA15: 1 | AB15: https://headfonics.com/?s=Shanling+UA7 | AC15: Dual JAN6418 tube dongle DAC, up to 577 mW | AD15: Déjà présent | AE15: 12 | AF15: 269 | AG15: Mélange réussi de propreté transistor et d’une légère richesse tube, sans coloration excessive. | AH15: Neutre-propre avec chaleur subtile en mode tube. | AI15: Dynamique forte, détail élevé et bonne aptitude aux casques. | AJ15: Tubes exposés et châssis anguleux. | AK15: https://headfonics.com/shanling-ua7-review/ | AL15: 4 | AM15: Élevée — 3+ sources, domaines variés | AN15: https://www.headfonia.com/shanling-ua7-review/ | AO15: https://mobileaudiophile.com/dacs/dongle/shanling-ua7-review/ | AP15: https://ichos-reviews.com/shanling-ua7-review/ | AQ15: Objectif atteint | AR15: Review éditoriale: 4
A16: iBasso | B16: DC07PRO | C16: Dongle DAC/amp | D16: Transparent, légèrement chaleureux, équilibré | E16: Valeur sûre, fond noir, largeur et placement | F16: Profondeur/holographie derrière DC-Elite | G16: 9.4 | H16: 9.1 | I16: 8.7 | J16: 8.6 | K16: 8.9 | L16: 8.9 | M16: 9 | N16: 8.7 | O16: 9.5 | P16: 8.7 | Q16: =IF(COUNT(G16:P16)=10,ROUND((G16*'Pondérations'!$B$5+H16*'Pondérations'!$B$6+I16*'Pondérations'!$B$7+J16*'Pondérations'!$B$8+K16*'Pondérations'!$B$9+L16*'Pondérations'!$B$10+M16*'Pondérations'!$B$11+N16*'Pondérations'!$B$12+O16*'Pondérations'!$B$13+P16*'Pondérations'!$B$14)/'Pondérations'!$B$16,3),"") | R16: =IF(Q16="","",1+COUNTIF($Q$7:$Q$178,">"&Q16)+COUNTIF($Q$7:Q16,Q16)-1) | V16: Élevée | W16: Discussion initiale | AF16: 189 | AG16: Le DC07PRO est jugé très neutre et propre, avec un grave rapide, un aigu aérien et une excellente résolution. Il reste légèrement plus doux que les dongles les plus incisifs. | AH16: Neutre, propre, légèrement douce | AI16: Scène large et raisonnablement profonde, excellente séparation et placement; profondeur un cran sous les meilleures sources haut de gamme. | AJ16: Layering avant-arrière pas tout à fait holographique; moins texturé et volumique que le DC-Elite. | AK16: https://www.headfonia.com/ibasso-dc07pro-review/2/ | AL16: 4 | AM16: Élevée — 3+ sources, domaines variés | AN16: https://www.head-fi.org/showcase/ibasso-dc07-pro.27359/reviews | AO16: https://moonstarreviews.net/ibasso-dc07-pro-review/ | AP16: https://androidbrick.com/ibasso-dc07pro-review/ | AQ16: Objectif atteint | AR16: Head-Fi reviews: 1; Review éditoriale: 3
A17: Shanling | B17: UA6 II | C17: Dongle DAC/amp | D17: Très propre, précis, neutre, légèrement chaleureux | E17: Fond noir, séparation, résolution, transitoires | F17: Profondeur bonne mais pas clairement holographique | G17: 9.5 | H17: 9.2 | I17: 8.6 | J17: 8.5 | K17: 9.1 | L17: 8.7 | M17: 9 | N17: 8.1 | O17: 9.5 | P17: 8.6 | Q17: =IF(COUNT(G17:P17)=10,ROUND((G17*'Pondérations'!$B$5+H17*'Pondérations'!$B$6+I17*'Pondérations'!$B$7+J17*'Pondérations'!$B$8+K17*'Pondérations'!$B$9+L17*'Pondérations'!$B$10+M17*'Pondérations'!$B$11+N17*'Pondérations'!$B$12+O17*'Pondérations'!$B$13+P17*'Pondérations'!$B$14)/'Pondérations'!$B$16,3),"") | R17: =IF(Q17="","",1+COUNTIF($Q$7:$Q$178,">"&Q17)+COUNTIF($Q$7:Q17,Q17)-1) | V17: Moyenne | W17: Discussion initiale | AF17: 219 | AG17: Le UA6 II est décrit comme très propre, contrôlé et résolvant, avec un fond noir et une légère chaleur. Son mode 8 DAC privilégie surtout ouverture et transparence. | AH17: Neutre à légèrement chaude, rapide | AI17: Bonne largeur, séparation et lecture des couches; la profondeur est correcte mais les reviews ne le décrivent pas comme franchement holographique. | AJ17: Bas-médium plutôt mince et aigu pouvant mordre avec des associations lumineuses; peu de reviews indépendantes disponibles. | AK17: https://mobileaudiophile.com/dacs/dongle/shanling-ua6-ii-review/ | AL17: 3 | AM17: Élevée — 3+ sources, domaines variés | AN17: https://hearit-hk.com/en/shanling-ua6-ii-8-cs43131-dac-2/ | AO17: https://www.notebookcheck.net/Shanling-UA6-II-portable-USB-DAC-launches-with-4-4mm-balanced-output-8-high-fidelity-DACs-and-DSD-Hi-Res-Audio.1333153.0.html | AQ17: Objectif atteint | AR17: Communauté Reddit: 1; Head-Fi reviews: 1; Review éditoriale: 1
A18: ONIX | B18: Alpha XI1 | C18: Dongle DAC/amp | D18: Musical, texturé, assez ouvert | E18: Rapport qualité/prix, puissance, matière | F18: Avis contradictoires sur profondeur/scène | G18: 9 | H18: 8.8 | I18: 8.5 | J18: 8.5 | K18: 8.6 | L18: 9 | M18: 8.9 | N18: 8.8 | O18: 9.4 | P18: 8.4 | Q18: =IF(COUNT(G18:P18)=10,ROUND((G18*'Pondérations'!$B$5+H18*'Pondérations'!$B$6+I18*'Pondérations'!$B$7+J18*'Pondérations'!$B$8+K18*'Pondérations'!$B$9+L18*'Pondérations'!$B$10+M18*'Pondérations'!$B$11+N18*'Pondérations'!$B$12+O18*'Pondérations'!$B$13+P18*'Pondérations'!$B$14)/'Pondérations'!$B$16,3),"") | R18: =IF(Q18="","",1+COUNTIF($Q$7:$Q$178,">"&Q18)+COUNTIF($Q$7:Q18,Q18)-1) | V18: Moyenne | W18: Discussion + Headfonics | X18: 7.9 | Y18: Reader | Z18: 45593 | AA18: 3 | AB18: https://headfonics.com/?s=ONIX+Alpha+XI1 | AC18: Dual CS43198 dongle DAC, up to 500 mW | AD18: Déjà présent | AE18: 45 | AF18: 109 | AG18: Très bon rapport qualité/prix, puissant et jugé parmi les meilleurs dongles autour de 200 $. | AH18: Plutôt neutre/équilibré. | AI18: Bonne qualité sonore globale et bonne réserve de puissance. | AJ18: Format assez volumineux; low gain encore relativement fort. | AK18: https://headfonics.com/onix-alpha-xi1-review/ | AL18: 4 | AM18: Élevée — 3+ sources, domaines variés | AN18: https://www.headfonia.com/onix-alpha-xi1-review/ | AO18: https://www.audiophile-heaven.com/2024/07/shanling-onix-alpha-xi1-bold-sound-good-function-dac-amp.html | AP18: https://www.reddit.com/r/headphones/comments/1dnbl2j | AQ18: Objectif atteint | AR18: Communauté Reddit: 1; Review éditoriale: 3
A19: xDuoo | B19: XD05 BAL 2 | C19: DAC/amp portable sur batterie | D19: Charnu, doux, puissant, plutôt sombre | E19: Puissance, matière, évolutivité par AOP | F19: Encombrant; moins incisif et moins micro-résolvant | G19: 8.6 | H19: 8.5 | I19: 8.7 | J19: 8.4 | K19: 8.8 | L19: 9.2 | M19: 9.2 | N19: 10 | O19: 5.5 | P19: 8.2 | Q19: =IF(COUNT(G19:P19)=10,ROUND((G19*'Pondérations'!$B$5+H19*'Pondérations'!$B$6+I19*'Pondérations'!$B$7+J19*'Pondérations'!$B$8+K19*'Pondérations'!$B$9+L19*'Pondérations'!$B$10+M19*'Pondérations'!$B$11+N19*'Pondérations'!$B$12+O19*'Pondérations'!$B$13+P19*'Pondérations'!$B$14)/'Pondérations'!$B$16,3),"") | R19: =IF(Q19="","",1+COUNTIF($Q$7:$Q$178,">"&Q19)+COUNTIF($Q$7:Q19,Q19)-1) | V19: Élevée | W19: Discussion + Headfonics | X19: 8 | Y19: Reader | Z19: 45184 | AA19: 4 | AB19: https://headfonics.com/?s=xDuoo+XD05+BAL+2 | AC19: High-power battery portable DAC/amp | AD19: Déjà présent | AE19: 76 | AF19: 429 | AG19: Portable très puissant, riche en ton et en texture, avec un grave convaincant et une restitution plutôt douce. | AH19: Charnue, douce, plutôt sombre | AI19: Bonne ampleur et dynamique, davantage axée matière que lumière dans le haut | AJ19: Aigu parfois trop lisse; médium un peu en retrait; encombrant | AK19: https://headfonics.com/xduoo-xd05-bal-2-review/ | AL19: 3 | AM19: Élevée — 3+ sources, domaines variés | AN19: https://www.arkaudio.se/en/headphones/headphones/xduoo-xd05-bal2-portable-dac-tube-headphone-amplifier.html | AO19: https://uk.testseek.com/home-electronics/hifi/dac/xduoo-xd05-bal-2-p-d129f994-2837-8d55-1622-1ce104837e79.html | AQ19: Objectif atteint | AR19: Review éditoriale: 3
A20: Dethonray | B20: Pegasus SG1 | C20: Récepteur Bluetooth DAC/amp | D20: Charnu, énergique, grave présent, aigu calme | E20: Grande scène, impact, relief en Bluetooth | F20: Bluetooth uniquement; coloré; souffle possible IEM sensibles | G20: 8.2 | H20: 8.1 | I20: 9 | J20: 8.9 | K20: 8.7 | L20: 9.4 | M20: 9 | N20: 8.7 | O20: 7.5 | P20: 7.8 | Q20: =IF(COUNT(G20:P20)=10,ROUND((G20*'Pondérations'!$B$5+H20*'Pondérations'!$B$6+I20*'Pondérations'!$B$7+J20*'Pondérations'!$B$8+K20*'Pondérations'!$B$9+L20*'Pondérations'!$B$10+M20*'Pondérations'!$B$11+N20*'Pondérations'!$B$12+O20*'Pondérations'!$B$13+P20*'Pondérations'!$B$14)/'Pondérations'!$B$16,3),"") | R20: =IF(Q20="","",1+COUNTIF($Q$7:$Q$178,">"&Q20)+COUNTIF($Q$7:Q20,Q20)-1) | V20: Moyenne | W20: Discussion initiale | AF20: 351 | AG20: Le Pegasus SG1 vise une écoute naturelle et musicale, légèrement chaude, avec des médiums séduisants. Sa restitution est davantage charnelle que strictement analytique. | AH20: Neutre-chaude, douce et musicale | AI20: Bonne profondeur et bon layering mais largeur plus modérée; séparation correcte et présentation cohérente. | AJ20: Grave pas toujours très texturé/impactant; Bluetooth uniquement et léger bruit possible avec IEM très sensibles. | AK20: https://www.headfonia.com/dethonray-pegasus-sg1-review/2/ | AL20: 3 | AM20: Élevée — 3+ sources, domaines variés | AN20: https://www.head-fi.org/showcase/dethonray-pegasus-sg1.26154/ | AO20: https://www.headphonesty.com/2020/12/best-portable-dac-amp-combo/ | AQ20: Objectif atteint | AR20: Head-Fi reviews: 1; Review éditoriale: 2
A21: Shanling | B21: H5 MQA | C21: DAC/amp portable sur batterie | D21: Chaud, fluide, grave généreux | E21: Puissance, autonomie, fonctions, lecture microSD | F21: Moins précis/spatial; impédance sortie à surveiller avec IEM | G21: 8.4 | H21: 8.3 | I21: 8.6 | J21: 8.5 | K21: 8.5 | L21: 9.2 | M21: 8.7 | N21: 9.5 | O21: 6.5 | P21: 8 | Q21: =IF(COUNT(G21:P21)=10,ROUND((G21*'Pondérations'!$B$5+H21*'Pondérations'!$B$6+I21*'Pondérations'!$B$7+J21*'Pondérations'!$B$8+K21*'Pondérations'!$B$9+L21*'Pondérations'!$B$10+M21*'Pondérations'!$B$11+N21*'Pondérations'!$B$12+O21*'Pondérations'!$B$13+P21*'Pondérations'!$B$14)/'Pondérations'!$B$16,3),"") | R21: =IF(Q21="","",1+COUNTIF($Q$7:$Q$178,">"&Q21)+COUNTIF($Q$7:Q21,Q21)-1) | V21: Moyenne | W21: Discussion + Headfonics | X21: 8.3 | Y21: Reader | Z21: 45185 | AA21: 4 | AB21: https://headfonics.com/?s=Shanling+H5 | AC21: Battery portable DAC/amp | AD21: Déjà présent | AE21: 75 | AF21: 325 | AG21: DAC/amp polyvalent au son expressif, doux et puissant; restitution plaisante plus orientée musicalité que neutralité stricte. | AH21: Douce, chaleureuse, expressive | AI21: Bonne ampleur et puissance; présentation fluide plutôt que très analytique | AJ21: Impédance de sortie élevée, attention aux IEM sensibles | AK21: https://headfonics.com/shanling-h5-review/ | AL21: 3 | AM21: Élevée — 3+ sources, domaines variés | AN21: https://www.headfonia.com/shanling-h5-review/ | AO21: https://fr.testseek.com/electromenager/hifi/dac/shanling-h5-p-20b8dfcf-3635-15fc-9b6d-5aaade081297.html | AQ21: Objectif atteint | AR21: Review éditoriale: 3
A22: xDuoo | B22: POKE II | C22: DAC/amp portable sur batterie | D22: Équilibré, bonne scène, plutôt polyvalent | E22: Profondeur/hauteur correctes, puissance, fonctions | F22: Génération plus ancienne; moins raffiné que MUB1/DC-Elite | G22: 8.5 | H22: 8.4 | I22: 8.7 | J22: 8.6 | K22: 8.6 | L22: 8.7 | M22: 8.6 | N22: 9 | O22: 6.8 | P22: 8 | Q22: =IF(COUNT(G22:P22)=10,ROUND((G22*'Pondérations'!$B$5+H22*'Pondérations'!$B$6+I22*'Pondérations'!$B$7+J22*'Pondérations'!$B$8+K22*'Pondérations'!$B$9+L22*'Pondérations'!$B$10+M22*'Pondérations'!$B$11+N22*'Pondérations'!$B$12+O22*'Pondérations'!$B$13+P22*'Pondérations'!$B$14)/'Pondérations'!$B$16,3),"") | R22: =IF(Q22="","",1+COUNTIF($Q$7:$Q$178,">"&Q22)+COUNTIF($Q$7:Q22,Q22)-1) | V22: Moyenne | W22: Discussion + Headfonics | X22: 8.3 | Y22: Reader | Z22: 44769 | AA22: 5 | AB22: https://headfonics.com/?s=xDuoo+POKE+II | AC22: Battery portable DAC/amp | AD22: Déjà présent | AE22: 100 | AF22: 343 | AG22: Son propre et peu coloré avec beaucoup de puissance; bon sur la dynamique et assez tolérant avec les enregistrements moyens. | AH22: Neutre, propre | AI22: Bonne dynamique et polyvalence; spatialisation correcte sans accent marqué sur le relief | AJ22: Bluetooth de portée moyenne; entrées limitées USB/BT | AK22: https://headfonics.com/xduoo-poke-ii-review/ | AL22: 3 | AM22: Élevée — 3+ sources, domaines variés | AN22: https://www.head-fi.org/showcase/xduoo-poke-ii.25877/reviews | AO22: https://www.headfonia.com/xduoo-poke-ii-review/ | AQ22: Objectif atteint | AR22: Head-Fi reviews: 1; Review éditoriale: 2
A23: FiiO | B23: BTR17 | C23: Bluetooth DAC/amp | D23: Neutre, rapide, propre, fonctionnel | E23: Bluetooth, PEQ, puissance, polyvalence | F23: Spatialité/profondeur moins organiques; assez proche du L70 | G23: 9.3 | H23: 8.9 | I23: 8.3 | J23: 8.2 | K23: 8.7 | L23: 8.5 | M23: 9 | N23: 9.2 | O23: 9.8 | P23: 7.8 | Q23: =IF(COUNT(G23:P23)=10,ROUND((G23*'Pondérations'!$B$5+H23*'Pondérations'!$B$6+I23*'Pondérations'!$B$7+J23*'Pondérations'!$B$8+K23*'Pondérations'!$B$9+L23*'Pondérations'!$B$10+M23*'Pondérations'!$B$11+N23*'Pondérations'!$B$12+O23*'Pondérations'!$B$13+P23*'Pondérations'!$B$14)/'Pondérations'!$B$16,3),"") | R23: =IF(Q23="","",1+COUNTIF($Q$7:$Q$178,">"&Q23)+COUNTIF($Q$7:Q23,Q23)-1) | V23: Élevée | W23: Discussion initiale | AF23: 199 | AG23: Le BTR17 est apprécié pour son équilibre neutre, vif et très propre. En USB il offre une restitution crisp, dynamique et détaillée avec beaucoup de polyvalence. | AH23: Neutre, vive, légèrement sèche | AI23: Scène large et haute, transitoires rapides et bonne séparation; l'USB conserve davantage de microdétails que le Bluetooth. | AJ23: Bluetooth réduit un peu la finesse et l'extension; le grave peut manquer de matière pour qui cherche une présentation organique. | AK23: https://headfonics.com/fiio-btr17-review/ | AL23: 4 | AM23: Élevée — 3+ sources, domaines variés | AN23: https://www.head-fi.org/showcase/fiio-btr17.28043/reviews | AO23: https://www.techradar.com/audio/hi-fi/fiio-btr17-review | AP23: https://mobileaudiophile.com/dacs/dongle/fiio-btr17-review/ | AQ23: Objectif atteint | AR23: Head-Fi reviews: 1; Review éditoriale: 3
A24: FiiO | B24: QX13 | C24: Dongle DAC/amp | D24: Très propre, détaillé, énergique | E24: Puissance, fonctions, PEQ, résolution | F24: Peut rester trop “technique” / proche du L70 | G24: 9.5 | H24: 9.2 | I24: 8.4 | J24: 8.3 | K24: 8.9 | L24: 8.4 | M24: 9.4 | N24: 9.7 | O24: 9.2 | P24: 7.7 | Q24: =IF(COUNT(G24:P24)=10,ROUND((G24*'Pondérations'!$B$5+H24*'Pondérations'!$B$6+I24*'Pondérations'!$B$7+J24*'Pondérations'!$B$8+K24*'Pondérations'!$B$9+L24*'Pondérations'!$B$10+M24*'Pondérations'!$B$11+N24*'Pondérations'!$B$12+O24*'Pondérations'!$B$13+P24*'Pondérations'!$B$14)/'Pondérations'!$B$16,3),"") | R24: =IF(Q24="","",1+COUNTIF($Q$7:$Q$178,">"&Q24)+COUNTIF($Q$7:Q24,Q24)-1) | V24: Moyenne à élevée | W24: Discussion + Headfonics | X24: 8.5 | Y24: Reader | Z24: 45892 | AA24: 2 | AB24: https://headfonics.com/?s=FiiO+QX13 | AC24: ES9027SPRO high-end dongle DAC with color display | AD24: Déjà présent | AE24: 25 | AF24: 199 | AG24: Dongle de niveau presque desktop, très puissant, détaillé et ambitieux, avec une forte sensation de présence. | AH24: Clair, vivant, médiums présents. | AI24: Très bon layering, beaucoup de nuances et excellente puissance. | AJ24: Puissance maximale exige une seconde alimentation; consommation importante. | AK24: https://headfonics.com/fiio-qx13-review/ | AL24: 4 | AM24: Élevée — 3+ sources, domaines variés | AN24: https://www.headfonia.com/fiio-qx13-review/ | AO24: https://mobileaudiophile.com/dacs/dongle/fiio-qx13-review-when-portable-audio-grows-up/ | AP24: https://primeaudio.org/fiio-qx13-review/ | AQ24: Objectif atteint | AR24: Review éditoriale: 4
A25: SMSL | B25: DS20 | C25: DAC/amp portable | D25: Propre, large, résolvant | E25: Largeur, puissance, netteté | F25: Scène plus large que profonde; layering avant/arrière moyen | G25: 9.4 | H25: 9.1 | I25: 8 | J25: 7.8 | K25: 8.2 | L25: 8.4 | M25: 9.1 | N25: 9.2 | O25: 8.3 | P25: 7.2 | Q25: =IF(COUNT(G25:P25)=10,ROUND((G25*'Pondérations'!$B$5+H25*'Pondérations'!$B$6+I25*'Pondérations'!$B$7+J25*'Pondérations'!$B$8+K25*'Pondérations'!$B$9+L25*'Pondérations'!$B$10+M25*'Pondérations'!$B$11+N25*'Pondérations'!$B$12+O25*'Pondérations'!$B$13+P25*'Pondérations'!$B$14)/'Pondérations'!$B$16,3),"") | R25: =IF(Q25="","",1+COUNTIF($Q$7:$Q$178,">"&Q25)+COUNTIF($Q$7:Q25,Q25)-1) | V25: Moyenne | W25: Discussion + Headfonics | X25: 8.3 | Y25: Reader | Z25: 45899 | AA25: 2 | AB25: https://headfonics.com/?s=SMSL+DS20 | AC25: Quad CS43131 portable DAC/amp, up to 500 mW | AD25: Déjà présent | AE25: 24 | AF25: 199 | AG25: Portable énergique, avec grave rapide et très bien contrôlé, médiums clairs et bonne dynamique. | AH25: Grave énergique, médiums neutres. | AI25: Bonne dynamique et définition; moins axé douceur. | AJ25: Aigu pas toujours très lisse. | AK25: https://headfonics.com/smsl-ds20-review/ | AL25: 3 | AM25: Élevée — 3+ sources, domaines variés | AN25: https://primeaudio.org/smsl-ds20-review/ | AO25: https://headphonesandcoffee.home.blog/2025/09/22/smsl-ds20/ | AQ25: Objectif atteint | AR25: Review éditoriale: 3
A26: MUSE HiFi | B26: M5 Ultra | C26: DAC/amp portable hybride | D26: Doux, charnu, tubes plus profonds | E26: Corps médium, profondeur, caractère tubes | F26: Sous-grave/impédance/microdétail peuvent varier selon charge | G26: 8.5 | H26: 8.4 | I26: 8.8 | J26: 8.9 | K26: 8.7 | L26: 9.3 | M26: 8.6 | N26: 8.6 | O26: 7 | P26: 8 | Q26: =IF(COUNT(G26:P26)=10,ROUND((G26*'Pondérations'!$B$5+H26*'Pondérations'!$B$6+I26*'Pondérations'!$B$7+J26*'Pondérations'!$B$8+K26*'Pondérations'!$B$9+L26*'Pondérations'!$B$10+M26*'Pondérations'!$B$11+N26*'Pondérations'!$B$12+O26*'Pondérations'!$B$13+P26*'Pondérations'!$B$14)/'Pondérations'!$B$16,3),"") | R26: =IF(Q26="","",1+COUNTIF($Q$7:$Q$178,">"&Q26)+COUNTIF($Q$7:Q26,Q26)-1) | V26: Moyenne | W26: Discussion + Headfonics | X26: 8.1 | Y26: Reader | Z26: 45800 | AA26: 2 | AB26: https://headfonics.com/?s=MUSE+HiFi+M5+Ultra | AC26: Bluetooth ES9038Q2M tube/solid-state portable DAC/amp | AD26: Déjà présent | AE26: 32 | AF26: 269 | AG26: Très bon rendu dans les deux modes, avec une restitution tube naturelle et vivante et un transistor également convaincant. | AH26: Naturel; tube plus chaleureux. | AI26: Bonne transparence et silence de fond. | AJ26: Construction/commandes légèrement perfectibles. | AK26: https://headfonics.com/muse-hifi-m5-ultra-review/ | AL26: 4 | AM26: Élevée — 3+ sources, domaines variés | AN26: https://www.head-fi.org/showcase/muse-hifi-m5-ultra.28169/reviews | AO26: https://www.headfonia.com/muse-hifi-m5-ultra-review/ | AP26: https://primeaudio.org/muse-hifi-m5-ultra-review/ | AQ26: Objectif atteint | AR26: Head-Fi reviews: 1; Review éditoriale: 3
A27: Topping | B27: G5 | C27: DAC/amp portable sur batterie | D27: Très neutre, très propre, très contrôlé | E27: Mesures, puissance, fond noir | F27: Redondant avec L70; peu de gain en holographie | G27: 9.8 | H27: 9 | I27: 8 | J27: 7.8 | K27: 8.5 | L27: 8.2 | M27: 9.3 | N27: 9.8 | O27: 6.5 | P27: 6.8 | Q27: =IF(COUNT(G27:P27)=10,ROUND((G27*'Pondérations'!$B$5+H27*'Pondérations'!$B$6+I27*'Pondérations'!$B$7+J27*'Pondérations'!$B$8+K27*'Pondérations'!$B$9+L27*'Pondérations'!$B$10+M27*'Pondérations'!$B$11+N27*'Pondérations'!$B$12+O27*'Pondérations'!$B$13+P27*'Pondérations'!$B$14)/'Pondérations'!$B$16,3),"") | R27: =IF(Q27="","",1+COUNTIF($Q$7:$Q$178,">"&Q27)+COUNTIF($Q$7:Q27,Q27)-1) | V27: Élevée | W27: Discussion initiale | AF27: 299 | AG27: Le G5 propose un rendu très propre, dynamique et précis, avec un aigu net et une bonne résolution. Il privilégie la transparence plutôt que la coloration. | AH27: Neutre, propre, dynamique | AI27: Scène aérée et spacieuse avec placement précis, bonne largeur et profondeur; fond sombre. | AJ27: Caractère plutôt technique et peu coloré; ne constitue pas le meilleur choix si l'objectif est d'ajouter matière ou chaleur. | AK27: https://moonstarreviews.net/topping-g5-portable-dac-amplifier-review/ | AL27: 3 | AM27: Élevée — 3+ sources, domaines variés | AN27: https://www.head-fi.org/showcase/topping-g5.26030/reviews | AO27: https://iegems.nk-tran.com/2022/12/16/review-Topping-G5.html | AQ27: Objectif atteint | AR27: Head-Fi reviews: 1; Review éditoriale: 2
A28: Shanling | B28: UA6 | C28: Dongle DAC/amp | D28: Transparent, spacieux, légèrement chaleureux | E28: Scène, transparence, douceur | F28: UA6 II plus abouti; moins de recul dans notre comparaison | G28: 9.1 | H28: 8.8 | I28: 8.6 | J28: 8.7 | K28: 8.7 | L28: 9 | M28: 8.8 | N28: 8.5 | O28: 9.5 | P28: 8.2 | Q28: =IF(COUNT(G28:P28)=10,ROUND((G28*'Pondérations'!$B$5+H28*'Pondérations'!$B$6+I28*'Pondérations'!$B$7+J28*'Pondérations'!$B$8+K28*'Pondérations'!$B$9+L28*'Pondérations'!$B$10+M28*'Pondérations'!$B$11+N28*'Pondérations'!$B$12+O28*'Pondérations'!$B$13+P28*'Pondérations'!$B$14)/'Pondérations'!$B$16,3),"") | R28: =IF(Q28="","",1+COUNTIF($Q$7:$Q$178,">"&Q28)+COUNTIF($Q$7:Q28,Q28)-1) | V28: Moyenne | W28: Discussion initiale | AF28: 179 | AG28: Le UA6 original est un dongle très propre et détaillé, avec une restitution neutre et un bruit de fond très faible. Il met l'accent sur la lisibilité et l'organisation. | AH28: Neutre, propre, légèrement maigre selon les associations | AI28: Scène large avec profondeur/hauteur convaincantes, imagerie précise et bonne séparation. | AJ28: Peut paraître un peu lean ou peu charnu; la synergie avec des casques/IEM déjà clairs est importante. | AK28: https://headfonics.com/shanling-ua6-review/ | AL28: 4 | AM28: Élevée — 3+ sources, domaines variés | AN28: https://www.head-fi.org/showcase/shanling-ua6.28189/reviews | AO28: https://www.headfonia.com/shanling-ua6-review/ | AP28: https://primeaudio.org/shanling-ua6-review/ | AQ28: Objectif atteint | AR28: Head-Fi reviews: 1; Review éditoriale: 3
A29: Questyle | B29: M15C | C29: Dongle DAC/amp | D29: Propre, fluide, légèrement chaleureux | E29: Image stable, compacité, musicalité Questyle | F29: Moins ambitieux/puissant que M15i | G29: 9.1 | H29: 8.8 | I29: 8.8 | J29: 8.9 | K29: 8.8 | L29: 8.4 | M29: 8.7 | N29: 8.5 | O29: 8 | P29: 8.5 | Q29: =IF(COUNT(G29:P29)=10,ROUND((G29*'Pondérations'!$B$5+H29*'Pondérations'!$B$6+I29*'Pondérations'!$B$7+J29*'Pondérations'!$B$8+K29*'Pondérations'!$B$9+L29*'Pondérations'!$B$10+M29*'Pondérations'!$B$11+N29*'Pondérations'!$B$12+O29*'Pondérations'!$B$13+P29*'Pondérations'!$B$14)/'Pondérations'!$B$16,3),"") | R29: =IF(Q29="","",1+COUNTIF($Q$7:$Q$178,">"&Q29)+COUNTIF($Q$7:Q29,Q29)-1) | V29: Moyenne | W29: Discussion + Headfonics | X29: 8 | Y29: Reader | Z29: 45663 | AA29: 3 | AB29: https://headfonics.com/?s=Questyle+M15C | AC29: Balanced dongle DAC; updated M15 family | AD29: Déjà présent | AE29: 41 | AF29: 129 | AG29: Dongle solide, bien construit et suffisamment puissant, avec une qualité sonore globalement convaincante. | AH29: Neutre/Questyle propre. | AI29: Bonne qualité générale, sans point spatial majeur mis en avant. | AJ29: Volume minimum trop élevé; gain haut peu influent. | AK29: https://headfonics.com/questyle-m15c-review/ | AL29: 4 | AM29: Élevée — 3+ sources, domaines variés | AN29: https://www.head-fi.org/showcase/questyle-m15c.27912/reviews | AO29: https://www.ecoustics.com/reviews/questyle-m15c/ | AP29: https://www.pocnetwork.net/product-reviews/questyle-m15c-portable-headphone-amp/ | AQ29: Objectif atteint | AR29: Head-Fi reviews: 1; Review éditoriale: 3
A30: iBasso | B30: DC-Tonfa | C30: Dongle DAC/amp R-2R | D30: Prometteur: texture R-2R + précision iBasso | E30: Potentiel compromis naturel / résolution / profondeur | F30: Très récent; manque encore de recul indépendant | G30: 9.1 | H30: 8.9 | I30: 9.3 | J30: 9.2 | K30: 9.2 | L30: 9.2 | M30: 8.9 | N30: 8.7 | O30: 9 | P30: 9.3 | Q30: =IF(COUNT(G30:P30)=10,ROUND((G30*'Pondérations'!$B$5+H30*'Pondérations'!$B$6+I30*'Pondérations'!$B$7+J30*'Pondérations'!$B$8+K30*'Pondérations'!$B$9+L30*'Pondérations'!$B$10+M30*'Pondérations'!$B$11+N30*'Pondérations'!$B$12+O30*'Pondérations'!$B$13+P30*'Pondérations'!$B$14)/'Pondérations'!$B$16,3),"") | R30: =IF(Q30="","",1+COUNTIF($Q$7:$Q$178,">"&Q30)+COUNTIF($Q$7:Q30,Q30)-1) | V30: Faible / provisoire | W30: Discussion initiale | AF30: 292 | AG30: Les premiers essais du DC-Tonfa décrivent un R2R résolvant mais plus doux sur les contours, avec une sensation analogique, humide et naturelle plutôt qu'une précision agressive. | AH30: Naturelle, analogique, douce | AI30: Image fluide et vivante; les filtres modifient largeur, position des voix et réverbération, avec une bonne sensation de relief. | AJ30: Produit très récent: peu de recul et de comparaisons indépendantes; conclusions encore provisoires. | AK30: https://av.watch.impress.co.jp/docs/review/review/2126352.html | AL30: 3 | AM30: Élevée — 3+ sources, domaines variés | AN30: https://www.e-earphone.jp/blogs/feature/dc-tonfa_review | AO30: https://kajetblog.com/ibasso-dc-tonfa-4/ | AQ30: Objectif atteint | AR30: Review éditoriale: 3
A31: Questyle | B31: M18i Max | C31: Portable Amp/DAC (Headfonics) | D31: Neutre-référence avec légère chaleur et médiums un peu en avant. | E31: Microdétail, propreté/contrôle, dynamique | F31: Puissance assez limitée pour les casques très exigeants | G31: 9.4 | H31: 9.2 | I31: 8.8 | J31: 8.5 | K31: 9 | L31: 8.8 | M31: 9.1 | N31: 7 | O31: 8 | P31: 8.6 | Q31: =IF(COUNT(G31:P31)=10,ROUND((G31*'Pondérations'!$B$5+H31*'Pondérations'!$B$6+I31*'Pondérations'!$B$7+J31*'Pondérations'!$B$8+K31*'Pondérations'!$B$9+L31*'Pondérations'!$B$10+M31*'Pondérations'!$B$11+N31*'Pondérations'!$B$12+O31*'Pondérations'!$B$13+P31*'Pondérations'!$B$14)/'Pondérations'!$B$16,3),"") | R31: =IF(Q31="","",1+COUNTIF($Q$7:$Q$178,">"&Q31)+COUNTIF($Q$7:Q31,Q31)-1) | V31: Élevée | W31: Headfonics import | X31: 8.7 | Y31: Award | Z31: 46223 | AA31: 1 | AB31: https://headfonics.com/?s=Questyle+M18i+Max | AC31: ESS ES9219Q wireless portable DAC/amp | AD31: Ajout Headfonics | AE31: 1 | AF31: 307 | AG31: Très performant et musical pour un portable, avec un fond propre, une excellente résolution et une dynamique vive. | AH31: Neutre-référence avec légère chaleur et médiums un peu en avant. | AI31: Scène réaliste, bonne profondeur, layering précis et microdynamique très lisible. | AJ31: Puissance assez limitée pour les casques très exigeants; Bluetooth moins convaincant que l’USB. | AK31: https://headfonics.com/questyle-m18i-max-review/ | AL31: 4 | AM31: Élevée — 3+ sources, domaines variés | AN31: https://www.headfonia.com/questyle-m18i-max-review/ | AO31: https://kajetblog.com/questyle-m18i/ | AP31: https://www.milik.ai/articles/90800bdc7e | AQ31: Objectif atteint | AR31: Review éditoriale: 4
A32: AFUL | B32: ICEBORNE | C32: Portable Amp/DAC (Headfonics) | D32: Neutre/analytique mais non fatigant. | E32: Propreté/contrôle, image 3d, profondeur | F32: Réserve de puissance limitée avec les casques difficiles | G32: 9.2 | H32: 8.9 | I32: 8.8 | J32: 8.8 | K32: 8.8 | L32: 8.9 | M32: 8.8 | N32: 7 | O32: 9.5 | P32: 8.5 | Q32: =IF(COUNT(G32:P32)=10,ROUND((G32*'Pondérations'!$B$5+H32*'Pondérations'!$B$6+I32*'Pondérations'!$B$7+J32*'Pondérations'!$B$8+K32*'Pondérations'!$B$9+L32*'Pondérations'!$B$10+M32*'Pondérations'!$B$11+N32*'Pondérations'!$B$12+O32*'Pondérations'!$B$13+P32*'Pondérations'!$B$14)/'Pondérations'!$B$16,3),"") | R32: =IF(Q32="","",1+COUNTIF($Q$7:$Q$178,">"&Q32)+COUNTIF($Q$7:Q32,Q32)-1) | V32: Élevée | W32: Headfonics import | X32: 8.3 | Y32: Award | Z32: 46209 | AA32: 1 | AB32: https://headfonics.com/?s=AFUL+ICEBORNE | AC32: Dual CS43198 dongle DAC, up to 300 mW | AD32: Ajout Headfonics | AE32: 2 | AF32: 132 | AG32: Dongle neutre, transparent et agréable, surtout convaincant par sa propreté et son espace. | AH32: Neutre/analytique mais non fatigant. | AI32: Scène au-dessus de la moyenne et bonne transparence. | AJ32: Réserve de puissance limitée avec les casques difficiles. | AK32: https://headfonics.com/aful-iceborne-review/ | AL32: 4 | AM32: Élevée — 3+ sources, domaines variés | AN32: https://www.reddit.com/r/iems/comments/1tlm1cs/the_aful_iceborne_very_nice_but_worth_the_price/ | AO32: https://note.com/oto_iro_enpi/n/ncdcf63f3cf7b | AP32: https://audio-syumi70620.hatenablog.com/entry/2026/05/09/181031 | AQ32: Objectif atteint | AR32: Communauté Reddit: 1; Review éditoriale: 3
A33: Fosi Audio | B33: MD3 | C33: Portable Amp/DAC (Headfonics) | D33: Neutre, légèrement doux dans les médiums. | E33: Microdétail, propreté/contrôle, layering | F33: Grave pas le plus ferme | G33: 9.2 | H33: 9.3 | I33: 8.5 | J33: 8.4 | K33: 8.7 | L33: 8.8 | M33: 8 | N33: 7.8 | O33: 8 | P33: 8.1 | Q33: =IF(COUNT(G33:P33)=10,ROUND((G33*'Pondérations'!$B$5+H33*'Pondérations'!$B$6+I33*'Pondérations'!$B$7+J33*'Pondérations'!$B$8+K33*'Pondérations'!$B$9+L33*'Pondérations'!$B$10+M33*'Pondérations'!$B$11+N33*'Pondérations'!$B$12+O33*'Pondérations'!$B$13+P33*'Pondérations'!$B$14)/'Pondérations'!$B$16,3),"") | R33: =IF(Q33="","",1+COUNTIF($Q$7:$Q$178,">"&Q33)+COUNTIF($Q$7:Q33,Q33)-1) | V33: Élevée | W33: Headfonics import | X33: 7.9 | Y33: Award | Z33: 46207 | AA33: 1 | AB33: https://headfonics.com/?s=Fosi+Audio+MD3 | AC33: MagSafe ES9039Q2M portable DAC/amp, 180 mW | AD33: Ajout Headfonics | AE33: 3 | AF33: 132 | AG33: Restitution neutre et transparente avec beaucoup de microdétails et un aigu aéré, sans agressivité marquée. | AH33: Neutre, légèrement doux dans les médiums. | AI33: Scène spacieuse, plutôt large que profonde, mais séparation avant/arrière satisfaisante. | AJ33: Grave pas le plus ferme; dynamique moins explosive avec des casques. | AK33: https://headfonics.com/fosi-audio-md3-review/ | AL33: 4 | AM33: Élevée — 3+ sources, domaines variés | AN33: https://www.headfonia.com/fosi-audio-md3-review/ | AO33: https://moonstarreviews.net/fosi-audio-md3-review/ | AP33: https://www.ecoustics.com/reviews/fosi-audio-md3/ | AQ33: Objectif atteint | AR33: Review éditoriale: 4
A34: iFi audio | B34: GO link 2 | C34: Portable Amp/DAC (Headfonics) | D34: Neutre à légèrement énergique | E34: Microdétail, propreté/contrôle, image 3d | F34: Peut durcir à fort volume et manque de réserve avec les casques exigeants | G34: 9.3 | H34: 9.1 | I34: 8.9 | J34: 9 | K34: 9 | L34: 9 | M34: 9 | N34: 7 | O34: 9.5 | P34: 9 | Q34: =IF(COUNT(G34:P34)=10,ROUND((G34*'Pondérations'!$B$5+H34*'Pondérations'!$B$6+I34*'Pondérations'!$B$7+J34*'Pondérations'!$B$8+K34*'Pondérations'!$B$9+L34*'Pondérations'!$B$10+M34*'Pondérations'!$B$11+N34*'Pondérations'!$B$12+O34*'Pondérations'!$B$13+P34*'Pondérations'!$B$14)/'Pondérations'!$B$16,3),"") | R34: =IF(Q34="","",1+COUNTIF($Q$7:$Q$178,">"&Q34)+COUNTIF($Q$7:Q34,Q34)-1) | V34: Élevée | W34: Headfonics import | X34: 8.1 | Y34: Award | Z34: 46197 | AA34: 1 | AB34: https://headfonics.com/?s=iFi+audio+GO+link+2 | AC34: Dual ESS dongle DAC, up to 244 mW | AD34: Ajout Headfonics | AE34: 4 | AF34: 69 | AG34: Le GO link 2 est salué pour sa clarté, sa dynamique et son grave étonnamment solide au prix demandé. Il améliore nettement une sortie téléphone/PC sans complexité. | AH34: Neutre à légèrement énergique | AI34: Bonne clarté et timing, détail supérieur aux sorties intégrées; scène propre mais pas au niveau des dongles premium. | AJ34: Peut durcir à fort volume et manque de réserve avec les casques exigeants. | AK34: https://www.techradar.com/audio/dacs/ifi-go-link-2-review | AL34: 3 | AM34: Élevée — 3+ sources, domaines variés | AN34: https://www.whathifi.com/hi-fi/dacs/ifi-go-link-2 | AO34: https://audio46.com/blogs/headphones/ifi-go-link-2-portable-dacamp-review-whats-new-in-v2 | AQ34: Objectif atteint | AR34: Review éditoriale: 3
A35: MUSE HiFi | B35: M3 Ultra | C35: Portable Amp/DAC (Headfonics) | D35: Engageant, grave épais, aigu aéré. | E35: Image 3d, profondeur, matière/timbres | F35: Peut montrer ses limites à fort volume avec des casques exigeants | G35: 9.1 | H35: 8.8 | I35: 8.9 | J35: 8.9 | K35: 8.8 | L35: 9.1 | M35: 8.9 | N35: 7.8 | O35: 8 | P35: 8.4 | Q35: =IF(COUNT(G35:P35)=10,ROUND((G35*'Pondérations'!$B$5+H35*'Pondérations'!$B$6+I35*'Pondérations'!$B$7+J35*'Pondérations'!$B$8+K35*'Pondérations'!$B$9+L35*'Pondérations'!$B$10+M35*'Pondérations'!$B$11+N35*'Pondérations'!$B$12+O35*'Pondérations'!$B$13+P35*'Pondérations'!$B$14)/'Pondérations'!$B$16,3),"") | R35: =IF(Q35="","",1+COUNTIF($Q$7:$Q$178,">"&Q35)+COUNTIF($Q$7:Q35,Q35)-1) | V35: Élevée | W35: Headfonics import | X35: 8.3 | Y35: Award | Z35: 46181 | AA35: 1 | AB35: https://headfonics.com/?s=MUSE+HiFi+M3+Ultra | AC35: ES9028Q2M + dual JAN6418 tube portable amp, 480 mW | AD35: Ajout Headfonics | AE35: 5 | AF35: 109 | AG35: Son très transparent et spectaculaire, avec grave ample et aigu étendu; l’effet de scène est un vrai point fort. | AH35: Engageant, grave épais, aigu aéré. | AI35: Très grande scène, décrite comme holographique. | AJ35: Peut montrer ses limites à fort volume avec des casques exigeants. | AK35: https://headfonics.com/muse-hifi-m3-ultra-review/ | AL35: 4 | AM35: Élevée — 3+ sources, domaines variés | AN35: https://www.ecoustics.com/reviews/muse-hifi-m3-ultra/ | AO35: https://primeaudio.org/muse-hifi-m3-ultra-review/ | AP35: https://nextrift.com/202643639/ | AQ35: Objectif atteint | AR35: Review éditoriale: 4
A36: xDuoo | B36: Link3 | C36: Portable Amp/DAC (Headfonics) | D36: Légèrement chaleureux/analogique. | E36: Matière/timbres, profondeur, image 3d | F36: Format assez gros et chauffe sensiblement | G36: 9 | H36: 8.9 | I36: 8.9 | J36: 8.8 | K36: 8.9 | L36: 9.3 | M36: 9 | N36: 9 | O36: 7 | P36: 8.5 | Q36: =IF(COUNT(G36:P36)=10,ROUND((G36*'Pondérations'!$B$5+H36*'Pondérations'!$B$6+I36*'Pondérations'!$B$7+J36*'Pondérations'!$B$8+K36*'Pondérations'!$B$9+L36*'Pondérations'!$B$10+M36*'Pondérations'!$B$11+N36*'Pondérations'!$B$12+O36*'Pondérations'!$B$13+P36*'Pondérations'!$B$14)/'Pondérations'!$B$16,3),"") | R36: =IF(Q36="","",1+COUNTIF($Q$7:$Q$178,">"&Q36)+COUNTIF($Q$7:Q36,Q36)-1) | V36: Élevée | W36: Headfonics import | X36: 8.6 | Y36: Award | Z36: 46178 | AA36: 1 | AB36: https://headfonics.com/?s=xDuoo+Link3 | AC36: Dongle DAC with microSD slot | AD36: Ajout Headfonics | AE36: 6 | AF36: 239 | AG36: Présentation dynamique et propre, avec un côté analogique et musical plutôt qu’analytique. | AH36: Légèrement chaleureux/analogique. | AI36: Scène au-dessus de la moyenne, bonne dynamique et grave solide. | AJ36: Format assez gros et chauffe sensiblement. | AK36: https://headfonics.com/xduoo-link3-review/ | AL36: 4 | AM36: Élevée — 3+ sources, domaines variés | AN36: https://primeaudio.org/xduoo-link3-review/ | AO36: https://moonstarreviews.net/xduoo-link3-review/ | AP36: https://www.hifidaydreaming.com/post/portable-class-a-amp-dac-with-unique-twist-xduoo-link-3-review | AQ36: Objectif atteint | AR36: Review éditoriale: 4
A37: xDuoo | B37: XP-2 Bal | C37: Portable Amp/DAC (Headfonics) | D37: Neutre, analytique mais pas clinique. | E37: Microdétail, layering, propreté/contrôle | F37: Recharge lente | G37: 9.3 | H37: 9.2 | I37: 9 | J37: 8.9 | K37: 9.1 | L37: 8.7 | M37: 9.1 | N37: 8.7 | O37: 8 | P37: 8.8 | Q37: =IF(COUNT(G37:P37)=10,ROUND((G37*'Pondérations'!$B$5+H37*'Pondérations'!$B$6+I37*'Pondérations'!$B$7+J37*'Pondérations'!$B$8+K37*'Pondérations'!$B$9+L37*'Pondérations'!$B$10+M37*'Pondérations'!$B$11+N37*'Pondérations'!$B$12+O37*'Pondérations'!$B$13+P37*'Pondérations'!$B$14)/'Pondérations'!$B$16,3),"") | R37: =IF(Q37="","",1+COUNTIF($Q$7:$Q$178,">"&Q37)+COUNTIF($Q$7:Q37,Q37)-1) | V37: Élevée | W37: Headfonics import | X37: 8.4 | Y37: Award | Z37: 46157 | AA37: 1 | AB37: https://headfonics.com/?s=xDuoo+XP-2+Bal | AC37: Portable DAC/amp, balanced 320 mW, Bluetooth | AD37: Ajout Headfonics | AE37: 7 | AF37: 149 | AG37: Portable très détaillé et transparent, techniquement solide sans devenir froid. | AH37: Neutre, analytique mais pas clinique. | AI37: Bonne scène, grave tendu et lecture précise. | AJ37: Recharge lente; moins orienté couleur/matière. | AK37: https://headfonics.com/xduoo-xp-2-bal-review/ | AL37: 4 | AM37: Élevée — 3+ sources, domaines variés | AN37: https://www.youtube.com/watch?v=V-sVneIc1DQ | AO37: https://www.head-fi.org/threads/xduoo-xp-2-bal-balanced-bluetooth-dac-amp-now-on-apos-audio.966945/ | AP37: https://www.reddit.com/r/iems/comments/1gj8g45 | AQ37: Objectif atteint | AR37: Communauté Reddit: 1; Head-Fi forum: 1; Review éditoriale: 1; Vidéo review: 1
A38: iBasso | B38: PB6 MACAW | C38: Portable Amp/DAC (Headfonics) | D38: Tube doux, ample et riche. | E38: Matière/timbres, puissance, profondeur | F38: Encombrant | G38: 9 | H38: 8.7 | I38: 9 | J38: 8.9 | K38: 8.9 | L38: 9.5 | M38: 8.9 | N38: 9.3 | O38: 6.5 | P38: 8.5 | Q38: =IF(COUNT(G38:P38)=10,ROUND((G38*'Pondérations'!$B$5+H38*'Pondérations'!$B$6+I38*'Pondérations'!$B$7+J38*'Pondérations'!$B$8+K38*'Pondérations'!$B$9+L38*'Pondérations'!$B$10+M38*'Pondérations'!$B$11+N38*'Pondérations'!$B$12+O38*'Pondérations'!$B$13+P38*'Pondérations'!$B$14)/'Pondérations'!$B$16,3),"") | R38: =IF(Q38="","",1+COUNTIF($Q$7:$Q$178,">"&Q38)+COUNTIF($Q$7:Q38,Q38)-1) | V38: Élevée | W38: Headfonics import | X38: 9 | Y38: Award | Z38: 46081 | AA38: 1 | AB38: https://headfonics.com/?s=iBasso+PB6+MACAW | AC38: Quad JAN6418 tube portable headphone amplifier, up to 2.3 W | AD38: Ajout Headfonics | AE38: 9 | AF38: 438 | AG38: Ampli tube portable très puissant, fluide et expansif, tout en gardant un fond noir remarquable. | AH38: Tube doux, ample et riche. | AI38: Scène expansive et bon contrôle même avec des IEM sensibles. | AJ38: Encombrant; microphonie/tubes et protection physique à surveiller. | AK38: https://headfonics.com/ibasso-pb6-macaw-review/ | AL38: 4 | AM38: Élevée — 3+ sources, domaines variés | AN38: https://www.audiophile-heaven.com/2026/04/ibasso-pb6-macaw-tube-amplifier-review-portable-glow-of-magic-power.html | AO38: https://bloomaudio.com/blogs/articles/macaw-some-ibasso-pb6-macaw-review | AP38: https://www.open-end-music.com/forum/audiophile-kopfh%C3%B6rer/kh-kopfh%C3%B6rer-testberichte-rezensionen/768928-test-ibasso-pb6 | AQ38: Objectif atteint | AR38: Review éditoriale: 4
A39: HiBy | B39: W4 | C39: Portable Amp/DAC (Headfonics) | D39: Neutre avec légère euphonie et aigu aéré. | E39: Dynamique, layering, propreté/contrôle | F39: Commande de volume jugée particulière | G39: 9.1 | H39: 8.2 | I39: 8.8 | J39: 8.6 | K39: 8.9 | L39: 8.4 | M39: 8.4 | N39: 9.1 | O39: 8 | P39: 8.3 | Q39: =IF(COUNT(G39:P39)=10,ROUND((G39*'Pondérations'!$B$5+H39*'Pondérations'!$B$6+I39*'Pondérations'!$B$7+J39*'Pondérations'!$B$8+K39*'Pondérations'!$B$9+L39*'Pondérations'!$B$10+M39*'Pondérations'!$B$11+N39*'Pondérations'!$B$12+O39*'Pondérations'!$B$13+P39*'Pondérations'!$B$14)/'Pondérations'!$B$16,3),"") | R39: =IF(Q39="","",1+COUNTIF($Q$7:$Q$178,">"&Q39)+COUNTIF($Q$7:Q39,Q39)-1) | V39: Élevée | W39: Headfonics import | X39: 8.3 | Y39: Award | Z39: 46066 | AA39: 1 | AB39: https://headfonics.com/?s=HiBy+W4 | AC39: Bluetooth 5.4 dual-DAC portable amp, up to 475 mW | AD39: Ajout Headfonics | AE39: 10 | AF39: 87 | AG39: Bluetooth DAC agréable et euphonic, davantage musical que technique. | AH39: Neutre avec légère euphonie et aigu aéré. | AI39: Scène spacieuse mais résolution moins analytique. | AJ39: Commande de volume jugée particulière. | AK39: https://headfonics.com/hiby-w4-review/ | AL39: 4 | AM39: Élevée — 3+ sources, domaines variés | AN39: https://www.headfonia.com/hiby-w4-review/ | AO39: https://www.audiophile-heaven.com/2026/06/hiby-w4-portable-hifi-bluetooth-headphone-amplifier-review-dual-core-dual-mode-uncharge-dac.html | AP39: https://mobileaudiophile.com/wireless/hiby-w4-review/ | AQ39: Objectif atteint | AR39: Review éditoriale: 4
A40: Questyle | B40: SIGMA Pro | C40: Portable Amp/DAC (Headfonics) | D40: Neutre/analytique. | E40: Propreté/contrôle, puissance, dynamique | F40: Peu d’options de réglage | G40: 9.6 | H40: 9 | I40: 8.4 | J40: 8.3 | K40: 8.9 | L40: 8.5 | M40: 9.1 | N40: 9.4 | O40: 8 | P40: 8 | Q40: =IF(COUNT(G40:P40)=10,ROUND((G40*'Pondérations'!$B$5+H40*'Pondérations'!$B$6+I40*'Pondérations'!$B$7+J40*'Pondérations'!$B$8+K40*'Pondérations'!$B$9+L40*'Pondérations'!$B$10+M40*'Pondérations'!$B$11+N40*'Pondérations'!$B$12+O40*'Pondérations'!$B$13+P40*'Pondérations'!$B$14)/'Pondérations'!$B$16,3),"") | R40: =IF(Q40="","",1+COUNTIF($Q$7:$Q$178,">"&Q40)+COUNTIF($Q$7:Q40,Q40)-1) | V40: Élevée | W40: Headfonics import | X40: 8.6 | Y40: Award | Z40: 46053 | AA40: 1 | AB40: https://headfonics.com/?s=Questyle+SIGMA+Pro | AC40: Bluetooth-capable Current Mode portable DAC/amp | AD40: Ajout Headfonics | AE40: 11 | AF40: 790 | AG40: Portable résolument studio : très propre, équilibré et détaillé, visant la fidélité plutôt que la coloration. | AH40: Neutre/analytique. | AI40: Bonne précision et lisibilité des plans. | AJ40: Peu d’options de réglage; construction vitrée fragile. | AK40: https://headfonics.com/questyle-sigma-pro-review/ | AL40: 4 | AM40: Élevée — 3+ sources, domaines variés | AN40: https://kropka.audio/test/wzmacniacze/questyle-sigma-pro-recenzja/ | AO40: https://www.dtmstation.com/archives/75475.html | AP40: https://www.fujiya-avic.co.jp/blog/detail/996 | AQ40: Objectif atteint | AR40: Review éditoriale: 4
A41: iBasso | B41: D17 Atheris | C41: Portable Amp/DAC (Headfonics) | D41: Doux, analogique, riche; grave profond et voix charnues. | E41: Matière/timbres, image 3d, layering | F41: Puissance variable selon le mode | G41: 9.1 | H41: 8.9 | I41: 8.9 | J41: 9 | K41: 9 | L41: 9.7 | M41: 8.9 | N41: 7.2 | O41: 8 | P41: 8.8 | Q41: =IF(COUNT(G41:P41)=10,ROUND((G41*'Pondérations'!$B$5+H41*'Pondérations'!$B$6+I41*'Pondérations'!$B$7+J41*'Pondérations'!$B$8+K41*'Pondérations'!$B$9+L41*'Pondérations'!$B$10+M41*'Pondérations'!$B$11+N41*'Pondérations'!$B$12+O41*'Pondérations'!$B$13+P41*'Pondérations'!$B$14)/'Pondérations'!$B$16,3),"") | R41: =IF(Q41="","",1+COUNTIF($Q$7:$Q$178,">"&Q41)+COUNTIF($Q$7:Q41,Q41)-1) | V41: Élevée | W41: Headfonics import | X41: 9 | Y41: Reader | Z41: 45992 | AA41: 1 | AB41: https://headfonics.com/?s=iBasso+D17+Atheris | AC41: Discrete R2R + 1-bit portable DAC/amp, up to 1.2 W | AD41: Ajout Headfonics | AE41: 13 | AF41: 1757 | AG41: Très haut de gamme et polyvalent, avec plusieurs signatures DAC et une forte coloration analogique en mode tube. | AH41: Doux, analogique, riche; grave profond et voix charnues. | AI41: Grande richesse de texture et de nuances grâce aux modes DAC multiples. | AJ41: Puissance variable selon le mode; pas idéal pour les casques les plus difficiles. | AK41: https://headfonics.com/ibasso-d17-atheris-review/ | AL41: 4 | AM41: Élevée — 3+ sources, domaines variés | AN41: https://www.headfonia.com/ibasso-d17-atheris-review/ | AO41: https://moonstarreviews.net/ibasso-d17-atheris-review/ | AP41: https://www.audiophile-heaven.com/2025/12/ibasso-d17-atheris-r2r-1-bit-dac-and-tube-amp-review-complete-music-experience-systema-win.html | AQ41: Objectif atteint | AR41: Review éditoriale: 4
A42: Cayin | B42: RU3 | C42: Portable Amp/DAC (Headfonics) | D42: Neutre/propre. | E42: Matière/timbres, layering, microdétail | F42: Spatialisation encore limitée face aux modèles premium | G42: 9 | H42: 8.3 | I42: 8.1 | J42: 8.4 | K42: 9 | L42: 9.2 | M42: 8.9 | N42: 8.7 | O42: 9.5 | P42: 8 | Q42: =IF(COUNT(G42:P42)=10,ROUND((G42*'Pondérations'!$B$5+H42*'Pondérations'!$B$6+I42*'Pondérations'!$B$7+J42*'Pondérations'!$B$8+K42*'Pondérations'!$B$9+L42*'Pondérations'!$B$10+M42*'Pondérations'!$B$11+N42*'Pondérations'!$B$12+O42*'Pondérations'!$B$13+P42*'Pondérations'!$B$14)/'Pondérations'!$B$16,3),"") | R42: =IF(Q42="","",1+COUNTIF($Q$7:$Q$178,">"&Q42)+COUNTIF($Q$7:Q42,Q42)-1) | V42: Élevée | W42: Headfonics import | X42: 8.2 | Y42: Reader | Z42: 45990 | AA42: 1 | AB42: https://headfonics.com/?s=Cayin+RU3 | AC42: ES9069Q dongle DAC, app integration, up to 560 mW | AD42: Ajout Headfonics | AE42: 14 | AF42: 87 | AG42: Dongle propre et puissant pour son prix, avec un bon niveau général de qualité et de contrôle. | AH42: Neutre/propre. | AI42: Scène au-dessus de la moyenne mais pas très grande. | AJ42: Spatialisation encore limitée face aux modèles premium. | AK42: https://headfonics.com/cayin-ru3-review/ | AL42: 4 | AM42: Élevée — 3+ sources, domaines variés | AN42: https://porta-fi.com/cayin-ru3-review-usb-c-dongle-dac-amp-4-4mm-balanced-output/ | AO42: https://www.audiophile-heaven.com/2026/01/cayin-ru3-hifi-dac-amp-review-quad-balanced-bloomy-song.html | AP42: https://theheadphonelist.com/cayin-ru3-review-one-of-the-best-dongle-dac-amp-under-100/ | AQ42: Objectif atteint | AR42: Review éditoriale: 4
A43: FiiO | B43: SNOWSKY Tiny | C43: Portable Amp/DAC (Headfonics) | D43: Clair, vocal-forward. | E43: Microdétail, image 3d, profondeur | F43: Petit buzz au branchement et chauffe à l’usage | G43: 8.8 | H43: 8.4 | I43: 8.9 | J43: 8.2 | K43: 8.9 | L43: 9.1 | M43: 9 | N43: 7.9 | O43: 9.4 | P43: 8.6 | Q43: =IF(COUNT(G43:P43)=10,ROUND((G43*'Pondérations'!$B$5+H43*'Pondérations'!$B$6+I43*'Pondérations'!$B$7+J43*'Pondérations'!$B$8+K43*'Pondérations'!$B$9+L43*'Pondérations'!$B$10+M43*'Pondérations'!$B$11+N43*'Pondérations'!$B$12+O43*'Pondérations'!$B$13+P43*'Pondérations'!$B$14)/'Pondérations'!$B$16,3),"") | R43: =IF(Q43="","",1+COUNTIF($Q$7:$Q$178,">"&Q43)+COUNTIF($Q$7:Q43,Q43)-1) | V43: Élevée | W43: Headfonics import | X43: 8.1 | Y43: Reader | Z43: 45989 | AA43: 1 | AB43: https://headfonics.com/?s=FiiO+SNOWSKY+Tiny | AC43: Affordable dongle DAC, PCM384/DSD256, 10-band PEQ | AD43: Ajout Headfonics | AE43: 15 | AF43: 19 | AG43: Mini-dongle riche en fonctions, au rendu énergique et vocalement présent. | AH43: Clair, vocal-forward. | AI43: Plus axé énergie et personnalisation PEQ que raffinement spatial. | AJ43: Petit buzz au branchement et chauffe à l’usage. | AK43: https://headfonics.com/fiio-snowsky-tiny-review/ | AL43: 3 | AM43: Élevée — 3+ sources, domaines variés | AN43: https://www.hifioasis.com/reviews/fiio-snowsky-tiny-usb-dac-amp-review/ | AO43: https://www.reddit.com/r/iems/comments/1p07onz/got_the_fiio_snowsky_tiny_version_a_with_the_usbc/ | AQ43: Objectif atteint | AR43: Communauté Reddit: 1; Review éditoriale: 2
A44: Khadas | B44: Tea Pro | C44: Portable Amp/DAC (Headfonics) | D44: Transparent et plutôt neutre. | E44: Image 3d, profondeur, matière/timbres | F44: Recharge lente | G44: 8.9 | H44: 8.6 | I44: 8.8 | J44: 8.8 | K44: 8.8 | L44: 9 | M44: 8.8 | N44: 8.3 | O44: 8 | P44: 8.3 | Q44: =IF(COUNT(G44:P44)=10,ROUND((G44*'Pondérations'!$B$5+H44*'Pondérations'!$B$6+I44*'Pondérations'!$B$7+J44*'Pondérations'!$B$8+K44*'Pondérations'!$B$9+L44*'Pondérations'!$B$10+M44*'Pondérations'!$B$11+N44*'Pondérations'!$B$12+O44*'Pondérations'!$B$13+P44*'Pondérations'!$B$14)/'Pondérations'!$B$16,3),"") | R44: =IF(Q44="","",1+COUNTIF($Q$7:$Q$178,">"&Q44)+COUNTIF($Q$7:Q44,Q44)-1) | V44: Élevée | W44: Headfonics import | X44: 8.1 | Y44: Reader | Z44: 45965 | AA44: 1 | AB44: https://headfonics.com/?s=Khadas+Tea+Pro | AC44: Wireless ES9039Q2M magnetic portable DAC/amp | AD44: Ajout Headfonics | AE44: 17 | AF44: 175 | AG44: Portable Bluetooth transparent et suffisamment robuste pour alimenter même un HD6XX dans de bonnes conditions. | AH44: Transparent et plutôt neutre. | AI44: Bonne clarté générale; EQ/filtres utiles. | AJ44: Recharge lente. | AK44: https://headfonics.com/khadas-tea-pro-review/ | AL44: 4 | AM44: Élevée — 3+ sources, domaines variés | AN44: https://www.techradar.com/audio/dacs/khadas-tea-pro-review | AO44: https://mobileaudiophile.com/dacs/khadas-tea-pro-review-power-in-balance/ | AP44: https://www.audiophile-heaven.com/2025/10/khadas-tea-pro-dac-amp-review-uniting-android-and-iphone-users-for-music.html | AQ44: Objectif atteint | AR44: Review éditoriale: 4
A45: ddHiFi | B45: TC44Grip | C45: Portable Amp/DAC (Headfonics) | D45: Neutre-claire, brillante/analytique | E45: Microdétail, layering, propreté/contrôle | F45: Sous-grave et bas-médium maigres, impact limité | G45: 9.1 | H45: 9.2 | I45: 8.6 | J45: 8.6 | K45: 9 | L45: 8.4 | M45: 7.8 | N45: 8.6 | O45: 8 | P45: 8.2 | Q45: =IF(COUNT(G45:P45)=10,ROUND((G45*'Pondérations'!$B$5+H45*'Pondérations'!$B$6+I45*'Pondérations'!$B$7+J45*'Pondérations'!$B$8+K45*'Pondérations'!$B$9+L45*'Pondérations'!$B$10+M45*'Pondérations'!$B$11+N45*'Pondérations'!$B$12+O45*'Pondérations'!$B$13+P45*'Pondérations'!$B$14)/'Pondérations'!$B$16,3),"") | R45: =IF(Q45="","",1+COUNTIF($Q$7:$Q$178,">"&Q45)+COUNTIF($Q$7:Q45,Q45)-1) | V45: Élevée | W45: Headfonics import | X45: 7.7 | Y45: Reader | Z45: 45964 | AA45: 1 | AB45: https://headfonics.com/?s=ddHiFi+TC44Grip | AC45: Dual CS43198 smartphone-mounted dongle DAC, 330 mW | AD45: Ajout Headfonics | AE45: 18 | AF45: 159 | AG45: Le TC44Grip privilégie clarté des hauts-médiums, air et microdétails. Sa présentation est légère et articulate, mais volontairement peu chargée dans le grave. | AH45: Neutre-claire, brillante/analytique | AI45: Scène raisonnablement large, séparation précise et bon placement; forte sensation d'air, mais dynamique moins charnue. | AJ45: Sous-grave et bas-médium maigres, impact limité; peut fatiguer ou devenir sifflant sur des enregistrements brillants. | AK45: https://headfonics.com/ddhifi-tc44grip-review/ | AL45: 3 | AM45: Élevée — 3+ sources, domaines variés | AN45: https://androidbrick.com/ddhifi-tc44grip-phone-dac-review/ | AO45: https://www.ddhifi.com/en/review/21130/ | AP45: https://bloomaudio.com/products/ddhifi-tc44grip | AQ45: Objectif atteint | AR45: Review éditoriale: 3
A46: ddHiFi | B46: TC44 Pro E3 | C46: Portable Amp/DAC (Headfonics) | D46: Plutôt énergique/clair. | E46: Microdétail, image 3d, propreté/contrôle | F46: Peut devenir sibilant ou fatigant avec des écouteurs déjà brillants | G46: 9.2 | H46: 9 | I46: 8.8 | J46: 8.2 | K46: 8.9 | L46: 8.4 | M46: 8.9 | N46: 8.7 | O46: 9.5 | P46: 8.7 | Q46: =IF(COUNT(G46:P46)=10,ROUND((G46*'Pondérations'!$B$5+H46*'Pondérations'!$B$6+I46*'Pondérations'!$B$7+J46*'Pondérations'!$B$8+K46*'Pondérations'!$B$9+L46*'Pondérations'!$B$10+M46*'Pondérations'!$B$11+N46*'Pondérations'!$B$12+O46*'Pondérations'!$B$13+P46*'Pondérations'!$B$14)/'Pondérations'!$B$16,3),"") | R46: =IF(Q46="","",1+COUNTIF($Q$7:$Q$178,">"&Q46)+COUNTIF($Q$7:Q46,Q46)-1) | V46: Élevée | W46: Headfonics import | X46: 7.9 | Y46: Reader | Z46: 45945 | AA46: 1 | AB46: https://headfonics.com/?s=ddHiFi+TC44+Pro+E3 | AC46: Dual CS43198 dongle DAC, up to 510 mW | AD46: Ajout Headfonics | AE46: 20 | AF46: 104.9 | AG46: Dongle puissant avec bon sous-grave, mais dont l’équilibre dépend fortement de l’association. | AH46: Plutôt énergique/clair. | AI46: Bonne sensation de puissance; scène correcte. | AJ46: Peut devenir sibilant ou fatigant avec des écouteurs déjà brillants. | AK46: https://headfonics.com/ddhifi-tc44-pro-e3-review/ | AL46: 3 | AM46: Élevée — 3+ sources, domaines variés | AN46: https://moonstarreviews.net/ddhifi-eye3-tc44pro-e3-review/ | AO46: https://www.audioreviews.org/hifi-tc44pro-e3-review/ | AQ46: Objectif atteint | AR46: Review éditoriale: 3
A47: xDuoo | B47: Link10 | C47: Portable Amp/DAC (Headfonics) | D47: Chaud, relax, grave et bas-médium présents. | E47: Dynamique, matière/timbres, layering | F47: Aigu en retrait, pas idéal si l’on cherche beaucoup d’air et d’analyse | G47: 9.1 | H47: 7.5 | I47: 8.6 | J47: 8.5 | K47: 8.9 | L47: 9.1 | M47: 9.1 | N47: 9.1 | O47: 9.5 | P47: 8.2 | Q47: =IF(COUNT(G47:P47)=10,ROUND((G47*'Pondérations'!$B$5+H47*'Pondérations'!$B$6+I47*'Pondérations'!$B$7+J47*'Pondérations'!$B$8+K47*'Pondérations'!$B$9+L47*'Pondérations'!$B$10+M47*'Pondérations'!$B$11+N47*'Pondérations'!$B$12+O47*'Pondérations'!$B$13+P47*'Pondérations'!$B$14)/'Pondérations'!$B$16,3),"") | R47: =IF(Q47="","",1+COUNTIF($Q$7:$Q$178,">"&Q47)+COUNTIF($Q$7:Q47,Q47)-1) | V47: Élevée | W47: Headfonics import | X47: 7.7 | Y47: Reader | Z47: 45931 | AA47: 2 | AB47: https://headfonics.com/?s=xDuoo+Link10 | AC47: Dual CS43131 USB DAC/amp, up to 300 mW | AD47: Ajout Headfonics | AE47: 21 | AF47: 109 | AG47: Signature analogique et détendue qui se distingue des dongles CS43131 plus conventionnels. | AH47: Chaud, relax, grave et bas-médium présents. | AI47: Plus musical que démonstratif; filtres/NOS influents. | AJ47: Aigu en retrait, pas idéal si l’on cherche beaucoup d’air et d’analyse. | AK47: https://headfonics.com/xduoo-link10-review/ | AL47: 3 | AM47: Élevée — 3+ sources, domaines variés | AN47: https://bbs.erji.net/forum.php?mod=viewthread&tid=2404200 | AO47: https://inf.news/en/digital/f4754a56ebfbac0251b1eb9b168579f7.html | AQ47: Objectif atteint | AR47: Review éditoriale: 3
A48: FiiO | B48: JIEZI | C48: Portable Amp/DAC (Headfonics) | D48: V-shape énergique. | E48: Dynamique, propreté/contrôle, layering | F48: Pas très résolvant | G48: 8.2 | H48: 7.9 | I48: 8.6 | J48: 8.5 | K48: 8.9 | L48: 8.4 | M48: 9.2 | N48: 8.7 | O48: 9.5 | P48: 7.9 | Q48: =IF(COUNT(G48:P48)=10,ROUND((G48*'Pondérations'!$B$5+H48*'Pondérations'!$B$6+I48*'Pondérations'!$B$7+J48*'Pondérations'!$B$8+K48*'Pondérations'!$B$9+L48*'Pondérations'!$B$10+M48*'Pondérations'!$B$11+N48*'Pondérations'!$B$12+O48*'Pondérations'!$B$13+P48*'Pondérations'!$B$14)/'Pondérations'!$B$16,3),"") | R48: =IF(Q48="","",1+COUNTIF($Q$7:$Q$178,">"&Q48)+COUNTIF($Q$7:Q48,Q48)-1) | V48: Élevée | W48: Headfonics import | X48: 7.4 | Y48: Reader | Z48: 45927 | AA48: 2 | AB48: https://headfonics.com/?s=FiiO+JIEZI | AC48: Affordable 4.4 mm dongle DAC with 10-band PEQ | AD48: Ajout Headfonics | AE48: 22 | AF48: 11 | AG48: Petit dongle très énergique avec PEQ, pensé davantage pour le fun que pour la haute résolution. | AH48: V-shape énergique. | AI48: Bonne vivacité, mais détail/résolution modestes. | AJ48: Pas très résolvant. | AK48: https://headfonics.com/fiio-jiezi-review/ | AL48: 4 | AM48: Élevée — 3+ sources, domaines variés | AN48: https://www.headfonia.com/fiio-jiezi-review/ | AO48: https://portativ.ua/blog/ogljad-cap-pidsiljuvacha-fiio-jiezi-vse-scho-potribno.html | AP48: https://www.ixbt.com/live/digs/fiio-jade-audio-jiezi-obzor-mobilnogo-capa-usilitelya-dlya-naushnikov-nachalnogo-urovnya.html | AQ48: Objectif atteint | AR48: Review éditoriale: 4
A49: FiiO | B49: SNOWSKY Melody | C49: Portable Amp/DAC (Headfonics) | D49: V-shape énergique. | E49: Propreté/contrôle, dynamique, layering | F49: Manque de finesse et de détail face aux modèles plus ambitieux | G49: 8.4 | H49: 8 | I49: 8.7 | J49: 8.6 | K49: 8.9 | L49: 8.5 | M49: 9 | N49: 9.1 | O49: 9.5 | P49: 8 | Q49: =IF(COUNT(G49:P49)=10,ROUND((G49*'Pondérations'!$B$5+H49*'Pondérations'!$B$6+I49*'Pondérations'!$B$7+J49*'Pondérations'!$B$8+K49*'Pondérations'!$B$9+L49*'Pondérations'!$B$10+M49*'Pondérations'!$B$11+N49*'Pondérations'!$B$12+O49*'Pondérations'!$B$13+P49*'Pondérations'!$B$14)/'Pondérations'!$B$16,3),"") | R49: =IF(Q49="","",1+COUNTIF($Q$7:$Q$178,">"&Q49)+COUNTIF($Q$7:Q49,Q49)-1) | V49: Élevée | W49: Headfonics import | X49: 7.7 | Y49: Reader | Z49: 45913 | AA49: 2 | AB49: https://headfonics.com/?s=FiiO+SNOWSKY+Melody | AC49: Dual CS43131 wood-design dongle DAC, 250 mW | AD49: Ajout Headfonics | AE49: 23 | AF49: 35 | AG49: Dongle fun et personnalisable, agréable pour qui aime l’EQ et une restitution non technique. | AH49: V-shape énergique. | AI49: Scène correcte, résolution limitée. | AJ49: Manque de finesse et de détail face aux modèles plus ambitieux. | AK49: https://headfonics.com/fiio-snowsky-melody-review/ | AL49: 4 | AM49: Élevée — 3+ sources, domaines variés | AN49: https://primeaudio.org/fiio-snowsky-melody-review/ | AO49: https://www.headfonia.com/fiio-snowksy-melody-review/ | AP49: https://moonstarreviews.net/fiio-snowsky-melody-review/ | AQ49: Objectif atteint | AR49: Review éditoriale: 4
A50: xDuoo | B50: XD05 Basic2 | C50: Portable Amp/DAC (Headfonics) | D50: Analogique/chaud selon op-amp. | E50: Matière/timbres, profondeur, image 3d | F50: Résolution perçue moyenne | G50: 8.8 | H50: 8.3 | I50: 9 | J50: 8.9 | K50: 8.9 | L50: 9.4 | M50: 9 | N50: 9.1 | O50: 8 | P50: 8.4 | Q50: =IF(COUNT(G50:P50)=10,ROUND((G50*'Pondérations'!$B$5+H50*'Pondérations'!$B$6+I50*'Pondérations'!$B$7+J50*'Pondérations'!$B$8+K50*'Pondérations'!$B$9+L50*'Pondérations'!$B$10+M50*'Pondérations'!$B$11+N50*'Pondérations'!$B$12+O50*'Pondérations'!$B$13+P50*'Pondérations'!$B$14)/'Pondérations'!$B$16,3),"") | R50: =IF(Q50="","",1+COUNTIF($Q$7:$Q$178,">"&Q50)+COUNTIF($Q$7:Q50,Q50)-1) | V50: Élevée | W50: Headfonics import | X50: 8.3 | Y50: Reader | Z50: 45889 | AA50: 2 | AB50: https://headfonics.com/?s=xDuoo+XD05+Basic2 | AC50: CS43131 portable DAC/amp, 750 mW, swappable op-amps, wireless | AD50: Ajout Headfonics | AE50: 26 | AF50: 299 | AG50: Portable très polyvalent, au rendu analogique modifiable par changement d’op-amp. | AH50: Analogique/chaud selon op-amp. | AI50: Agréable et musical plus que hyper-résolvant. | AJ50: Résolution perçue moyenne; pas de 4.4 mm. | AK50: https://headfonics.com/xduoo-xd05-basic2-review/ | AL50: 3 | AM50: Élevée — 3+ sources, domaines variés | AN50: https://primeaudio.org/xduoo-xd05-basic2-review/ | AO50: https://www.headfonia.com/xduoo-xd05-basic2-review/ | AQ50: Objectif atteint | AR50: Review éditoriale: 3
A51: iBasso | B51: Nunchaku | C51: Portable Amp/DAC (Headfonics) | D51: Deux modes/timbres, dont tube. | E51: Matière/timbres, image 3d, profondeur | F51: Gros pour un dongle | G51: 8.9 | H51: 8.8 | I51: 8.9 | J51: 9 | K51: 8.9 | L51: 9.4 | M51: 8.8 | N51: 8.7 | O51: 6.5 | P51: 8.5 | Q51: =IF(COUNT(G51:P51)=10,ROUND((G51*'Pondérations'!$B$5+H51*'Pondérations'!$B$6+I51*'Pondérations'!$B$7+J51*'Pondérations'!$B$8+K51*'Pondérations'!$B$9+L51*'Pondérations'!$B$10+M51*'Pondérations'!$B$11+N51*'Pondérations'!$B$12+O51*'Pondérations'!$B$13+P51*'Pondérations'!$B$14)/'Pondérations'!$B$16,3),"") | R51: =IF(Q51="","",1+COUNTIF($Q$7:$Q$178,">"&Q51)+COUNTIF($Q$7:Q51,Q51)-1) | V51: Élevée | W51: Headfonics import | X51: 8.6 | Y51: Reader | Z51: 45864 | AA51: 2 | AB51: https://headfonics.com/?s=iBasso+Nunchaku | AC51: Portable DAC/amp; Headfonics category entry added after older cache snapshots | AD51: Ajout Headfonics | AE51: 27 | AF51: 299 | AG51: Dongle haut de gamme à double personnalité sonore, plus flexible que le DC-Elite dans ses timbres. | AH51: Deux modes/timbres, dont tube. | AI51: Très bon niveau global, caractère ajustable. | AJ51: Gros pour un dongle; tube sujet au 'ping' microphonique. | AK51: https://headfonics.com/ibasso-nunchaku-review/ | AL51: 4 | AM51: Élevée — 3+ sources, domaines variés | AN51: https://www.head-fi.org/showcase/ibasso-nunchaku.27945/reviews | AO51: https://www.headfonia.com/ibasso-nunchaku-review/ | AP51: https://moonstarreviews.net/ibasso-nunchaku-review/ | AQ51: Objectif atteint | AR51: Head-Fi reviews: 1; Review éditoriale: 3
A52: NiPO | B52: A100 | C52: Portable Amp/DAC (Headfonics) | D52: Analytique avec légère musicalité. | E52: Propreté/contrôle, dynamique, microdétail | F52: Impossible à utiliser pendant la charge | G52: 9.4 | H52: 8.9 | I52: 8.7 | J52: 8.6 | K52: 8.8 | L52: 8.6 | M52: 9 | N52: 9 | O52: 8 | P52: 8.2 | Q52: =IF(COUNT(G52:P52)=10,ROUND((G52*'Pondérations'!$B$5+H52*'Pondérations'!$B$6+I52*'Pondérations'!$B$7+J52*'Pondérations'!$B$8+K52*'Pondérations'!$B$9+L52*'Pondérations'!$B$10+M52*'Pondérations'!$B$11+N52*'Pondérations'!$B$12+O52*'Pondérations'!$B$13+P52*'Pondérations'!$B$14)/'Pondérations'!$B$16,3),"") | R52: =IF(Q52="","",1+COUNTIF($Q$7:$Q$178,">"&Q52)+COUNTIF($Q$7:Q52,Q52)-1) | V52: Élevée | W52: Headfonics import | X52: 8 | Y52: Reader | Z52: 45859 | AA52: 2 | AB52: https://headfonics.com/?s=NiPO+A100 | AC52: ES9039Q2M portable DAC/amp, up to 550 mW | AD52: Ajout Headfonics | AE52: 28 | AF52: 351 | AG52: Portable propre et analytique, avec suffisamment de corps pour éviter une présentation sèche. | AH52: Analytique avec légère musicalité. | AI52: Fond silencieux et bonne lisibilité. | AJ52: Impossible à utiliser pendant la charge; pas d’écran. | AK52: https://headfonics.com/nipo-a100-review/ | AL52: 4 | AM52: Élevée — 3+ sources, domaines variés | AN52: https://twister6.com/2025/08/08/nipo-a100/ | AO52: https://trefle-lab.com/nipo-a100-review/ | AP52: https://note.com/ralphhinkley/n/n48e78452f0d8?hl=en | AQ52: Objectif atteint | AR52: Review éditoriale: 4
A53: ddHiFi | B53: TC44Pro M3 | C53: Portable Amp/DAC (Headfonics) | D53: Neutre-chaud léger. | E53: Microdétail, image 3d, propreté/contrôle | F53: Format large pouvant gêner les ports voisins | G53: 9.2 | H53: 9 | I53: 8.8 | J53: 8.9 | K53: 8.9 | L53: 9.1 | M53: 8.9 | N53: 8.2 | O53: 7.2 | P53: 8.7 | Q53: =IF(COUNT(G53:P53)=10,ROUND((G53*'Pondérations'!$B$5+H53*'Pondérations'!$B$6+I53*'Pondérations'!$B$7+J53*'Pondérations'!$B$8+K53*'Pondérations'!$B$9+L53*'Pondérations'!$B$10+M53*'Pondérations'!$B$11+N53*'Pondérations'!$B$12+O53*'Pondérations'!$B$13+P53*'Pondérations'!$B$14)/'Pondérations'!$B$16,3),"") | R53: =IF(Q53="","",1+COUNTIF($Q$7:$Q$178,">"&Q53)+COUNTIF($Q$7:Q53,Q53)-1) | V53: Élevée | W53: Headfonics import | X53: 8 | Y53: Reader | Z53: 45852 | AA53: 2 | AB53: https://headfonics.com/?s=ddHiFi+TC44Pro+M3 | AC53: Dual CS43198 dongle DAC, up to 120 mW balanced | AD53: Ajout Headfonics | AE53: 29 | AF53: 79 | AG53: Dongle compact et propre, légèrement chaleureux, avec une bonne texture de grave. | AH53: Neutre-chaud léger. | AI53: Bonne définition générale dans un format compact. | AJ53: Format large pouvant gêner les ports voisins; accessoires limités. | AK53: https://headfonics.com/ddhifi-tc44pro-m3-review/ | AL53: 4 | AM53: Élevée — 3+ sources, domaines variés | AN53: https://www.head-fi.org/showcase/ddhifi-tc44pro-m3-mountain3-t-shaped-hi-res-dac-amp-dongle-adapter.28092/reviews | AO53: https://moonstarreviews.net/ddhifi-tc44pro-m3-review/ | AP53: https://www.audiophile-heaven.com/2025/09/ddhifi-tc44pro-m3-mountain3-review-t-shaped-dongle-dac-amp-with-an-engaging-signature.html | AQ53: Objectif atteint | AR53: Head-Fi reviews: 1; Review éditoriale: 3
A54: Cayin | B54: RU9 | C54: Portable Amp/DAC (Headfonics) | D54: Très ajustable selon modes/tubes. | E54: Matière/timbres, profondeur, image 3d | F54: Plus transportable que réellement dongle | G54: 8.8 | H54: 8.7 | I54: 8.9 | J54: 8.8 | K54: 8.9 | L54: 9.6 | M54: 8.8 | N54: 8.8 | O54: 6.5 | P54: 8.4 | Q54: =IF(COUNT(G54:P54)=10,ROUND((G54*'Pondérations'!$B$5+H54*'Pondérations'!$B$6+I54*'Pondérations'!$B$7+J54*'Pondérations'!$B$8+K54*'Pondérations'!$B$9+L54*'Pondérations'!$B$10+M54*'Pondérations'!$B$11+N54*'Pondérations'!$B$12+O54*'Pondérations'!$B$13+P54*'Pondérations'!$B$14)/'Pondérations'!$B$16,3),"") | R54: =IF(Q54="","",1+COUNTIF($Q$7:$Q$178,">"&Q54)+COUNTIF($Q$7:Q54,Q54)-1) | V54: Élevée | W54: Headfonics import | X54: 8.6 | Y54: Reader | Z54: 45850 | AA54: 2 | AB54: https://headfonics.com/?s=Cayin+RU9 | AC54: Tube/solid-state USB DAC/amp, up to 1 W | AD54: Ajout Headfonics | AE54: 30 | AF54: 438 | AG54: DAC/amp très modulable et puissant, pensé pour offrir plusieurs saveurs sonores plutôt qu’une signature unique. | AH54: Très ajustable selon modes/tubes. | AI54: Bon potentiel dynamique et de texture; batterie interne bénéfique. | AJ54: Plus transportable que réellement dongle. | AK54: https://headfonics.com/cayin-ru9-review/ | AL54: 4 | AM54: Élevée — 3+ sources, domaines variés | AN54: https://www.headfonia.com/cayin-ru9-review/ | AO54: https://www.ecoustics.com/reviews/cayin-ru9/ | AP54: https://kropka.audio/test/wzmacniacze/cayin-ru9-review/ | AQ54: Objectif atteint | AR54: Review éditoriale: 4
A55: Shanling | B55: UP6 | C55: Portable Amp/DAC (Headfonics) | D55: Propre, assez neutre. | E55: Image 3d, profondeur, layering | F55: Bluetooth pas de toute dernière génération | G55: 8.8 | H55: 8.6 | I55: 8.6 | J55: 8.6 | K55: 8.7 | L55: 8.8 | M55: 8.8 | N55: 8.9 | O55: 8 | P55: 8 | Q55: =IF(COUNT(G55:P55)=10,ROUND((G55*'Pondérations'!$B$5+H55*'Pondérations'!$B$6+I55*'Pondérations'!$B$7+J55*'Pondérations'!$B$8+K55*'Pondérations'!$B$9+L55*'Pondérations'!$B$10+M55*'Pondérations'!$B$11+N55*'Pondérations'!$B$12+O55*'Pondérations'!$B$13+P55*'Pondérations'!$B$14)/'Pondérations'!$B$16,3),"") | R55: =IF(Q55="","",1+COUNTIF($Q$7:$Q$178,">"&Q55)+COUNTIF($Q$7:Q55,Q55)-1) | V55: Élevée | W55: Headfonics import | X55: 8.4 | Y55: Reader | Z55: 45847 | AA55: 2 | AB55: https://headfonics.com/?s=Shanling+UP6 | AC55: Dual ES9069Q Bluetooth DAC/amp with LDAC/aptX | AD55: Ajout Headfonics | AE55: 31 | AF55: 189 | AG55: Bluetooth DAC propre et puissant, très complet et d’un bon rapport performances/fonctions. | AH55: Propre, assez neutre. | AI55: Bonne puissance et lisibilité, sans accent particulier sur l’holographie. | AJ55: Bluetooth pas de toute dernière génération; châssis anguleux. | AK55: https://headfonics.com/shanling-up6-review/ | AL55: 4 | AM55: Élevée — 3+ sources, domaines variés | AN55: https://www.head-fi.org/showcase/shanling-up6.28161/reviews | AO55: https://www.headfonia.com/shanling-up6-review/ | AP55: https://www.hifioasis.com/reviews/shanling-up6-review/ | AQ55: Objectif atteint | AR55: Head-Fi reviews: 1; Review éditoriale: 3
A56: Questyle | B56: M18i | C56: Portable Amp/DAC (Headfonics) | D56: Propre, neutre. | E56: Profondeur, matière/timbres, image 3d | F56: Ergonomie/charge et gain en Bluetooth perfectibles | G56: 9 | H56: 8.7 | I56: 9.1 | J56: 8.8 | K56: 8.9 | L56: 9.2 | M56: 9 | N56: 9 | O56: 9.5 | P56: 8.5 | Q56: =IF(COUNT(G56:P56)=10,ROUND((G56*'Pondérations'!$B$5+H56*'Pondérations'!$B$6+I56*'Pondérations'!$B$7+J56*'Pondérations'!$B$8+K56*'Pondérations'!$B$9+L56*'Pondérations'!$B$10+M56*'Pondérations'!$B$11+N56*'Pondérations'!$B$12+O56*'Pondérations'!$B$13+P56*'Pondérations'!$B$14)/'Pondérations'!$B$16,3),"") | R56: =IF(Q56="","",1+COUNTIF($Q$7:$Q$178,">"&Q56)+COUNTIF($Q$7:Q56,Q56)-1) | V56: Élevée | W56: Headfonics import | X56: 8.3 | Y56: Reader | Z56: 45798 | AA56: 2 | AB56: https://headfonics.com/?s=Questyle+M18i | AC56: ES9219Q wireless dongle DAC with Current Mode amplification | AD56: Ajout Headfonics | AE56: 33 | AF56: 307 | AG56: Dongle/Bluetooth de haut niveau, propre et techniquement très capable, avec une scène particulièrement grande et précise. | AH56: Propre, neutre. | AI56: Grande scène, forte précision et fond sombre. | AJ56: Ergonomie/charge et gain en Bluetooth perfectibles. | AK56: https://headfonics.com/questyle-m18i-review/ | AL56: 4 | AM56: Élevée — 3+ sources, domaines variés | AN56: https://www.headfonia.com/questyle-m18i-review/ | AO56: https://www.ecoustics.com/reviews/questyle-m18i/ | AP56: https://www.androidcentral.com/accessories/audio/review-questyle-m18i | AQ56: Objectif atteint | AR56: Review éditoriale: 4
A57: FiiO | B57: RR11 | C57: Portable Amp/DAC (Headfonics) | D57: Plutôt analytique. | E57: Microdétail, layering, image 3d | F57: Signature potentiellement trop analytique | G57: 8.4 | H57: 8.3 | I57: 8.8 | J57: 8.2 | K57: 9 | L57: 8.4 | M57: 8.9 | N57: 8.4 | O57: 9.5 | P57: 8.7 | Q57: =IF(COUNT(G57:P57)=10,ROUND((G57*'Pondérations'!$B$5+H57*'Pondérations'!$B$6+I57*'Pondérations'!$B$7+J57*'Pondérations'!$B$8+K57*'Pondérations'!$B$9+L57*'Pondérations'!$B$10+M57*'Pondérations'!$B$11+N57*'Pondérations'!$B$12+O57*'Pondérations'!$B$13+P57*'Pondérations'!$B$14)/'Pondérations'!$B$16,3),"") | R57: =IF(Q57="","",1+COUNTIF($Q$7:$Q$178,">"&Q57)+COUNTIF($Q$7:Q57,Q57)-1) | V57: Élevée | W57: Headfonics import | X57: 7.7 | Y57: Reader | Z57: 45787 | AA57: 2 | AB57: https://headfonics.com/?s=FiiO+RR11 | AC57: Portable FM radio with dongle functionality | AD57: Ajout Headfonics | AE57: 34 | AF57: 53 | AG57: Produit rétro surtout intéressant pour la radio, mais son mode dongle est correctement réussi. | AH57: Plutôt analytique. | AI57: Correct pour le prix, sans ambition audiophile extrême. | AJ57: Signature potentiellement trop analytique; fonctions sonores gadget limitées. | AK57: https://headfonics.com/fiio-rr11-review/ | AL57: 4 | AM57: Élevée — 3+ sources, domaines variés | AN57: https://www.head-fi.org/showcase/fiio-rr11.28083/reviews | AO57: https://www.headfonia.com/fiio-rr11-review/ | AP57: https://moonstarreviews.net/fiio-rr11-review/ | AQ57: Objectif atteint | AR57: Head-Fi reviews: 1; Review éditoriale: 3
A58: EarMen | B58: L-Amp | C58: Portable Amp/DAC (Headfonics) | D58: Chaleur tube avec clarté solide-state. | E58: Puissance, matière/timbres, image 3d | F58: Format/usage plus transportable que mini-dongle | G58: 9 | H58: 8.8 | I58: 8.7 | J58: 8.8 | K58: 8.8 | L58: 9.2 | M58: 8.9 | N58: 9.3 | O58: 6.5 | P58: 8.3 | Q58: =IF(COUNT(G58:P58)=10,ROUND((G58*'Pondérations'!$B$5+H58*'Pondérations'!$B$6+I58*'Pondérations'!$B$7+J58*'Pondérations'!$B$8+K58*'Pondérations'!$B$9+L58*'Pondérations'!$B$10+M58*'Pondérations'!$B$11+N58*'Pondérations'!$B$12+O58*'Pondérations'!$B$13+P58*'Pondérations'!$B$14)/'Pondérations'!$B$16,3),"") | R58: =IF(Q58="","",1+COUNTIF($Q$7:$Q$178,">"&Q58)+COUNTIF($Q$7:Q58,Q58)-1) | V58: Élevée | W58: Headfonics import | X58: 8.6 | Y58: Reader | Z58: 45770 | AA58: 2 | AB58: https://headfonics.com/?s=EarMen+L-Amp | AC58: Dual JAN6418 NOS tube portable headphone amplifier/DAC | AD58: Ajout Headfonics | AE58: 35 | AF58: 351 | AG58: Ampli/DAC tube très puissant combinant fluidité et précision, avec un bon équilibre entre chaleur et clarté. | AH58: Chaleur tube avec clarté solide-state. | AI58: Bonne dynamique et ample réserve de puissance. | AJ58: Format/usage plus transportable que mini-dongle. | AK58: https://headfonics.com/earmen-l-amp-review/ | AL58: 3 | AM58: Élevée — 3+ sources, domaines variés | AN58: https://www.head-fi.org/threads/earmen-l-amp-review.976122/ | AO58: https://www.headfonia.com/earmen-l-amp-review/ | AQ58: Objectif atteint | AR58: Head-Fi forum: 1; Review éditoriale: 2
A59: FiiO | B59: SNOWSKY RETRO NANO | C59: Portable Amp/DAC (Headfonics) | D59: Plutôt polyvalent/fun. | E59: Puissance, matière/timbres, dynamique | F59: Autonomie courte et trappe de batterie fragile | G59: 8.8 | H59: 8.6 | I59: 8.6 | J59: 8.4 | K59: 8.7 | L59: 8.9 | M59: 8.9 | N59: 9.4 | O59: 8 | P59: 7.9 | Q59: =IF(COUNT(G59:P59)=10,ROUND((G59*'Pondérations'!$B$5+H59*'Pondérations'!$B$6+I59*'Pondérations'!$B$7+J59*'Pondérations'!$B$8+K59*'Pondérations'!$B$9+L59*'Pondérations'!$B$10+M59*'Pondérations'!$B$11+N59*'Pondérations'!$B$12+O59*'Pondérations'!$B$13+P59*'Pondérations'!$B$14)/'Pondérations'!$B$16,3),"") | R59: =IF(Q59="","",1+COUNTIF($Q$7:$Q$178,">"&Q59)+COUNTIF($Q$7:Q59,Q59)-1) | V59: Élevée | W59: Headfonics import | X59: 8.1 | Y59: Reader | Z59: 45745 | AA59: 2 | AB59: https://headfonics.com/?s=FiiO+SNOWSKY+RETRO+NANO | AC59: Self-powered Bluetooth dongle DAC, up to 220 mW | AD59: Ajout Headfonics | AE59: 36 | AF59: 53 | AG59: Petit DAC Bluetooth très riche en fonctions et très bon marché, davantage axé polyvalence que performance sonore ultime. | AH59: Plutôt polyvalent/fun. | AI59: Correct techniquement pour le prix. | AJ59: Autonomie courte et trappe de batterie fragile. | AK59: https://headfonics.com/fiio-snowsky-retro-nano-review/ | AL59: 4 | AM59: Élevée — 3+ sources, domaines variés | AN59: https://www.head-fi.org/showcase/snowsky-retro-nano.27828/reviews | AO59: https://www.hifioasis.com/reviews/snowsky-retro-nano-review/ | AP59: https://audio46.com/blogs/headphones/fiio-snowsky-retro-nano-bluetooth-dac-amp-review | AQ59: Objectif atteint | AR59: Head-Fi reviews: 1; Review éditoriale: 3
A60: Cayin | B60: C9ii | C60: Portable Amp/DAC (Headfonics) | D60: Très ajustable, tube/solid-state selon modes. | E60: Propreté/contrôle, matière/timbres, image 3d | F60: Très volumineux : transportable plus que portable | G60: 9.1 | H60: 8.8 | I60: 8.6 | J60: 8.6 | K60: 8.7 | L60: 9 | M60: 8.9 | N60: 9 | O60: 6.5 | P60: 8.1 | Q60: =IF(COUNT(G60:P60)=10,ROUND((G60*'Pondérations'!$B$5+H60*'Pondérations'!$B$6+I60*'Pondérations'!$B$7+J60*'Pondérations'!$B$8+K60*'Pondérations'!$B$9+L60*'Pondérations'!$B$10+M60*'Pondérations'!$B$11+N60*'Pondérations'!$B$12+O60*'Pondérations'!$B$13+P60*'Pondérations'!$B$14)/'Pondérations'!$B$16,3),"") | R60: =IF(Q60="","",1+COUNTIF($Q$7:$Q$178,">"&Q60)+COUNTIF($Q$7:Q60,Q60)-1) | V60: Élevée | W60: Headfonics import | X60: 9.1 | Y60: Reader | Z60: 45735 | AA60: 2 | AB60: https://headfonics.com/?s=Cayin+C9ii | AC60: Solid-state / Gen 5 Nutube portable headphone amplifier | AD60: Ajout Headfonics | AE60: 37 | AF60: 2108 | AG60: Ampli portable tube extrêmement complet et puissant, avec bien plus de dynamique et un fond plus noir que le C9. | AH60: Très ajustable, tube/solid-state selon modes. | AI60: Large plage de réglages, forte dynamique et bonne maîtrise. | AJ60: Très volumineux : transportable plus que portable. | AK60: https://headfonics.com/cayin-c9ii-review/ | AL60: 3 | AM60: Élevée — 3+ sources, domaines variés | AN60: https://www.headfonia.com/cayin-c9ii-review/ | AO60: https://www.head-fi.org/threads/cayin-c9ii-dual-nutube-prtable-headphone-amplifier-gen5-3x-timbre-anode-nfb-pre-line.973711/ | AQ60: Objectif atteint | AR60: Head-Fi forum: 1; Review éditoriale: 2
A61: ddHiFi | B61: TC35M2 | C61: Portable Amp/DAC (Headfonics) | D61: Neutre fonctionnel. | E61: Matière/timbres, dynamique, layering | F61: Pas idéal avec IEM ultra-sensibles ni casques difficiles | G61: 8.8 | H61: 8 | I61: 8.8 | J61: 8.7 | K61: 8.9 | L61: 9.1 | M61: 9 | N61: 7.5 | O61: 8 | P61: 8.3 | Q61: =IF(COUNT(G61:P61)=10,ROUND((G61*'Pondérations'!$B$5+H61*'Pondérations'!$B$6+I61*'Pondérations'!$B$7+J61*'Pondérations'!$B$8+K61*'Pondérations'!$B$9+L61*'Pondérations'!$B$10+M61*'Pondérations'!$B$11+N61*'Pondérations'!$B$12+O61*'Pondérations'!$B$13+P61*'Pondérations'!$B$14)/'Pondérations'!$B$16,3),"") | R61: =IF(Q61="","",1+COUNTIF($Q$7:$Q$178,">"&Q61)+COUNTIF($Q$7:Q61,Q61)-1) | V61: Élevée | W61: Headfonics import | X61: 7.9 | Y61: Reader | Z61: 45691 | AA61: 2 | AB61: https://headfonics.com/?s=ddHiFi+TC35M2 | AC61: Tiny 384 kHz USB-C DAC to 3.5 mm converter | AD61: Ajout Headfonics | AE61: 38 | AF61: 32 | AG61: Très petit DAC surtout remarquable par sa commodité, pas par ses performances absolues. | AH61: Neutre fonctionnel. | AI61: Clarté correcte mais détail médium limité. | AJ61: Pas idéal avec IEM ultra-sensibles ni casques difficiles. | AK61: https://headfonics.com/ddhifi-tc35m2-review/ | AL61: 3 | AM61: Élevée — 3+ sources, domaines variés | AN61: https://www.head-fi.org/showcase/ddhifi-tc35m2.27896/reviews | AO61: https://www.audioreviews.org/ddhifi-tc35cm2-review/ | AQ61: Objectif atteint | AR61: Head-Fi reviews: 1; Review éditoriale: 2
A62: iFi audio | B62: GO link Max | C62: Portable Amp/DAC (Headfonics) | D62: Coloré, grave plutôt maigre. | E62: Propreté/contrôle, dynamique, microdétail | F62: Grave lean selon les associations | G62: 8.4 | H62: 8.9 | I62: 8.6 | J62: 8.6 | K62: 8.2 | L62: 8.2 | M62: 8 | N62: 8.7 | O62: 9.5 | P62: 8.1 | Q62: =IF(COUNT(G62:P62)=10,ROUND((G62*'Pondérations'!$B$5+H62*'Pondérations'!$B$6+I62*'Pondérations'!$B$7+J62*'Pondérations'!$B$8+K62*'Pondérations'!$B$9+L62*'Pondérations'!$B$10+M62*'Pondérations'!$B$11+N62*'Pondérations'!$B$12+O62*'Pondérations'!$B$13+P62*'Pondérations'!$B$14)/'Pondérations'!$B$16,3),"") | R62: =IF(Q62="","",1+COUNTIF($Q$7:$Q$178,">"&Q62)+COUNTIF($Q$7:Q62,Q62)-1) | V62: Élevée | W62: Headfonics import | X62: 7.8 | Y62: Reader | Z62: 45672 | AA62: 2 | AB62: https://headfonics.com/?s=iFi+audio+GO+link+Max | AC62: Compact DSD256-capable dongle DAC | AD62: Ajout Headfonics | AE62: 39 | AF62: 69 | AG62: Petit dongle étonnamment puissant, mais avec une coloration qui peut réduire la polyvalence d’association. | AH62: Coloré, grave plutôt maigre. | AI62: Bonne énergie et puissance pour le format. | AJ62: Grave lean selon les associations. | AK62: https://headfonics.com/ifi-audio-go-link-max-review/ | AL62: 4 | AM62: Élevée — 3+ sources, domaines variés | AN62: https://www.head-fi.org/showcase/ifi-audio-go-link-max.27729/reviews | AO62: https://www.whathifi.com/reviews/ifi-go-link-max | AP62: https://primeaudio.org/ifi-go-link-max-review/ | AQ62: Objectif atteint | AR62: Head-Fi reviews: 1; Review éditoriale: 3
A63: Heartfield | B63: R1 | C63: Portable Amp/DAC (Headfonics) | D63: Chaud, analogique. | E63: Matière/timbres, image 3d, profondeur | F63: Distorsion/pops et qualité de construction signalés | G63: 7.5 | H63: 8.9 | I63: 8.9 | J63: 8.9 | K63: 8.9 | L63: 8.2 | M63: 7.5 | N63: 8.7 | O63: 8 | P63: 8.6 | Q63: =IF(COUNT(G63:P63)=10,ROUND((G63*'Pondérations'!$B$5+H63*'Pondérations'!$B$6+I63*'Pondérations'!$B$7+J63*'Pondérations'!$B$8+K63*'Pondérations'!$B$9+L63*'Pondérations'!$B$10+M63*'Pondérations'!$B$11+N63*'Pondérations'!$B$12+O63*'Pondérations'!$B$13+P63*'Pondérations'!$B$14)/'Pondérations'!$B$16,3),"") | R63: =IF(Q63="","",1+COUNTIF($Q$7:$Q$178,">"&Q63)+COUNTIF($Q$7:Q63,Q63)-1) | V63: Élevée | W63: Headfonics import | X63: 7.7 | Y63: Reader | Z63: 45665 | AA63: 2 | AB63: https://headfonics.com/?s=Heartfield+R1 | AC63: 64-resistor R2R balanced dongle DAC | AD63: Ajout Headfonics | AE63: 40 | AF63: 140 | AG63: R2R chaleureux et naturel, séduisant pour la musicalité plus que pour l’analyse. | AH63: Chaud, analogique. | AI63: Bonne sensation organique et clarté correcte. | AJ63: Distorsion/pops et qualité de construction signalés; formats haute résolution limités. | AK63: https://headfonics.com/heartfield-r1-review/ | AL63: 3 | AM63: Élevée — 3+ sources, domaines variés | AN63: https://www.head-fi.org/showcase/heartfield-r1.27610/ | AO63: https://www.linsoul.com/products/heartfield-r1 | AP63: https://www.audiophile-heaven.com/2024/10/heartfield-r1-r2r-hifi-portable-dac-amp-low-mass-music-class.html | AQ63: Objectif atteint | AR63: Head-Fi reviews: 1; Review éditoriale: 2
A64: iBasso | B64: PB5 Osprey | C64: Portable Amp/DAC (Headfonics) | D64: Tube riche, lisse et plein. | E64: Matière/timbres, puissance, profondeur | F64: Pas d’entrée single-ended | G64: 8.9 | H64: 8.8 | I64: 9 | J64: 8.9 | K64: 9 | L64: 9.5 | M64: 8.9 | N64: 9.3 | O64: 7.2 | P64: 8.6 | Q64: =IF(COUNT(G64:P64)=10,ROUND((G64*'Pondérations'!$B$5+H64*'Pondérations'!$B$6+I64*'Pondérations'!$B$7+J64*'Pondérations'!$B$8+K64*'Pondérations'!$B$9+L64*'Pondérations'!$B$10+M64*'Pondérations'!$B$11+N64*'Pondérations'!$B$12+O64*'Pondérations'!$B$13+P64*'Pondérations'!$B$14)/'Pondérations'!$B$16,3),"") | R64: =IF(Q64="","",1+COUNTIF($Q$7:$Q$178,">"&Q64)+COUNTIF($Q$7:Q64,Q64)-1) | V64: Élevée | W64: Headfonics import | X64: 9 | Y64: Reader | Z64: 45647 | AA64: 3 | AB64: https://headfonics.com/?s=iBasso+PB5+Osprey | AC64: Dual Nutube 6P1 portable headphone amplifier, up to 1.7 W | AD64: Ajout Headfonics | AE64: 42 | AF64: 1317 | AG64: Ampli tube portable très doux, dense et charnu, avec une excellente plage dynamique et beaucoup de puissance propre. | AH64: Tube riche, lisse et plein. | AI64: Bonne dynamique, ampleur et compatibilité IEM/casque. | AJ64: Pas d’entrée single-ended; format simple et assez gros. | AK64: https://headfonics.com/ibasso-pb5-osprey-review/ | AL64: 4 | AM64: Élevée — 3+ sources, domaines variés | AN64: https://www.headfonia.com/ibasso-pb5-review/ | AO64: https://www.audiodiscourse.com/2024/04/ibasso-pb5-osprey-nutube-portable.html | AP64: https://www.audiophile-heaven.com/2024/09/ibasso-pb5-osprey-hifi-tube-amplifier-apex-analogic-musicality.html | AQ64: Objectif atteint | AR64: Review éditoriale: 4
A65: FiiO | B65: KA15 | C65: Portable Amp/DAC (Headfonics) | D65: Plutôt neutre et adaptable. | E65: Matière/timbres, profondeur, image 3d | F65: Léger bruit de fond en symétrique avec certains IEM sensibles | G65: 8.7 | H65: 8.5 | I65: 8.7 | J65: 8.6 | K65: 8.6 | L65: 9.1 | M65: 8.8 | N65: 8.9 | O65: 9.5 | P65: 8 | Q65: =IF(COUNT(G65:P65)=10,ROUND((G65*'Pondérations'!$B$5+H65*'Pondérations'!$B$6+I65*'Pondérations'!$B$7+J65*'Pondérations'!$B$8+K65*'Pondérations'!$B$9+L65*'Pondérations'!$B$10+M65*'Pondérations'!$B$11+N65*'Pondérations'!$B$12+O65*'Pondérations'!$B$13+P65*'Pondérations'!$B$14)/'Pondérations'!$B$16,3),"") | R65: =IF(Q65="","",1+COUNTIF($Q$7:$Q$178,">"&Q65)+COUNTIF($Q$7:Q65,Q65)-1) | V65: Élevée | W65: Headfonics import | X65: 8.1 | Y65: Reader | Z65: 45619 | AA65: 3 | AB65: https://headfonics.com/?s=FiiO+KA15 | AC65: Dual CS43198 dongle DAC, up to 500 mW | AD65: Ajout Headfonics | AE65: 43 | AF65: 109 | AG65: Dongle polyvalent et puissant, avec beaucoup d’options de personnalisation et un bon rapport fonctionnalités/prix. | AH65: Plutôt neutre et adaptable. | AI65: Bonne puissance; performance générale solide. | AJ65: Léger bruit de fond en symétrique avec certains IEM sensibles; menus moins intuitifs sans app. | AK65: https://headfonics.com/fiio-ka15-review/ | AL65: 4 | AM65: Élevée — 3+ sources, domaines variés | AN65: https://www.head-fi.org/showcase/fiio-ka15-dac-and-headphone-amplifier.27557/reviews | AO65: https://www.headfonia.com/fiio-ka15-review/ | AP65: https://moonstarreviews.net/fiio-ka15-review/ | AQ65: Objectif atteint | AR65: Head-Fi reviews: 1; Review éditoriale: 3
A66: TempoTec | B66: Sonata BHD Pro | C66: Portable Amp/DAC (Headfonics) | D66: Neutre variable selon pairing. | E66: Matière/timbres, image 3d, profondeur | F66: Synergie parfois difficile | G66: 8 | H66: 8.2 | I66: 8.8 | J66: 8.8 | K66: 8.8 | L66: 8 | M66: 6.5 | N66: 8.7 | O66: 9.5 | P66: 8.4 | Q66: =IF(COUNT(G66:P66)=10,ROUND((G66*'Pondérations'!$B$5+H66*'Pondérations'!$B$6+I66*'Pondérations'!$B$7+J66*'Pondérations'!$B$8+K66*'Pondérations'!$B$9+L66*'Pondérations'!$B$10+M66*'Pondérations'!$B$11+N66*'Pondérations'!$B$12+O66*'Pondérations'!$B$13+P66*'Pondérations'!$B$14)/'Pondérations'!$B$16,3),"") | R66: =IF(Q66="","",1+COUNTIF($Q$7:$Q$178,">"&Q66)+COUNTIF($Q$7:Q66,Q66)-1) | V66: Élevée | W66: Headfonics import | X66: 7 | Y66: Reader | Z66: 45609 | AA66: 3 | AB66: https://headfonics.com/?s=TempoTec+Sonata+BHD+Pro | AC66: Dual CS43131 dongle DAC, up to 280 mW | AD66: Ajout Headfonics | AE66: 44 | AF66: 61 | AG66: Dongle compact et assez puissant pour IEM et casques faciles, mais plus sensible aux associations. | AH66: Neutre variable selon pairing. | AI66: Correct techniquement pour le prix. | AJ66: Synergie parfois difficile; moins convaincant avec certains casques/IEM. | AK66: https://headfonics.com/tempotec-sonata-bhd-pro-review/ | AL66: 3 | AM66: Élevée — 3+ sources, domaines variés | AN66: https://www.head-fi.org/showcase/tempotec-sonata-bhd-pro.26579/reviews | AO66: https://forum.hifiguides.com/t/tempotec-sonata-bhd-pro-review/41099 | AQ66: Objectif atteint | AR66: Forum / communauté: 1; Head-Fi reviews: 1; Review éditoriale: 1
A67: iBasso | B67: D16 Taipan | C67: Portable Amp/DAC (Headfonics) | D67: Analogique, texturé, naturel. | E67: Image 3d, microdétail, layering | F67: Puissance insuffisante pour certains casques exigeants | G67: 9.3 | H67: 9.2 | I67: 9 | J67: 9.3 | K67: 9.1 | L67: 9.3 | M67: 9 | N67: 7 | O67: 8 | P67: 9.2 | Q67: =IF(COUNT(G67:P67)=10,ROUND((G67*'Pondérations'!$B$5+H67*'Pondérations'!$B$6+I67*'Pondérations'!$B$7+J67*'Pondérations'!$B$8+K67*'Pondérations'!$B$9+L67*'Pondérations'!$B$10+M67*'Pondérations'!$B$11+N67*'Pondérations'!$B$12+O67*'Pondérations'!$B$13+P67*'Pondérations'!$B$14)/'Pondérations'!$B$16,3),"") | R67: =IF(Q67="","",1+COUNTIF($Q$7:$Q$178,">"&Q67)+COUNTIF($Q$7:Q67,Q67)-1) | V67: Élevée | W67: Headfonics import | X67: 8.7 | Y67: Reader | Z67: 45591 | AA67: 3 | AB67: https://headfonics.com/?s=iBasso+D16+Taipan | AC67: Discrete 1-bit DAC + Super Class A amp, up to 1.125 W | AD67: Ajout Headfonics | AE67: 46 | AF67: 1490 | AG67: DAC/amp haut de gamme à la restitution analogique très texturée, avec une imagerie particulièrement immersive. | AH67: Analogique, texturé, naturel. | AI67: Imagerie holographique et grande finesse de placement. | AJ67: Puissance insuffisante pour certains casques exigeants; écran basique. | AK67: https://headfonics.com/ibasso-d16-taipan-review/ | AL67: 4 | AM67: Élevée — 3+ sources, domaines variés | AN67: https://www.head-fi.org/showcase/ibasso-d16-taipan.27482/reviews | AO67: https://www.headfonia.com/ibasso-d16-review/ | AP67: https://moonstarreviews.net/ibasso-d16-taipan-review/ | AQ67: Objectif atteint | AR67: Head-Fi reviews: 1; Review éditoriale: 3
A68: 7Hz | B68: Artemis39 | C68: Portable Amp/DAC (Headfonics) | D68: Plutôt neutre/énergique. | E68: Image 3d, matière/timbres, profondeur | F68: Le test met davantage en avant polyvalence et puissance que finesse sonore ultime | G68: 8.8 | H68: 8.6 | I68: 8.6 | J68: 8.6 | K68: 8.6 | L68: 8.9 | M68: 8.8 | N68: 8.8 | O68: 8 | P68: 8 | Q68: =IF(COUNT(G68:P68)=10,ROUND((G68*'Pondérations'!$B$5+H68*'Pondérations'!$B$6+I68*'Pondérations'!$B$7+J68*'Pondérations'!$B$8+K68*'Pondérations'!$B$9+L68*'Pondérations'!$B$10+M68*'Pondérations'!$B$11+N68*'Pondérations'!$B$12+O68*'Pondérations'!$B$13+P68*'Pondérations'!$B$14)/'Pondérations'!$B$16,3),"") | R68: =IF(Q68="","",1+COUNTIF($Q$7:$Q$178,">"&Q68)+COUNTIF($Q$7:Q68,Q68)-1) | V68: Élevée | W68: Headfonics import | X68: 8 | Y68: Reader | Z68: 45567 | AA68: 3 | AB68: https://headfonics.com/?s=7Hz+Artemis39 | AC68: Wireless ES9039Q2M dongle DAC, LDAC, up to 405 mW | AD68: Ajout Headfonics | AE68: 47 | AF68: 149 | AG68: Portable sans-fil polyvalent et puissant, avec bonne autonomie et DAC de niveau desktop. | AH68: Plutôt neutre/énergique. | AI68: Bonne réserve de puissance; spatialisation correcte. | AJ68: Le test met davantage en avant polyvalence et puissance que finesse sonore ultime. | AK68: https://headfonics.com/7hz-artemis39-review/ | AL68: 3 | AM68: Élevée — 3+ sources, domaines variés | AN68: https://www.head-fi.org/showcase/7hz-artemis-39.27382/reviews | AO68: https://www.youtube.com/watch?v=9_EumJz2pSc | AQ68: Objectif atteint | AR68: Head-Fi reviews: 1; Review éditoriale: 1; Vidéo review: 1
A69: SMSL | B69: D10 | C69: Portable Amp/DAC (Headfonics) | D69: Neutre/propre. | E69: Propreté/contrôle, microdétail, profondeur | F69: Grave peu incarné | G69: 9.1 | H69: 8.9 | I69: 8.7 | J69: 8.6 | K69: 8.8 | L69: 8.3 | M69: 8.9 | N69: 8.8 | O69: 9.5 | P69: 8.2 | Q69: =IF(COUNT(G69:P69)=10,ROUND((G69*'Pondérations'!$B$5+H69*'Pondérations'!$B$6+I69*'Pondérations'!$B$7+J69*'Pondérations'!$B$8+K69*'Pondérations'!$B$9+L69*'Pondérations'!$B$10+M69*'Pondérations'!$B$11+N69*'Pondérations'!$B$12+O69*'Pondérations'!$B$13+P69*'Pondérations'!$B$14)/'Pondérations'!$B$16,3),"") | R69: =IF(Q69="","",1+COUNTIF($Q$7:$Q$178,">"&Q69)+COUNTIF($Q$7:Q69,Q69)-1) | V69: Élevée | W69: Headfonics import | X69: 8.1 | Y69: Reader | Z69: 45555 | AA69: 3 | AB69: https://headfonics.com/?s=SMSL+D10 | AC69: Dual CS43131 balanced dongle DAC, up to 500 mW | AD69: Ajout Headfonics | AE69: 48 | AF69: 62 | AG69: Dongle simple, propre et polyvalent, mais dont le grave est jugé assez stérile. | AH69: Neutre/propre. | AI69: Lisibilité correcte, scène sans caractère marquant. | AJ69: Grave peu incarné; pas d’application. | AK69: https://headfonics.com/smsl-d10-review/ | AL69: 4 | AM69: Élevée — 3+ sources, domaines variés | AN69: https://www.head-fi.org/showcase/smsl-d10.27738/reviews | AO69: https://primeaudio.org/smsl-d10-review/ | AP69: https://www.audioreviews.org/smsl-d10-review/ | AQ69: Objectif atteint | AR69: Head-Fi reviews: 1; Review éditoriale: 3
A70: FiiO | B70: JA11 | C70: Portable Amp/DAC (Headfonics) | D70: Neutre. | E70: Layering, propreté/contrôle, microdétail | F70: Puissance moyenne | G70: 9.1 | H70: 8.9 | I70: 8.7 | J70: 8.7 | K70: 8.9 | L70: 8.9 | M70: 8.9 | N70: 7.5 | O70: 8 | P70: 8.3 | Q70: =IF(COUNT(G70:P70)=10,ROUND((G70*'Pondérations'!$B$5+H70*'Pondérations'!$B$6+I70*'Pondérations'!$B$7+J70*'Pondérations'!$B$8+K70*'Pondérations'!$B$9+L70*'Pondérations'!$B$10+M70*'Pondérations'!$B$11+N70*'Pondérations'!$B$12+O70*'Pondérations'!$B$13+P70*'Pondérations'!$B$14)/'Pondérations'!$B$16,3),"") | R70: =IF(Q70="","",1+COUNTIF($Q$7:$Q$178,">"&Q70)+COUNTIF($Q$7:Q70,Q70)-1) | V70: Élevée | W70: Headfonics import | X70: 7.5 | Y70: Reader | Z70: 45513 | AA70: 3 | AB70: https://headfonics.com/?s=FiiO+JA11 | AC70: Portable dongle DAC/amp | AD70: Ajout Headfonics | AE70: 49 | AF70: 13 | AG70: Entrée de gamme très compétitive, neutre et légère, sans coloration marquée. | AH70: Neutre. | AI70: Correcte pour le prix; PEQ utile. | AJ70: Puissance moyenne; réglages avancés dépendants de l’app FiiO. | AK70: https://headfonics.com/fiio-ja11-review/ | AL70: 4 | AM70: Élevée — 3+ sources, domaines variés | AN70: https://www.head-fi.org/showcase/fiio-ja11.27321/reviews | AO70: https://www.headfonia.com/fiio-ja11-review/ | AP70: https://mobileaudiophile.com/dacs/dongle/fiio-ja11-review-peq-on-budget/ | AQ70: Objectif atteint | AR70: Head-Fi reviews: 1; Review éditoriale: 3
A71: Shanling | B71: H2 | C71: Portable Amp/DAC (Headfonics) | D71: Doux/lisse. | E71: Image 3d, profondeur, propreté/contrôle | F71: Bluetooth ancien et application perfectible | G71: 9 | H71: 8.8 | I71: 8.7 | J71: 8.7 | K71: 8.8 | L71: 8.9 | M71: 8.9 | N71: 9 | O71: 9.3 | P71: 8.2 | Q71: =IF(COUNT(G71:P71)=10,ROUND((G71*'Pondérations'!$B$5+H71*'Pondérations'!$B$6+I71*'Pondérations'!$B$7+J71*'Pondérations'!$B$8+K71*'Pondérations'!$B$9+L71*'Pondérations'!$B$10+M71*'Pondérations'!$B$11+N71*'Pondérations'!$B$12+O71*'Pondérations'!$B$13+P71*'Pondérations'!$B$14)/'Pondérations'!$B$16,3),"") | R71: =IF(Q71="","",1+COUNTIF($Q$7:$Q$178,">"&Q71)+COUNTIF($Q$7:Q71,Q71)-1) | V71: Élevée | W71: Headfonics import | X71: 8.1 | Y71: Reader | Z71: 45509 | AA71: 3 | AB71: https://headfonics.com/?s=Shanling+H2 | AC71: CS43198 portable DAC/headphone amp | AD71: Ajout Headfonics | AE71: 50 | AF71: 149 | AG71: Portable compact et très fonctionnel, avec une restitution douce et suffisamment de puissance pour beaucoup de casques. | AH71: Doux/lisse. | AI71: Bonne polyvalence plus que démonstration technique. | AJ71: Bluetooth ancien et application perfectible. | AK71: https://headfonics.com/shanling-h2-review/ | AL71: 3 | AM71: Élevée — 3+ sources, domaines variés | AN71: https://www.headfonia.com/shanling-h2-review/ | AO71: https://www.head-fi.org/threads/introducing-shanling-h2-budget-portable-dac-amp-with-built-in-player.970935/ | AQ71: Objectif atteint | AR71: Head-Fi forum: 1; Review éditoriale: 2
A72: LETSHUOER | B72: DT03 | C72: Portable Amp/DAC (Headfonics) | D72: Lean, assez clair. | E72: Dynamique, layering, profondeur | F72: Médium trop mince selon le test | G72: 8.9 | H72: 8.7 | I72: 8.6 | J72: 8.5 | K72: 8.8 | L72: 8.6 | M72: 7.8 | N72: 9.1 | O72: 9.5 | P72: 8 | Q72: =IF(COUNT(G72:P72)=10,ROUND((G72*'Pondérations'!$B$5+H72*'Pondérations'!$B$6+I72*'Pondérations'!$B$7+J72*'Pondérations'!$B$8+K72*'Pondérations'!$B$9+L72*'Pondérations'!$B$10+M72*'Pondérations'!$B$11+N72*'Pondérations'!$B$12+O72*'Pondérations'!$B$13+P72*'Pondérations'!$B$14)/'Pondérations'!$B$16,3),"") | R72: =IF(Q72="","",1+COUNTIF($Q$7:$Q$178,">"&Q72)+COUNTIF($Q$7:Q72,Q72)-1) | V72: Élevée | W72: Headfonics import | X72: 7.8 | Y72: Reader | Z72: 45495 | AA72: 3 | AB72: https://headfonics.com/?s=LETSHUOER+DT03 | AC72: Portable dongle DAC/amp | AD72: Ajout Headfonics | AE72: 52 | AF72: 87 | AG72: Dongle polyvalent mais au médium maigre; l’association avec les IEM devient déterminante. | AH72: Lean, assez clair. | AI72: Correct en technique, mais dynamique et matière moyennes. | AJ72: Médium trop mince selon le test. | AK72: https://headfonics.com/letshuoer-dt03-review/ | AL72: 4 | AM72: Élevée — 3+ sources, domaines variés | AN72: https://www.head-fi.org/showcase/letshuoer-dt03.27289/reviews | AO72: https://mobileaudiophile.com/dacs/dongle/letshuoer-dt03-dongle-review-unsuspecting-power-can/ | AP72: https://ichos-reviews.com/letshuoer-dt03-review/ | AQ72: Objectif atteint | AR72: Head-Fi reviews: 1; Review éditoriale: 3
A73: Kiwi Ears | B73: Allegro | C73: Portable Amp/DAC (Headfonics) | D73: Bas chaleureux, haut brillant/sibilant. | E73: Image 3d, layering, propreté/contrôle | F73: Synergie délicate | G73: 9.1 | H73: 8.2 | I73: 8.8 | J73: 8.8 | K73: 8.9 | L73: 9 | M73: 8.9 | N73: 7.8 | O73: 9.5 | P73: 8.5 | Q73: =IF(COUNT(G73:P73)=10,ROUND((G73*'Pondérations'!$B$5+H73*'Pondérations'!$B$6+I73*'Pondérations'!$B$7+J73*'Pondérations'!$B$8+K73*'Pondérations'!$B$9+L73*'Pondérations'!$B$10+M73*'Pondérations'!$B$11+N73*'Pondérations'!$B$12+O73*'Pondérations'!$B$13+P73*'Pondérations'!$B$14)/'Pondérations'!$B$16,3),"") | R73: =IF(Q73="","",1+COUNTIF($Q$7:$Q$178,">"&Q73)+COUNTIF($Q$7:Q73,Q73)-1) | V73: Élevée | W73: Headfonics import | X73: 7.7 | Y73: Reader | Z73: 45476 | AA73: 3 | AB73: https://headfonics.com/?s=Kiwi+Ears+Allegro | AC73: Portable dongle DAC/amp | AD73: Ajout Headfonics | AE73: 53 | AF73: 53 | AG73: Dongle original et bien construit, mais à la signature contrastée entre chaleur du bas et aigu potentiellement agressif. | AH73: Bas chaleureux, haut brillant/sibilant. | AI73: Bonne polyvalence d’I/O, scène correcte. | AJ73: Synergie délicate; sibilance possible. | AK73: https://headfonics.com/kiwi-ears-allegro-review/ | AL73: 4 | AM73: Élevée — 3+ sources, domaines variés | AN73: https://www.head-fi.org/showcase/kiwi-ears-allegro.27061/reviews | AO73: https://www.pragmaticaudio.com/reviews/2024/11/kiwi-ears-allegro/ | AP73: https://www.audiodiscourse.com/2024/03/kiwi-ears-allegro-portable-dac-review.html | AQ73: Objectif atteint | AR73: Head-Fi reviews: 1; Review éditoriale: 3
A74: Hidizs | B74: S8 Pro Robin | C74: Portable Amp/DAC (Headfonics) | D74: Douce, chaude, légèrement en V | E74: Profondeur, matière/timbres, image 3d | F74: Moins détaillé, fond moins silencieux avec IEM sensibles et puissance seulement moyenne | G74: 8.9 | H74: 8 | I74: 9.2 | J74: 8.9 | K74: 8.9 | L74: 9.3 | M74: 8.9 | N74: 8.9 | O74: 8 | P74: 8.6 | Q74: =IF(COUNT(G74:P74)=10,ROUND((G74*'Pondérations'!$B$5+H74*'Pondérations'!$B$6+I74*'Pondérations'!$B$7+J74*'Pondérations'!$B$8+K74*'Pondérations'!$B$9+L74*'Pondérations'!$B$10+M74*'Pondérations'!$B$11+N74*'Pondérations'!$B$12+O74*'Pondérations'!$B$13+P74*'Pondérations'!$B$14)/'Pondérations'!$B$16,3),"") | R74: =IF(Q74="","",1+COUNTIF($Q$7:$Q$178,">"&Q74)+COUNTIF($Q$7:Q74,Q74)-1) | V74: Élevée | W74: Headfonics import | X74: 8 | Y74: Reader | Z74: 45471 | AA74: 3 | AB74: https://headfonics.com/?s=Hidizs+S8+Pro+Robin | AC74: Portable dongle DAC/amp | AD74: Ajout Headfonics | AE74: 54 | AF74: 69.52 | AG74: Le S8 Pro Robin privilégie une écoute douce et chaleureuse avec plusieurs filtres. Il offre un grave convenablement autoritaire mais sacrifie une partie du microdétail. | AH74: Douce, chaude, légèrement en V | AI74: Bonne profondeur et poids des notes, surtout en 4,4 mm; séparation et placement plus modestes que les modèles Hidizs supérieurs. | AJ74: Moins détaillé, fond moins silencieux avec IEM sensibles et puissance seulement moyenne. | AK74: https://headfonics.com/hidizs-s8-pro-robin-review/ | AL74: 4 | AM74: Élevée — 3+ sources, domaines variés | AN74: https://www.head-fi.org/showcase/hidizs-s8-pro-robin.27188/reviews | AO74: https://www.techradar.com/audio/hi-fi/hidizs-s8-pro-robin-review | AP74: https://www.headfonia.com/hidizs-s8-pro-robin-review/ | AQ74: Objectif atteint | AR74: Head-Fi reviews: 1; Review éditoriale: 3
A75: iFi audio | B75: GO bar Kensei | C75: Portable Amp/DAC (Headfonics) | D75: Neutre-naturel, modulable via filtres/K2HD. | E75: Microdétail, matière/timbres, dynamique | F75: Chauffe et peut vider rapidement la batterie du téléphone | G75: 9.1 | H75: 9.1 | I75: 8.7 | J75: 8.7 | K75: 8.8 | L75: 9.1 | M75: 9 | N75: 8.7 | O75: 9.3 | P75: 8.4 | Q75: =IF(COUNT(G75:P75)=10,ROUND((G75*'Pondérations'!$B$5+H75*'Pondérations'!$B$6+I75*'Pondérations'!$B$7+J75*'Pondérations'!$B$8+K75*'Pondérations'!$B$9+L75*'Pondérations'!$B$10+M75*'Pondérations'!$B$11+N75*'Pondérations'!$B$12+O75*'Pondérations'!$B$13+P75*'Pondérations'!$B$14)/'Pondérations'!$B$16,3),"") | R75: =IF(Q75="","",1+COUNTIF($Q$7:$Q$178,">"&Q75)+COUNTIF($Q$7:Q75,Q75)-1) | V75: Élevée | W75: Headfonics import | X75: 8.1 | Y75: Reader | Z75: 45465 | AA75: 3 | AB75: https://headfonics.com/?s=iFi+audio+GO+bar+Kensei | AC75: Portable dongle DAC/amp | AD75: Ajout Headfonics | AE75: 55 | AF75: 449 | AG75: Dongle premium très abouti, jugé excellent en qualité sonore et riche en options de réglage. | AH75: Neutre-naturel, modulable via filtres/K2HD. | AI75: Très bonne définition et bonne réserve de puissance. | AJ75: Chauffe et peut vider rapidement la batterie du téléphone. | AK75: https://headfonics.com/ifi-audio-go-bar-kensei-review/ | AL75: 4 | AM75: Élevée — 3+ sources, domaines variés | AN75: https://www.head-fi.org/showcase/ifi-audio-go-bar-kensei.27123/reviews | AO75: https://www.headfonia.com/ifi-audio-go-bar-kensei-review/ | AP75: https://www.techradar.com/audio/hi-fi/ifi-go-bar-kensei-review | AQ75: Objectif atteint | AR75: Head-Fi reviews: 1; Review éditoriale: 3
A76: ONIX | B76: Mystic XP1 | C76: Portable Amp/DAC (Headfonics) | D76: Doux, dense, grave charnu. | E76: Puissance, profondeur, matière/timbres | F76: Impédance de sortie élevée peu idéale pour certains IEM | G76: 8.8 | H76: 8.7 | I76: 9.1 | J76: 8.8 | K76: 8.9 | L76: 9.3 | M76: 8.9 | N76: 9.3 | O76: 6.5 | P76: 8.4 | Q76: =IF(COUNT(G76:P76)=10,ROUND((G76*'Pondérations'!$B$5+H76*'Pondérations'!$B$6+I76*'Pondérations'!$B$7+J76*'Pondérations'!$B$8+K76*'Pondérations'!$B$9+L76*'Pondérations'!$B$10+M76*'Pondérations'!$B$11+N76*'Pondérations'!$B$12+O76*'Pondérations'!$B$13+P76*'Pondérations'!$B$14)/'Pondérations'!$B$16,3),"") | R76: =IF(Q76="","",1+COUNTIF($Q$7:$Q$178,">"&Q76)+COUNTIF($Q$7:Q76,Q76)-1) | V76: Élevée | W76: Headfonics import | X76: 8.7 | Y76: Reader | Z76: 45439 | AA76: 3 | AB76: https://headfonics.com/?s=ONIX+Mystic+XP1 | AC76: Portable amplifier/DAC | AD76: Ajout Headfonics | AE76: 56 | AF76: 1317 | AG76: Solution transportable très puissante au rendu lisse, avec un grave dense et une profondeur particulièrement addictive. | AH76: Doux, dense, grave charnu. | AI76: Très bonne profondeur et forte réserve dynamique. | AJ76: Impédance de sortie élevée peu idéale pour certains IEM; gros format. | AK76: https://headfonics.com/onix-mystic-xp1-review/ | AL76: 3 | AM76: Élevée — 3+ sources, domaines variés | AN76: https://www.head-fi.org/showcase/onix-mystic-xp1-%E2%80%93-high-end-portable-dac-amp.27530/reviews | AO76: https://www.head-fi.org/threads/introducing-onix-mystic-xp1-%E2%80%93-high-end-portable-dac-amp.970241/ | AQ76: Objectif atteint | AR76: Head-Fi forum: 1; Head-Fi reviews: 1; Review éditoriale: 1
A77: Shanling | B77: UA4 | C77: Portable Amp/DAC (Headfonics) | D77: Neutre/propre. | E77: Image 3d, profondeur, propreté/contrôle | F77: Application Eddict encore perfectible | G77: 8.9 | H77: 8.7 | I77: 8.6 | J77: 8.6 | K77: 8.7 | L77: 8.8 | M77: 8.8 | N77: 7.5 | O77: 9.5 | P77: 8.1 | Q77: =IF(COUNT(G77:P77)=10,ROUND((G77*'Pondérations'!$B$5+H77*'Pondérations'!$B$6+I77*'Pondérations'!$B$7+J77*'Pondérations'!$B$8+K77*'Pondérations'!$B$9+L77*'Pondérations'!$B$10+M77*'Pondérations'!$B$11+N77*'Pondérations'!$B$12+O77*'Pondérations'!$B$13+P77*'Pondérations'!$B$14)/'Pondérations'!$B$16,3),"") | R77: =IF(Q77="","",1+COUNTIF($Q$7:$Q$178,">"&Q77)+COUNTIF($Q$7:Q77,Q77)-1) | V77: Élevée | W77: Headfonics import | X77: 7.5 | Y77: Reader | Z77: 45425 | AA77: 3 | AB77: https://headfonics.com/?s=Shanling+UA4 | AC77: Portable dongle DAC/amp | AD77: Ajout Headfonics | AE77: 57 | AF77: 99 | AG77: Dongle propre, peu énergivore et convaincant en spatialisation pour son prix. | AH77: Neutre/propre. | AI77: Bonne scène et bonne lisibilité globale. | AJ77: Application Eddict encore perfectible. | AK77: https://headfonics.com/shanling-ua4-review/ | AL77: 3 | AM77: Élevée — 3+ sources, domaines variés | AN77: https://www.headfonia.com/shanling-ua4-review/ | AO77: https://www.reddit.com/r/headphones/comments/1bbvgpf | AQ77: Objectif atteint | AR77: Communauté Reddit: 1; Review éditoriale: 2
A78: FiiO | B78: KA11 | C78: Portable Amp/DAC (Headfonics) | D78: Légèrement chaud/coloré. | E78: Matière/timbres, image 3d, profondeur | F78: Coloration peu adaptée aux amateurs de stricte neutralité | G78: 8.9 | H78: 8.7 | I78: 8.8 | J78: 8.8 | K78: 8.8 | L78: 9.2 | M78: 8.9 | N78: 8.9 | O78: 9.5 | P78: 8.3 | Q78: =IF(COUNT(G78:P78)=10,ROUND((G78*'Pondérations'!$B$5+H78*'Pondérations'!$B$6+I78*'Pondérations'!$B$7+J78*'Pondérations'!$B$8+K78*'Pondérations'!$B$9+L78*'Pondérations'!$B$10+M78*'Pondérations'!$B$11+N78*'Pondérations'!$B$12+O78*'Pondérations'!$B$13+P78*'Pondérations'!$B$14)/'Pondérations'!$B$16,3),"") | R78: =IF(Q78="","",1+COUNTIF($Q$7:$Q$178,">"&Q78)+COUNTIF($Q$7:Q78,Q78)-1) | V78: Élevée | W78: Headfonics import | Y78: Reader (non relevé) | Z78: 45418 | AA78: 3 | AB78: https://headfonics.com/?s=FiiO+KA11 | AC78: Portable dongle DAC/amp | AD78: Ajout Headfonics | AE78: 58 | AF78: 26 | AG78: Très petit dongle puissant et légèrement chaleureux, agréable pour un usage nomade simple. | AH78: Légèrement chaud/coloré. | AI78: Bonne énergie pour le format. | AJ78: Coloration peu adaptée aux amateurs de stricte neutralité. | AK78: https://headfonics.com/fiio-ka11-review/ | AL78: 4 | AM78: Élevée — 3+ sources, domaines variés | AN78: https://www.head-fi.org/showcase/fiio-ka11.27035/reviews | AO78: https://www.headfonia.com/fiio-ka11-review/ | AP78: https://www.androidcentral.com/accessories/audio/fiio-ka11-review | AQ78: Objectif atteint | AR78: Head-Fi reviews: 1; Review éditoriale: 3
A79: FiiO | B79: KA17 | C79: Portable Amp/DAC (Headfonics) | D79: Plutôt neutre/énergique. | E79: Propreté/contrôle, image 3d, profondeur | F79: Chauffe, châssis massif et arêtes vives | G79: 9.1 | H79: 8.8 | I79: 8.7 | J79: 8.7 | K79: 8.8 | L79: 8.8 | M79: 8.9 | N79: 8.7 | O79: 9.3 | P79: 8.2 | Q79: =IF(COUNT(G79:P79)=10,ROUND((G79*'Pondérations'!$B$5+H79*'Pondérations'!$B$6+I79*'Pondérations'!$B$7+J79*'Pondérations'!$B$8+K79*'Pondérations'!$B$9+L79*'Pondérations'!$B$10+M79*'Pondérations'!$B$11+N79*'Pondérations'!$B$12+O79*'Pondérations'!$B$13+P79*'Pondérations'!$B$14)/'Pondérations'!$B$16,3),"") | R79: =IF(Q79="","",1+COUNTIF($Q$7:$Q$178,">"&Q79)+COUNTIF($Q$7:Q79,Q79)-1) | V79: Élevée | W79: Headfonics import | Y79: Reader (non relevé) | Z79: 45409 | AA79: 3 | AB79: https://headfonics.com/?s=FiiO+KA17 | AC79: Portable dongle DAC/amp | AD79: Ajout Headfonics | AE79: 59 | AF79: 159 | AG79: Flagship dongle très polyvalent, puissant et doté d’une scène convaincante. | AH79: Plutôt neutre/énergique. | AI79: Bonne spatialisation et forte puissance. | AJ79: Chauffe, châssis massif et arêtes vives. | AK79: https://headfonics.com/fiio-ka17-review/ | AL79: 4 | AM79: Élevée — 3+ sources, domaines variés | AN79: https://www.head-fi.org/showcase/fiio-ka17.26982/reviews | AO79: https://www.headfonia.com/fiio-ka17-review/ | AP79: https://primeaudio.org/fiio-ka17-review/ | AQ79: Objectif atteint | AR79: Head-Fi reviews: 1; Review éditoriale: 3
A80: Colorfly | B80: CDA-M2 | C80: Portable Amp/DAC (Headfonics) | D80: Neutre/clean. | E80: Propreté/contrôle, microdétail, dynamique | F80: Chauffe rapidement | G80: 9 | H80: 8.8 | I80: 8.6 | J80: 8.5 | K80: 8.7 | L80: 8.7 | M80: 8.9 | N80: 9.1 | O80: 9.3 | P80: 8 | Q80: =IF(COUNT(G80:P80)=10,ROUND((G80*'Pondérations'!$B$5+H80*'Pondérations'!$B$6+I80*'Pondérations'!$B$7+J80*'Pondérations'!$B$8+K80*'Pondérations'!$B$9+L80*'Pondérations'!$B$10+M80*'Pondérations'!$B$11+N80*'Pondérations'!$B$12+O80*'Pondérations'!$B$13+P80*'Pondérations'!$B$14)/'Pondérations'!$B$16,3),"") | R80: =IF(Q80="","",1+COUNTIF($Q$7:$Q$178,">"&Q80)+COUNTIF($Q$7:Q80,Q80)-1) | V80: Élevée | W80: Headfonics import | X80: 8 | Y80: Reader | Z80: 45408 | AA80: 3 | AB80: https://headfonics.com/?s=Colorfly+CDA-M2 | AC80: Portable dongle DAC/amp | AD80: Ajout Headfonics | AE80: 60 | AF80: 140 | AG80: Dongle premium neutre et propre, avec beaucoup de contrôle et de fonctions. | AH80: Neutre/clean. | AI80: Bonne clarté et polyvalence; restitution plutôt droite. | AJ80: Chauffe rapidement; accessoires limités. | AK80: https://headfonics.com/colorfly-cda-m2-review/ | AL80: 4 | AM80: Élevée — 3+ sources, domaines variés | AN80: https://www.headphonesty.com/2024/08/colorfly-cda-m2-review/ | AO80: https://primeaudio.org/colorfly-cda-m2-review/ | AP80: https://moonstarreviews.net/colorfly-cda-m2-review/ | AQ80: Objectif atteint | AR80: Review éditoriale: 4
A81: ddHiFi | B81: TC44Pro E2 | C81: Portable Amp/DAC (Headfonics) | D81: Neutre, légèrement charnu. | E81: Propreté/contrôle, microdétail, matière/timbres | F81: Grand pour un dongle | G81: 9.4 | H81: 9 | I81: 8.8 | J81: 8.7 | K81: 8.9 | L81: 9.1 | M81: 9 | N81: 8.4 | O81: 9.5 | P81: 8.5 | Q81: =IF(COUNT(G81:P81)=10,ROUND((G81*'Pondérations'!$B$5+H81*'Pondérations'!$B$6+I81*'Pondérations'!$B$7+J81*'Pondérations'!$B$8+K81*'Pondérations'!$B$9+L81*'Pondérations'!$B$10+M81*'Pondérations'!$B$11+N81*'Pondérations'!$B$12+O81*'Pondérations'!$B$13+P81*'Pondérations'!$B$14)/'Pondérations'!$B$16,3),"") | R81: =IF(Q81="","",1+COUNTIF($Q$7:$Q$178,">"&Q81)+COUNTIF($Q$7:Q81,Q81)-1) | V81: Élevée | W81: Headfonics import | X81: 8 | Y81: Reader | Z81: 45394 | AA81: 4 | AB81: https://headfonics.com/?s=ddHiFi+TC44Pro+E2 | AC81: Portable dongle DAC/amp | AD81: Ajout Headfonics | AE81: 61 | AF81: 79 | AG81: Dongle neutre avec très bonne résolution, tout en conservant du poids et de la texture dans les notes. | AH81: Neutre, légèrement charnu. | AI81: Bonne résolution et bonne densité. | AJ81: Grand pour un dongle; peu de fonctions pour le prix. | AK81: https://headfonics.com/ddhifi-tc44pro-e2-review/ | AL81: 4 | AM81: Élevée — 3+ sources, domaines variés | AN81: https://www.head-fi.org/showcase/ddhifi-tc44pro-e2.27259/reviews | AO81: https://www.headfonia.com/ddhifi-tc44pro-e2-review/ | AP81: https://audio46.com/blogs/headphones/ddhifi-tc44pro-e2-review | AQ81: Objectif atteint | AR81: Head-Fi reviews: 1; Review éditoriale: 3
A82: Hidizs | B82: SD2 | C82: Portable Amp/DAC (Headfonics) | D82: Plutôt neutre. | E82: Image 3d, profondeur, matière/timbres | F82: Se raye facilement | G82: 8.9 | H82: 8.7 | I82: 8.9 | J82: 8.9 | K82: 8.9 | L82: 9.1 | M82: 8.9 | N82: 8.1 | O82: 9.5 | P82: 8.5 | Q82: =IF(COUNT(G82:P82)=10,ROUND((G82*'Pondérations'!$B$5+H82*'Pondérations'!$B$6+I82*'Pondérations'!$B$7+J82*'Pondérations'!$B$8+K82*'Pondérations'!$B$9+L82*'Pondérations'!$B$10+M82*'Pondérations'!$B$11+N82*'Pondérations'!$B$12+O82*'Pondérations'!$B$13+P82*'Pondérations'!$B$14)/'Pondérations'!$B$16,3),"") | R82: =IF(Q82="","",1+COUNTIF($Q$7:$Q$178,">"&Q82)+COUNTIF($Q$7:Q82,Q82)-1) | V82: Élevée | W82: Headfonics import | X82: 7.8 | Y82: Reader | Z82: 45359 | AA82: 4 | AB82: https://headfonics.com/?s=Hidizs+SD2 | AC82: Portable dongle DAC/amp | AD82: Ajout Headfonics | AE82: 62 | AF82: 44 | AG82: Petit dongle universel surtout réussi par sa portabilité et sa capacité à ouvrir la scène des IEM. | AH82: Plutôt neutre. | AI82: Améliore sensiblement l’ouverture avec des IEM. | AJ82: Se raye facilement; design particulier. | AK82: https://headfonics.com/hidizs-sd2-review/ | AL82: 3 | AM82: Élevée — 3+ sources, domaines variés | AN82: https://www.head-fi.org/showcase/hidizs-sd2.27003/reviews | AO82: https://mobileaudiophile.com/dacs/dongle/hidizs-sd2-review-enjoy-the-versatility/ | AQ82: Objectif atteint | AR82: Head-Fi reviews: 1; Review éditoriale: 2
A83: Colorfly | B83: CDA-M1P | C83: Portable Amp/DAC (Headfonics) | D83: Neutre/transparent. | E83: Layering, image 3d, profondeur | F83: Chauffe beaucoup et reste lourd pour un dongle | G83: 9.1 | H83: 8.9 | I83: 9 | J83: 9 | K83: 9.2 | L83: 9.2 | M83: 9 | N83: 8.9 | O83: 9.3 | P83: 8.7 | Q83: =IF(COUNT(G83:P83)=10,ROUND((G83*'Pondérations'!$B$5+H83*'Pondérations'!$B$6+I83*'Pondérations'!$B$7+J83*'Pondérations'!$B$8+K83*'Pondérations'!$B$9+L83*'Pondérations'!$B$10+M83*'Pondérations'!$B$11+N83*'Pondérations'!$B$12+O83*'Pondérations'!$B$13+P83*'Pondérations'!$B$14)/'Pondérations'!$B$16,3),"") | R83: =IF(Q83="","",1+COUNTIF($Q$7:$Q$178,">"&Q83)+COUNTIF($Q$7:Q83,Q83)-1) | V83: Élevée | W83: Headfonics import | X83: 8.2 | Y83: Reader | Z83: 45350 | AA83: 4 | AB83: https://headfonics.com/?s=Colorfly+CDA-M1P | AC83: Portable dongle DAC/amp | AD83: Ajout Headfonics | AE83: 63 | AF83: 69 | AG83: Dongle très neutre et sans coloration, avec bonne clarté du grave et des médiums. | AH83: Neutre/transparent. | AI83: Bonne scène avec IEM et bonne séparation. | AJ83: Chauffe beaucoup et reste lourd pour un dongle. | AK83: https://headfonics.com/colorfly-cda-m1p-review/ | AL83: 4 | AM83: Élevée — 3+ sources, domaines variés | AN83: https://www.head-fi.org/showcase/colorfly-cda-m1p-portable-hifi-dsd512-usb-ak4493seq-dac-amplifier.27007/reviews | AO83: https://www.audioreviews.org/colorfly-cda-m1p-review-dw/ | AP83: https://androidbrick.com/colorfly-cda-m1p-review/ | AQ83: Objectif atteint | AR83: Head-Fi reviews: 1; Review éditoriale: 3
A84: FiiO | B84: Q15 | C84: Portable Amp/DAC (Headfonics) | D84: Neutre/technique, polyvalent. | E84: Propreté/contrôle, dynamique, microdétail | F84: Assez volumineux pour un usage empilé avec téléphone | G84: 9.2 | H84: 8.9 | I84: 8.7 | J84: 8.7 | K84: 8.8 | L84: 8.8 | M84: 9 | N84: 8.7 | O84: 8 | P84: 8.3 | Q84: =IF(COUNT(G84:P84)=10,ROUND((G84*'Pondérations'!$B$5+H84*'Pondérations'!$B$6+I84*'Pondérations'!$B$7+J84*'Pondérations'!$B$8+K84*'Pondérations'!$B$9+L84*'Pondérations'!$B$10+M84*'Pondérations'!$B$11+N84*'Pondérations'!$B$12+O84*'Pondérations'!$B$13+P84*'Pondérations'!$B$14)/'Pondérations'!$B$16,3),"") | R84: =IF(Q84="","",1+COUNTIF($Q$7:$Q$178,">"&Q84)+COUNTIF($Q$7:Q84,Q84)-1) | V84: Élevée | W84: Headfonics import | Y84: Reader (non relevé) | Z84: 45339 | AA84: 4 | AB84: https://headfonics.com/?s=FiiO+Q15 | AC84: Portable DAC/amp | AD84: Ajout Headfonics | AE84: 64 | AF84: 351 | AG84: Portable très complet, bien construit et silencieux, avec une résolution solide et assez de puissance pour beaucoup de casques. | AH84: Neutre/technique, polyvalent. | AI84: Bonne résolution, très bon contrôle du bruit et dynamique robuste. | AJ84: Assez volumineux pour un usage empilé avec téléphone. | AK84: https://headfonics.com/fiio-q15-review/ | AL84: 4 | AM84: Élevée — 3+ sources, domaines variés | AN84: https://www.head-fi.org/showcase/fiio-q15.26846/reviews | AO84: https://www.headfonia.com/fiio-q15-review/ | AP84: https://www.androidcentral.com/accessories/audio/fiio-q15-review | AQ84: Objectif atteint | AR84: Head-Fi reviews: 1; Review éditoriale: 3
A85: iFi audio | B85: iDSD Diablo 2 | C85: Portable Amp/DAC (Headfonics) | D85: Énergique, plutôt neutre-vif. | E85: Image 3d, propreté/contrôle, microdétail | F85: Peu pocket-friendly | G85: 9.1 | H85: 8.9 | I85: 8.7 | J85: 8.8 | K85: 8.8 | L85: 9 | M85: 8.9 | N85: 8.9 | O85: 8 | P85: 8.3 | Q85: =IF(COUNT(G85:P85)=10,ROUND((G85*'Pondérations'!$B$5+H85*'Pondérations'!$B$6+I85*'Pondérations'!$B$7+J85*'Pondérations'!$B$8+K85*'Pondérations'!$B$9+L85*'Pondérations'!$B$10+M85*'Pondérations'!$B$11+N85*'Pondérations'!$B$12+O85*'Pondérations'!$B$13+P85*'Pondérations'!$B$14)/'Pondérations'!$B$16,3),"") | R85: =IF(Q85="","",1+COUNTIF($Q$7:$Q$178,">"&Q85)+COUNTIF($Q$7:Q85,Q85)-1) | V85: Élevée | W85: Headfonics import | X85: 8.8 | Y85: Reader | Z85: 45318 | AA85: 4 | AB85: https://headfonics.com/?s=iFi+audio+iDSD+Diablo+2 | AC85: Transportable/portable DAC/amp | AD85: Ajout Headfonics | AE85: 65 | AF85: 1141 | AG85: Évolution nette du Diablo original, plus détaillée, énergique et très polyvalente. | AH85: Énergique, plutôt neutre-vif. | AI85: Très bonne production de détail, faible bruit de fond et forte puissance. | AJ85: Peu pocket-friendly; déséquilibre de canal à très faible volume. | AK85: https://headfonics.com/ifi-audio-idsd-diablo-2-review/ | AL85: 4 | AM85: Élevée — 3+ sources, domaines variés | AN85: https://www.head-fi.org/showcase/ifi-audio-idsd-diablo-2.26962/reviews | AO85: https://www.techradar.com/audio/hi-fi/ifi-idsd-diablo-2-review-the-red-dacs-more-devilishly-good-second-time-around | AP85: https://audio46.com/blogs/headphones/ifi-diablo-2-review | AQ85: Objectif atteint | AR85: Head-Fi reviews: 1; Review éditoriale: 3
A86: ddHiFi | B86: TC35Pro Eye2 & Mountain2 | C86: Portable Amp/DAC (Headfonics) | D86: Fraîche, énergique | E86: Puissance, dynamique, propreté/contrôle | F86: Peu de fonctions | G86: 9.2 | H86: 8.9 | I86: 8.6 | J86: 8.5 | K86: 8.8 | L86: 8.6 | M86: 9.1 | N86: 7.5 | O86: 9.5 | P86: 8.1 | Q86: =IF(COUNT(G86:P86)=10,ROUND((G86*'Pondérations'!$B$5+H86*'Pondérations'!$B$6+I86*'Pondérations'!$B$7+J86*'Pondérations'!$B$8+K86*'Pondérations'!$B$9+L86*'Pondérations'!$B$10+M86*'Pondérations'!$B$11+N86*'Pondérations'!$B$12+O86*'Pondérations'!$B$13+P86*'Pondérations'!$B$14)/'Pondérations'!$B$16,3),"") | R86: =IF(Q86="","",1+COUNTIF($Q$7:$Q$178,">"&Q86)+COUNTIF($Q$7:Q86,Q86)-1) | V86: Élevée | W86: Headfonics import | X86: 7.9 | Y86: Reader | Z86: 45294 | AA86: 4 | AB86: https://headfonics.com/?s=ddHiFi+TC35Pro+Eye2+%26+Mountain2 | AC86: Portable USB DAC adapters | AD86: Ajout Headfonics | AE86: 66 | AF86: 62 | AG86: Deux dongles équilibrés, assez résolvants, à la tonalité plutôt fraîche et énergique; adaptés surtout aux IEM milieu de gamme. | AH86: Fraîche, énergique | AI86: Bonne résolution et séparation générale, sans puissance ni scène exceptionnelles | AJ86: Peu de fonctions; puissance moyenne pour le prix | AK86: https://headfonics.com/ddhifi-tc35pro-eye2-mountain2-review/ | AL86: 3 | AM86: Élevée — 3+ sources, domaines variés | AN86: https://www.headfonia.com/ddhifi-tc35pro-eye2-mountain2-review/ | AO86: https://androidbrick.com/ddhifi-tc35pro-eye2-and-mountain2-review/ | AQ86: Objectif atteint | AR86: Review éditoriale: 3
A87: Shanling | B87: UA1 Plus | C87: Portable Amp/DAC (Headfonics) | D87: Neutre/propre. | E87: Propreté/contrôle, dynamique, microdétail | F87: Puissance limitée | G87: 9.4 | H87: 8.9 | I87: 8.6 | J87: 8.4 | K87: 8.8 | L87: 8.7 | M87: 9 | N87: 7 | O87: 9.5 | P87: 8.3 | Q87: =IF(COUNT(G87:P87)=10,ROUND((G87*'Pondérations'!$B$5+H87*'Pondérations'!$B$6+I87*'Pondérations'!$B$7+J87*'Pondérations'!$B$8+K87*'Pondérations'!$B$9+L87*'Pondérations'!$B$10+M87*'Pondérations'!$B$11+N87*'Pondérations'!$B$12+O87*'Pondérations'!$B$13+P87*'Pondérations'!$B$14)/'Pondérations'!$B$16,3),"") | R87: =IF(Q87="","",1+COUNTIF($Q$7:$Q$178,">"&Q87)+COUNTIF($Q$7:Q87,Q87)-1) | V87: Élevée | W87: Headfonics import | X87: 8 | Y87: Reader | Z87: 45290 | AA87: 4 | AB87: https://headfonics.com/?s=Shanling+UA1+Plus | AC87: Portable dongle DAC/amp | AD87: Ajout Headfonics | AE87: 67 | AF87: 43 | AG87: Petit dongle sobre et peu énergivore, avec fond sombre et qualité correcte pour IEM. | AH87: Neutre/propre. | AI87: Fond noir et fluidité correcte; spatialisation modeste. | AJ87: Puissance limitée. | AK87: https://headfonics.com/shanling-ua1-plus-review/ | AL87: 4 | AM87: Élevée — 3+ sources, domaines variés | AN87: https://www.head-fi.org/showcase/shanling-ua1-plus.26636/reviews | AO87: https://androidbrick.com/shanling-ua1-plus-review/ | AP87: https://ichos-reviews.com/shanling-ua1-plus-review/ | AQ87: Objectif atteint | AR87: Head-Fi reviews: 1; Review éditoriale: 3
A88: iFi audio | B88: hip-dac 3 | C88: Portable Amp/DAC (Headfonics) | D88: Légèrement chaud/organique. | E88: Propreté/contrôle, microdétail, puissance | F88: Pas d’app de contrôle | G88: 9.4 | H88: 9.1 | I88: 8.6 | J88: 8.5 | K88: 8.8 | L88: 8.8 | M88: 9.1 | N88: 9.2 | O88: 7.2 | P88: 8.2 | Q88: =IF(COUNT(G88:P88)=10,ROUND((G88*'Pondérations'!$B$5+H88*'Pondérations'!$B$6+I88*'Pondérations'!$B$7+J88*'Pondérations'!$B$8+K88*'Pondérations'!$B$9+L88*'Pondérations'!$B$10+M88*'Pondérations'!$B$11+N88*'Pondérations'!$B$12+O88*'Pondérations'!$B$13+P88*'Pondérations'!$B$14)/'Pondérations'!$B$16,3),"") | R88: =IF(Q88="","",1+COUNTIF($Q$7:$Q$178,">"&Q88)+COUNTIF($Q$7:Q88,Q88)-1) | V88: Élevée | W88: Headfonics import | X88: 8.1 | Y88: Reader | Z88: 45271 | AA88: 4 | AB88: https://headfonics.com/?s=iFi+audio+hip-dac+3 | AC88: Battery portable DAC/amp | AD88: Ajout Headfonics | AE88: 68 | AF88: 199 | AG88: Version la plus aboutie du hip-dac, avec fond sombre, puissance correcte et meilleure gestion des IEM grâce à IEMatch. | AH88: Légèrement chaud/organique. | AI88: Bonne dynamique et bruit très bas. | AJ88: Pas d’app de contrôle; format toujours plus gros qu’un dongle. | AK88: https://headfonics.com/ifi-audio-hip-dac-3-review/ | AL88: 4 | AM88: Élevée — 3+ sources, domaines variés | AN88: https://www.head-fi.org/showcase/ifi-audio-hip-dac-3.26837/reviews | AO88: https://www.whathifi.com/reviews/ifi-hip-dac-3 | AP88: https://www.headphonesty.com/2024/02/ifi-hip-dac-3-review/ | AQ88: Objectif atteint | AR88: Head-Fi reviews: 1; Review éditoriale: 3
A89: Hidizs | B89: S9 Pro Plus Martha | C89: Portable Amp/DAC (Headfonics) | D89: Plutôt neutre, modulable par filtres. | E89: Propreté/contrôle, microdétail, image 3d | F89: Puissance réduite | G89: 9.1 | H89: 8.2 | I89: 8.7 | J89: 8.7 | K89: 8.7 | L89: 9 | M89: 8.9 | N89: 8.7 | O89: 9.6 | P89: 8.3 | Q89: =IF(COUNT(G89:P89)=10,ROUND((G89*'Pondérations'!$B$5+H89*'Pondérations'!$B$6+I89*'Pondérations'!$B$7+J89*'Pondérations'!$B$8+K89*'Pondérations'!$B$9+L89*'Pondérations'!$B$10+M89*'Pondérations'!$B$11+N89*'Pondérations'!$B$12+O89*'Pondérations'!$B$13+P89*'Pondérations'!$B$14)/'Pondérations'!$B$16,3),"") | R89: =IF(Q89="","",1+COUNTIF($Q$7:$Q$178,">"&Q89)+COUNTIF($Q$7:Q89,Q89)-1) | V89: Élevée | W89: Headfonics import | X89: 8.1 | Y89: Reader | Z89: 45264 | AA89: 4 | AB89: https://headfonics.com/?s=Hidizs+S9+Pro+Plus+Martha | AC89: Portable dongle DAC/amp | AD89: Ajout Headfonics | AE89: 69 | AF89: 85 | AG89: Dongle très compact et bon rapport qualité/prix, avec filtres intéressants et volume intégré. | AH89: Plutôt neutre, modulable par filtres. | AI89: Bonne performance générale mais moins de puissance que le S9 Pro. | AJ89: Puissance réduite; pas de câble iOS inclus. | AK89: https://headfonics.com/hidizs-s9-pro-plus-martha-review/ | AL89: 4 | AM89: Élevée — 3+ sources, domaines variés | AN89: https://www.head-fi.org/showcase/hidizs-s9-pro-plus-martha.26811/reviews | AO89: https://www.headphonesty.com/2023/12/review-hidizs-s9-pro-plus-martha/ | AP89: https://mobileaudiophile.com/dacs/hidizs-s9-pro-plus-martha-review/ | AQ89: Objectif atteint | AR89: Head-Fi reviews: 1; Review éditoriale: 3
A90: xDuoo | B90: XD05 Pro | C90: Portable Amp/DAC (Headfonics) | D90: Variable selon modules; stock plutôt neutre/technique. | E90: Puissance, dynamique, profondeur | F90: Gros et lourd | G90: 9 | H90: 8.7 | I90: 8.7 | J90: 8.6 | K90: 8.7 | L90: 8.9 | M90: 9 | N90: 9.3 | O90: 6.5 | P90: 8.1 | Q90: =IF(COUNT(G90:P90)=10,ROUND((G90*'Pondérations'!$B$5+H90*'Pondérations'!$B$6+I90*'Pondérations'!$B$7+J90*'Pondérations'!$B$8+K90*'Pondérations'!$B$9+L90*'Pondérations'!$B$10+M90*'Pondérations'!$B$11+N90*'Pondérations'!$B$12+O90*'Pondérations'!$B$13+P90*'Pondérations'!$B$14)/'Pondérations'!$B$16,3),"") | R90: =IF(Q90="","",1+COUNTIF($Q$7:$Q$178,">"&Q90)+COUNTIF($Q$7:Q90,Q90)-1) | V90: Élevée | W90: Headfonics import | X90: 8.7 | Y90: Reader | Z90: 45250 | AA90: 4 | AB90: https://headfonics.com/?s=xDuoo+XD05+Pro | AC90: Modular transportable DAC/amp | AD90: Ajout Headfonics | AE90: 70 | AF90: 749 | AG90: Transportable très puissant et modulaire, dont DAC, ampli et op-amps peuvent modifier fortement le résultat. | AH90: Variable selon modules; stock plutôt neutre/technique. | AI90: Excellent potentiel dynamique et grande adaptabilité. | AJ90: Gros et lourd; stock pas idéal avec IEM sensibles. | AK90: https://headfonics.com/xduoo-xd05-pro-review/ | AL90: 4 | AM90: Élevée — 3+ sources, domaines variés | AN90: https://www.headphonesty.com/2024/03/xduoo-xd05-pro-review/ | AO90: https://soundnews.net/reviews/sources/dacs/xduoo-xd05-pro-review-badassery-on-the-go/ | AP90: https://www.youtube.com/watch?v=nznizrQYqyA | AQ90: Objectif atteint | AR90: Review éditoriale: 3; Vidéo review: 1
A91: FiiO | B91: KA13 | C91: Portable Amp/DAC (Headfonics) | D91: Plutôt neutre/énergique. | E91: Matière/timbres, profondeur, image 3d | F91: Mode desktop gourmand en batterie | G91: 8.8 | H91: 8.7 | I91: 8.7 | J91: 8.6 | K91: 8.7 | L91: 9 | M91: 8.8 | N91: 8.7 | O91: 9.5 | P91: 8.1 | Q91: =IF(COUNT(G91:P91)=10,ROUND((G91*'Pondérations'!$B$5+H91*'Pondérations'!$B$6+I91*'Pondérations'!$B$7+J91*'Pondérations'!$B$8+K91*'Pondérations'!$B$9+L91*'Pondérations'!$B$10+M91*'Pondérations'!$B$11+N91*'Pondérations'!$B$12+O91*'Pondérations'!$B$13+P91*'Pondérations'!$B$14)/'Pondérations'!$B$16,3),"") | R91: =IF(Q91="","",1+COUNTIF($Q$7:$Q$178,">"&Q91)+COUNTIF($Q$7:Q91,Q91)-1) | V91: Élevée | W91: Headfonics import | Y91: Reader (non relevé) | Z91: 45234 | AA91: 4 | AB91: https://headfonics.com/?s=FiiO+KA13 | AC91: Portable dongle DAC/amp | AD91: Ajout Headfonics | AE91: 71 | AF91: 79 | AG91: Dongle budget surtout remarquable par une puissance très élevée pour le prix. | AH91: Plutôt neutre/énergique. | AI91: Bonne dynamique grâce à la réserve de puissance, plus fonctionnel que raffiné. | AJ91: Mode desktop gourmand en batterie; application limitée. | AK91: https://headfonics.com/fiio-ka13-review/ | AL91: 4 | AM91: Élevée — 3+ sources, domaines variés | AN91: https://www.head-fi.org/showcase/fiio-ka13.26751/reviews | AO91: https://www.headfonia.com/fiio-ka13-review/ | AP91: https://www.androidcentral.com/accessories/audio/fiio-ka13-review | AQ91: Objectif atteint | AR91: Head-Fi reviews: 1; Review éditoriale: 3
A92: Audirect | B92: Beam 4 | C92: Portable Amp/DAC (Headfonics) | D92: Plus brillant que neutre, assez clinique. | E92: Profondeur, propreté/contrôle, image 3d | F92: Peut être trop lumineux selon le casque/IEM | G92: 9 | H92: 8.8 | I92: 8.7 | J92: 8.6 | K92: 8.7 | L92: 8.6 | M92: 8.9 | N92: 8.1 | O92: 8 | P92: 8.1 | Q92: =IF(COUNT(G92:P92)=10,ROUND((G92*'Pondérations'!$B$5+H92*'Pondérations'!$B$6+I92*'Pondérations'!$B$7+J92*'Pondérations'!$B$8+K92*'Pondérations'!$B$9+L92*'Pondérations'!$B$10+M92*'Pondérations'!$B$11+N92*'Pondérations'!$B$12+O92*'Pondérations'!$B$13+P92*'Pondérations'!$B$14)/'Pondérations'!$B$16,3),"") | R92: =IF(Q92="","",1+COUNTIF($Q$7:$Q$178,">"&Q92)+COUNTIF($Q$7:Q92,Q92)-1) | V92: Élevée | W92: Headfonics import | X92: 8 | Y92: Reader | Z92: 45231 | AA92: 4 | AB92: https://headfonics.com/?s=Audirect+Beam+4 | AC92: Portable DAC/amp | AD92: Ajout Headfonics | AE92: 72 | AF92: 211 | AG92: DAC/amp portable très bien construit au rendu franchement clair et engageant. | AH92: Plus brillant que neutre, assez clinique. | AI92: Bonne précision et attaque. | AJ92: Peut être trop lumineux selon le casque/IEM. | AK92: https://headfonics.com/audirect-beam-4-review/ | AL92: 3 | AM92: Élevée — 3+ sources, domaines variés | AN92: https://www.headphonesty.com/2023/07/review-audirect-beam-4/ | AO92: https://www.head-fi.org/threads/reviews-impressions-rants-and-more-from-darmanastartes.963101/page-4 | AQ92: Objectif atteint | AR92: Head-Fi forum: 1; Review éditoriale: 2
A93: ddHiFi | B93: TC44Pro | C93: Portable Amp/DAC (Headfonics) | D93: Cool/clair, énergique. | E93: Dynamique, propreté/contrôle, image 3d | F93: Peu de fonctions | G93: 9 | H93: 8.8 | I93: 8.6 | J93: 8.6 | K93: 8.7 | L93: 8.8 | M93: 9 | N93: 8.8 | O93: 9.5 | P93: 8.1 | Q93: =IF(COUNT(G93:P93)=10,ROUND((G93*'Pondérations'!$B$5+H93*'Pondérations'!$B$6+I93*'Pondérations'!$B$7+J93*'Pondérations'!$B$8+K93*'Pondérations'!$B$9+L93*'Pondérations'!$B$10+M93*'Pondérations'!$B$11+N93*'Pondérations'!$B$12+O93*'Pondérations'!$B$13+P93*'Pondérations'!$B$14)/'Pondérations'!$B$16,3),"") | R93: =IF(Q93="","",1+COUNTIF($Q$7:$Q$178,">"&Q93)+COUNTIF($Q$7:Q93,Q93)-1) | V93: Élevée | W93: Headfonics import | X93: 8.2 | Y93: Reader | Z93: 45229 | AA93: 4 | AB93: https://headfonics.com/?s=ddHiFi+TC44Pro | AC93: Portable dongle DAC/amp | AD93: Ajout Headfonics | AE93: 73 | AF93: 70 | AG93: Dongle équilibré, résolvant et assez puissant, avec une tonalité fraîche et légèrement énergique. | AH93: Cool/clair, énergique. | AI93: Bonne résolution et contrôle avec IEM. | AJ93: Peu de fonctions; uniquement sortie symétrique. | AK93: https://headfonics.com/ddhifi-tc44pro-review/ | AL93: 3 | AM93: Élevée — 3+ sources, domaines variés | AN93: https://www.head-fi.org/showcase/ddhifi-tc44pro.26664/reviews | AO93: https://www.headfonia.com/ddhifi-tc44pro-review/ | AP93: https://www.ddhifi.com/en/review/6588/ | AQ93: Objectif atteint | AR93: Head-Fi reviews: 1; Review éditoriale: 2
A94: Moondrop | B94: Dawn Pro | C94: Portable Amp/DAC (Headfonics) | D94: Neutre/propre. | E94: Propreté/contrôle, microdétail, dynamique | F94: Pas de gain physique | G94: 9.4 | H94: 9.1 | I94: 8.7 | J94: 8.6 | K94: 8.9 | L94: 8.7 | M94: 9.1 | N94: 9.1 | O94: 9.5 | P94: 8.3 | Q94: =IF(COUNT(G94:P94)=10,ROUND((G94*'Pondérations'!$B$5+H94*'Pondérations'!$B$6+I94*'Pondérations'!$B$7+J94*'Pondérations'!$B$8+K94*'Pondérations'!$B$9+L94*'Pondérations'!$B$10+M94*'Pondérations'!$B$11+N94*'Pondérations'!$B$12+O94*'Pondérations'!$B$13+P94*'Pondérations'!$B$14)/'Pondérations'!$B$16,3),"") | R94: =IF(Q94="","",1+COUNTIF($Q$7:$Q$178,">"&Q94)+COUNTIF($Q$7:Q94,Q94)-1) | V94: Élevée | W94: Headfonics import | X94: 7.7 | Y94: Reader | Z94: 45219 | AA94: 4 | AB94: https://headfonics.com/?s=Moondrop+Dawn+Pro | AC94: Portable dongle DAC/amp | AD94: Ajout Headfonics | AE94: 74 | AF94: 44 | AG94: Petit dongle très convaincant pour le prix, améliorant nettement clarté et ouverture par rapport à la sortie d’un téléphone. | AH94: Neutre/propre. | AI94: Bonne clarté et scène plus ouverte que le smartphone seul. | AJ94: Pas de gain physique; puissance surtout adaptée aux IEM. | AK94: https://headfonics.com/moondrop-dawn-pro-review/ | AL94: 4 | AM94: Élevée — 3+ sources, domaines variés | AN94: https://www.head-fi.org/showcase/moondrop-dawn-pro.26937/reviews | AO94: https://androidbrick.com/moondrop-dawn-pro-review/ | AP94: https://sonicmantra.org/product-review/moondrop-dawn-pro-review-arifgraphy/ | AQ94: Objectif atteint | AR94: Head-Fi reviews: 1; Review éditoriale: 3
A95: Moondrop | B95: MoonRiver 2: Ti | C95: Portable Amp/DAC (Headfonics) | D95: Neutre, propre. | E95: Propreté/contrôle, microdétail, dynamique | F95: Chauffe et consomme sensiblement la batterie de la source | G95: 9.7 | H95: 9.1 | I95: 8.7 | J95: 8.6 | K95: 9 | L95: 8.6 | M95: 9.1 | N95: 8.7 | O95: 7.8 | P95: 8.4 | Q95: =IF(COUNT(G95:P95)=10,ROUND((G95*'Pondérations'!$B$5+H95*'Pondérations'!$B$6+I95*'Pondérations'!$B$7+J95*'Pondérations'!$B$8+K95*'Pondérations'!$B$9+L95*'Pondérations'!$B$10+M95*'Pondérations'!$B$11+N95*'Pondérations'!$B$12+O95*'Pondérations'!$B$13+P95*'Pondérations'!$B$14)/'Pondérations'!$B$16,3),"") | R95: =IF(Q95="","",1+COUNTIF($Q$7:$Q$178,">"&Q95)+COUNTIF($Q$7:Q95,Q95)-1) | V95: Élevée | W95: Headfonics import | Y95: Reader (non relevé) | Z95: 45163 | AA95: 4 | AB95: https://headfonics.com/?s=Moondrop+MoonRiver+2%3A+Ti | AC95: Portable dongle DAC/amp | AD95: Ajout Headfonics | AE95: 77 | AF95: 167 | AG95: Version plus puissante et mieux équipée du MoonRiver 2, avec fond noir et bonne capacité d’entraînement. | AH95: Neutre, propre. | AI95: Fond silencieux et bonne dynamique. | AJ95: Chauffe et consomme sensiblement la batterie de la source. | AK95: https://headfonics.com/moondrop-moonriver-2-ti-review/ | AL95: 4 | AM95: Élevée — 3+ sources, domaines variés | AN95: https://www.head-fi.org/showcase/moondrop-moonriver-2-ti.26642/reviews | AO95: https://primeaudio.org/moondrop-moonriver-2-ti-review/ | AP95: https://moonstarreviews.net/moondrop-moonriver-2-ti-review/ | AQ95: Objectif atteint | AR95: Head-Fi reviews: 1; Review éditoriale: 3
A96: HiBy | B96: FC6 | C96: Portable Amp/DAC (Headfonics) | D96: Chaud/naturel, médiums riches. | E96: Puissance, matière/timbres, dynamique | F96: Pas de sortie symétrique | G96: 9 | H96: 8.7 | I96: 8.8 | J96: 8.7 | K96: 8.9 | L96: 9.2 | M96: 9 | N96: 9.3 | O96: 8 | P96: 8.3 | Q96: =IF(COUNT(G96:P96)=10,ROUND((G96*'Pondérations'!$B$5+H96*'Pondérations'!$B$6+I96*'Pondérations'!$B$7+J96*'Pondérations'!$B$8+K96*'Pondérations'!$B$9+L96*'Pondérations'!$B$10+M96*'Pondérations'!$B$11+N96*'Pondérations'!$B$12+O96*'Pondérations'!$B$13+P96*'Pondérations'!$B$14)/'Pondérations'!$B$16,3),"") | R96: =IF(Q96="","",1+COUNTIF($Q$7:$Q$178,">"&Q96)+COUNTIF($Q$7:Q96,Q96)-1) | V96: Élevée | W96: Headfonics import | Y96: Reader (non relevé) | Z96: 45124 | AA96: 4 | AB96: https://headfonics.com/?s=HiBy+FC6 | AC96: Portable dongle DAC/amp | AD96: Ajout Headfonics | AE96: 79 | AF96: 263 | AG96: R2R compact, dense et naturel, avec médiums pleins et aigu détendu; les modes NOS/OS permettent d’ajuster le rendu. | AH96: Chaud/naturel, médiums riches. | AI96: Bonne matière et densité plus que recherche de contours ultra-précis. | AJ96: Pas de sortie symétrique; bruit possible en NOS avec certains Samsung. | AK96: https://headfonics.com/hiby-fc6-review/ | AL96: 3 | AM96: Élevée — 3+ sources, domaines variés | AN96: https://www.head-fi.org/showcase/hiby-fc6.26906/reviews | AO96: https://store.hiby.com/blogs/hiby-fc6-review/hiby-fc6-review-moonstarreviews | AP96: https://www.head-fi.org/threads/hiby-fc6-r2r-dongle-dac-reborn.969134/ | AQ96: Objectif atteint | AR96: Head-Fi forum: 1; Head-Fi reviews: 1; Review éditoriale: 1
A97: ddHiFi | B97: TC35C | C97: Portable Amp/DAC (Headfonics) | D97: Neutre/propre. | E97: Puissance, matière/timbres, profondeur | F97: Pas d’app/firmware | G97: 8.9 | H97: 8.7 | I97: 8.9 | J97: 8.8 | K97: 8.9 | L97: 9.2 | M97: 8.9 | N97: 7 | O97: 9.5 | P97: 8.4 | Q97: =IF(COUNT(G97:P97)=10,ROUND((G97*'Pondérations'!$B$5+H97*'Pondérations'!$B$6+I97*'Pondérations'!$B$7+J97*'Pondérations'!$B$8+K97*'Pondérations'!$B$9+L97*'Pondérations'!$B$10+M97*'Pondérations'!$B$11+N97*'Pondérations'!$B$12+O97*'Pondérations'!$B$13+P97*'Pondérations'!$B$14)/'Pondérations'!$B$16,3),"") | R97: =IF(Q97="","",1+COUNTIF($Q$7:$Q$178,">"&Q97)+COUNTIF($Q$7:Q97,Q97)-1) | V97: Élevée | W97: Headfonics import | X97: 7.9 | Y97: Reader | Z97: 45114 | AA97: 4 | AB97: https://headfonics.com/?s=ddHiFi+TC35C | AC97: Portable USB DAC adapter | AD97: Ajout Headfonics | AE97: 80 | AF97: 43 | AG97: Mini dongle très simple, propre et économe en batterie, particulièrement adapté aux IEM efficaces. | AH97: Neutre/propre. | AI97: Bonne propreté de sortie mais ambitions techniques modestes. | AJ97: Pas d’app/firmware; réservé aux IEM faciles. | AK97: https://headfonics.com/ddhifi-tc35c-review/ | AL97: 3 | AM97: Élevée — 3+ sources, domaines variés | AN97: https://www.ddhifi.com/en/review/6605/ | AO97: https://www.audiophile-heaven.com/2023/05/ddhifi-tc35c-dongle-dac-ultra-minimal-power-source.html | AP97: https://www.head-fi.org/threads/usb-c-to-3-5mm-adapters-dac-lets-find-the-best.908839/page-247 | AQ97: Objectif atteint | AR97: Head-Fi forum: 1; Review éditoriale: 2
A98: FiiO | B98: KA5 | C98: Portable Amp/DAC (Headfonics) | D98: Plutôt neutre/technique. | E98: Puissance, dynamique, propreté/contrôle | F98: Chauffe si poussé | G98: 9 | H98: 8.7 | I98: 8.4 | J98: 8.3 | K98: 8.6 | L98: 8.7 | M98: 9 | N98: 9.3 | O98: 9.3 | P98: 7.8 | Q98: =IF(COUNT(G98:P98)=10,ROUND((G98*'Pondérations'!$B$5+H98*'Pondérations'!$B$6+I98*'Pondérations'!$B$7+J98*'Pondérations'!$B$8+K98*'Pondérations'!$B$9+L98*'Pondérations'!$B$10+M98*'Pondérations'!$B$11+N98*'Pondérations'!$B$12+O98*'Pondérations'!$B$13+P98*'Pondérations'!$B$14)/'Pondérations'!$B$16,3),"") | R98: =IF(Q98="","",1+COUNTIF($Q$7:$Q$178,">"&Q98)+COUNTIF($Q$7:Q98,Q98)-1) | V98: Élevée | W98: Headfonics import | Y98: Reader (non relevé) | Z98: 45103 | AA98: 5 | AB98: https://headfonics.com/?s=FiiO+KA5 | AC98: Portable dongle DAC/amp | AD98: Ajout Headfonics | AE98: 81 | AF98: 129 | AG98: Dongle riche en fonctions avec beaucoup de puissance et un équipement complet pour le prix. | AH98: Plutôt neutre/technique. | AI98: Bonne dynamique et polyvalence. | AJ98: Chauffe si poussé; ergonomie physique un peu anguleuse. | AK98: https://headfonics.com/fiio-ka5-review/ | AL98: 4 | AM98: Élevée — 3+ sources, domaines variés | AN98: https://www.head-fi.org/threads/fiio-ka5-review-and-ka3-comparison.967506/ | AO98: https://www.headfonia.com/fiio-ka5-review/ | AP98: https://www.androidcentral.com/accessories/audio/fiio-ka5-review | AQ98: Objectif atteint | AR98: Head-Fi forum: 1; Review éditoriale: 3
A99: FiiO | B99: Q11 | C99: Portable Amp/DAC (Headfonics) | D99: Neutre-naturel. | E99: Puissance, propreté/contrôle, microdétail | F99: Moins de fonctions héritées que les anciens Q-series | G99: 9 | H99: 8.8 | I99: 8.6 | J99: 8.5 | K99: 8.7 | L99: 8.8 | M99: 8.9 | N99: 9.3 | O99: 8 | P99: 8 | Q99: =IF(COUNT(G99:P99)=10,ROUND((G99*'Pondérations'!$B$5+H99*'Pondérations'!$B$6+I99*'Pondérations'!$B$7+J99*'Pondérations'!$B$8+K99*'Pondérations'!$B$9+L99*'Pondérations'!$B$10+M99*'Pondérations'!$B$11+N99*'Pondérations'!$B$12+O99*'Pondérations'!$B$13+P99*'Pondérations'!$B$14)/'Pondérations'!$B$16,3),"") | R99: =IF(Q99="","",1+COUNTIF($Q$7:$Q$178,">"&Q99)+COUNTIF($Q$7:Q99,Q99)-1) | V99: Élevée | W99: Headfonics import | Y99: Reader (non relevé) | Z99: 45073 | AA99: 5 | AB99: https://headfonics.com/?s=FiiO+Q11 | AC99: Battery portable DAC/amp | AD99: Ajout Headfonics | AE99: 82 | AF99: 79 | AG99: Portable orienté qualité sonore, neutre et naturel, avec beaucoup de puissance et une bonne autonomie. | AH99: Neutre-naturel. | AI99: Bonne dynamique et tenue, plutôt raffiné pour le prix. | AJ99: Moins de fonctions héritées que les anciens Q-series; app limitée. | AK99: https://headfonics.com/fiio-q11-review/ | AL99: 4 | AM99: Élevée — 3+ sources, domaines variés | AN99: https://www.head-fi.org/showcase/fiio-q11.26394/reviews | AO99: https://www.headfonia.com/fiio-q11-review/ | AP99: https://audio46.com/blogs/headphones/fiio-q11-dac-amp-review | AQ99: Objectif atteint | AR99: Head-Fi reviews: 1; Review éditoriale: 3
A100: iFi audio | B100: UNO | C100: Portable Amp/DAC (Headfonics) | D100: Plutôt neutre avec réglages EQ. | E100: Microdétail, propreté/contrôle, layering | F100: Sensible aux interférences EMI | G100: 9.3 | H100: 9.1 | I100: 8.8 | J100: 8.8 | K100: 9 | L100: 9.1 | M100: 9 | N100: 8.5 | O100: 6.5 | P100: 8.7 | Q100: =IF(COUNT(G100:P100)=10,ROUND((G100*'Pondérations'!$B$5+H100*'Pondérations'!$B$6+I100*'Pondérations'!$B$7+J100*'Pondérations'!$B$8+K100*'Pondérations'!$B$9+L100*'Pondérations'!$B$10+M100*'Pondérations'!$B$11+N100*'Pondérations'!$B$12+O100*'Pondérations'!$B$13+P100*'Pondérations'!$B$14)/'Pondérations'!$B$16,3),"") | R100: =IF(Q100="","",1+COUNTIF($Q$7:$Q$178,">"&Q100)+COUNTIF($Q$7:Q100,Q100)-1) | V100: Élevée | W100: Headfonics import | X100: 8.3 | Y100: Reader | Z100: 45066 | AA100: 5 | AB100: https://headfonics.com/?s=iFi+audio+UNO | AC100: Portable/desktop USB DAC/amp | AD100: Ajout Headfonics | AE100: 83 | AF100: 69 | AG100: Petit DAC/amp USB transportable, simple et efficace, un cran au-dessus des dongles basiques. | AH100: Plutôt neutre avec réglages EQ. | AI100: Bonne prestation générale pour l’entrée de gamme. | AJ100: Sensible aux interférences EMI; pas d’alimentation externe séparée. | AK100: https://headfonics.com/ifi-audio-uno-review/ | AL100: 4 | AM100: Élevée — 3+ sources, domaines variés | AN100: https://www.head-fi.org/showcase/ifi-audio-uno.26225/reviews | AO100: https://www.headfonia.com/ifi-audio-uno-review/ | AP100: https://www.techradar.com/audio/hi-fi/ifi-uno-review | AQ100: Objectif atteint | AR100: Head-Fi reviews: 1; Review éditoriale: 3
...

Sheet Technique & sources
A1: Colonnes D à K : vérification unitaire sur sources primaires, 2026-08-10. Une cellule remplie = valeur attestée par une source ouverte et citée (voir feuille « Sources technique »). Une cellule VIDE = non vérifiable avec certitude, ce n’est pas un « non ». Les remplissages automatiques antérieurs de F-K ont été effacés.
A2: Données techniques, prix indicatifs et sources
A3: Un repère de prix par produit. Les prix déjà consolidés sont conservés; les compléments utilisent un prix européen direct quand disponible, sinon un MSRP/prix de lancement converti en euros au taux ECB du 29/07/2026. Source et devise d’origine : commentaire de la cellule prix.
A5: Marque | B5: Modèle | C5: Architecture / DAC | D5: Batterie | E5: Bluetooth | F5: Sortie 3.5mm | G5: Sortie 4.4mm | H5: Sortie 2.5mm | I5: Sortie 6.35mm | J5: Sortie XLR | K5: DSP / PEQ | L5: Puissance discutée | M5: Prix moyen / MSRP (≈€) | N5: Type | O5: Confiance | P5: Source URL | Q5: Profil sonore | R5: Rôle conseillé | S5: Score HF | T5: Type score HF | U5: Date review HF | V5: Page HF | W5: Lien Headfonics | X5: Résumé HF
A6: Cayin | B6: N7 | C6: DAC 1-bit discret, classe A/AB | D6: Oui | E6: Oui | F6: Oui | G6: Oui | H6: Non | I6: Non | J6: Non | K6: Non | L6: DAP — puissance modérée | M6: 1757 | N6: DAP / référence | O6: Élevée | P6: https://en.cayin.cn/features/7/15/592.html | Q6: Organique, fluide, texturé, très naturel | R6: Référence pour relief / matière / spatialisation
A7: Topping | B7: L70 | C7: NFCA, ampli analogique | D7: Non | E7: Non | F7: Non | G7: Oui | H7: Non | I7: Oui | J7: Oui | K7: Non | L7: Très élevée (desktop) | M7: 307 | N7: Ampli casque desktop / référence | O7: Élevée | Q7: Très propre, neutre, contrôlé, ferme | R7: Référence propreté / contrôle / puissance
A8: iBasso | B8: DC-Elite | C8: ROHM BD34301EKV + étage analogique ambitieux | D8: Non | E8: Non | F8: Oui | G8: Oui | H8: Non | I8: Non | J8: Non | K8: Non | L8: ≈280 mW @ 32 Ω (4,4 mm) | M8: 439 | N8: Dongle DAC/amp | O8: Élevée | P8: https://www.audiophonics.fr/fr/amplificateurs-casque-mobiles/ibasso-dc-elite-p-18544.html | Q8: Neutre-naturel, très résolvant, incisif sans sécheresse | R8: Meilleur complément nomade au N7/L70 | S8: 8.6 | T8: Reader | U8: 45499 | V8: 3 | W8: https://headfonics.com/?s=iBasso+DC-Elite | X8: Flagship dongle DAC/amp
A9: Quloos | B9: MUB1 | C9: 4× CS43131 | D9: Oui | E9: Oui | F9: Oui | G9: Oui | H9: Non | I9: Non | J9: Non | K9: Non | L9: ≈1,1 W @ 32 Ω (bal.) | M9: 439 | N9: DAC/amp portable sur batterie | O9: Moyenne à élevée | P9: https://moonstarreviews.net/quloos-mub1-review/ | Q9: Légèrement chaleureux, dense, transparent | R9: Meilleur tout-en-un autonome / batterie + BT
A10: Cayin | B10: RU7 | C10: DAC 1-bit discret, DSD64/128/256 | D10: Non | E10: Non | F10: Oui | G10: Oui | H10: Non | I10: Non | J10: Non | K10: Non | L10: ≈400 mW @ 32 Ω (bal.) | M10: 255 | N10: Dongle DAC/amp R-2R/1-bit | O10: Élevée | P10: https://headfonics.com/cayin-ru7-review/ | Q10: Fluide, organique, doux, spatial | R10: Mini-N7 ultraportable | S10: 8.6 | T10: Reader | U10: 45143 | V10: 4 | W10: https://headfonics.com/?s=Cayin+RU7 | X10: 1-bit discrete resistor-network dongle DAC/amp
A11: Dethonray | B11: Clarinet | C11: AK4493S, alimentations séparées | D11: Oui | E11: Non | F11: Oui | G11: Oui | H11: Non | I11: Non | J11: Non | K11: Non | L11: À confirmer | M11: 196 | N11: DAC/amp portable sur batterie | O11: Moyenne | P11: https://www.audiophile-heaven.com/2025/04/the-canto-master-dethonray-clarinet-dac-headphone-amp.html | Q11: Naturel, doux, légèrement sombre, texturé | R11: Choix charnel / grande scène
A12: Moondrop | B12: Moonriver 3 | C12: 2× CS43198 + étages d’amplification séparés | D12: Non | E12: Non | F12: Oui | G12: Oui | H12: Non | I12: Non | J12: Non | K12: Oui | L12: ≈500 mW / 4 Vrms | M12: 229 | N12: Dongle DAC/amp | O12: Élevée | P12: https://www.audiophonics.fr/fr/dac-portables/moondrop-moonriver-3-p-21677.html | Q12: Neutre, très ouvert, analytique sans être stérile | R12: Rapport prix/résolution/espace | S12: 8.7 | T12: Award | U12: 46144 | V12: 1 | W12: https://headfonics.com/?s=Moondrop+Moonriver+3 | X12: Dual CS43198 dongle DAC, DSP, up to 500 mW
A13: ONIX | B13: Beta XI2 | C13: Mode transistor + tubes JAN6418 | D13: Non | E13: Non | F13: Oui | G13: Oui | H13: Non | I13: Non | J13: Non | K13: Non | L13: À confirmer | M13: 349 | N13: DAC/amp portable hybride | O13: Moyenne | P13: https://www.audiophonics.fr/fr/dac-portables/shanling-onix-beta-xi2-p-21159.html | Q13: Naturel, légèrement chaleureux; tubes plus organiques | R13: Option organique polyvalente | S13: 8.5 | T13: Reader | U13: 45987 | V13: 1 | W13: https://headfonics.com/?s=ONIX+Beta+XI2 | X13: Hybrid solid-state/JAN6418 tube dongle DAC
A14: MUSE HiFi | B14: M6 Double | C14: ES9039 + transistors / tubes JAN6418 | D14: Oui | E14: Oui | F14: Oui | G14: Oui | H14: Non | I14: Non | J14: Non | K14: Non | L14: Élevée / à confirmer | M14: 449 | N14: DAC/amp portable hybride | O14: Moyenne | P14: https://www.audiophonics.fr/fr/dac-portables/musehifi-m6-p-21634.html | Q14: Spacieux, immersif, tubes plus charnels | R14: Maximum immersion / effet 3D | S14: 8.6 | T14: Reader | U14: 45958 | V14: 1 | W14: https://headfonics.com/?s=MUSE+HiFi+M6+Double | X14: Dual-mode transistor/JAN6418 tube portable DAC/amp
A15: Questyle | B15: M15i | C15: Amplification CMA en mode courant | D15: Non | E15: Non | F15: Oui | G15: Oui | H15: Non | I15: Non | J15: Non | K15: Non | L15: ≈2,62 Vrms (bal.) | M15: 259 | N15: Dongle DAC/amp | O15: Élevée | P15: https://www.audiophonics.fr/fr/dac-portables/questyle-m15i-p-19563.html | Q15: Propre, doux, légèrement charnu, très spatial | R15: Excellent avec IEM / casque facile
A16: Shanling | B16: UA7 | C16: Transistors + tubes | D16: Non | E16: Non | F16: Oui | G16: Oui | H16: Non | I16: Non | J16: Non | K16: Non | L16: ≈577 mW @ 32 Ω | M16: 269 | N16: Dongle DAC/amp hybride | O16: Moyenne à élevée | P16: https://www.headfonia.com/shanling-ua7-review/ | Q16: Propre, légèrement chaleureux; tube plus organique | R16: Compromis tube/transistor moderne | S16: 8.6 | T16: Award | U16: 46050 | V16: 1 | W16: https://headfonics.com/?s=Shanling+UA7 | X16: Dual JAN6418 tube dongle DAC, up to 577 mW
A17: iBasso | B17: DC07PRO | C17: DAC Cirrus Logic (multi-DAC) | D17: Non | E17: Non | F17: Oui | G17: Oui | H17: Non | I17: Non | J17: Non | K17: Non | L17: ≈430 mW @ 32 Ω | M17: 189 | N17: Dongle DAC/amp | O17: Élevée | P17: https://www.audiophonics.fr/fr/dac-portables/ibasso-dc07pro-noir-p-19619.html | Q17: Transparent, légèrement chaleureux, équilibré | R17: Choix rationnel sous 200 €
A18: Shanling | B18: UA6 II | C18: 8× CS43131, mode 4/8 DAC | D18: Non | E18: Non | F18: Oui | G18: Oui | H18: Non | I18: Non | J18: Non | K18: Non | L18: ≈365 mW @ 32 Ω | M18: 219 | N18: Dongle DAC/amp | O18: Moyenne | P18: https://www.audiophonics.fr/fr/dac-portables/shanling-ua6-ii-p-22362.html | Q18: Très propre, précis, neutre, légèrement chaleureux | R18: Choix résolution/propreté vers 220 €
A19: ONIX | B19: Alpha XI1 | C19: Cirrus Logic / architecture ONIX | D19: Non | E19: Non | F19: Oui | G19: Oui | H19: Non | I19: Non | J19: Non | K19: Non | L19: ≈500 mW @ 32 Ω | M19: 109 | N19: Dongle DAC/amp | O19: Moyenne | P19: https://www.audiophonics.fr/fr/dac-portables/shanling-onix-alpha-xi1-p-19347.html | Q19: Musical, texturé, assez ouvert | R19: Affaire budget | S19: 7.9 | T19: Reader | U19: 45593 | V19: 3 | W19: https://headfonics.com/?s=ONIX+Alpha+XI1 | X19: Dual CS43198 dongle DAC, up to 500 mW
A20: xDuoo | B20: XD05 BAL 2 | C20: DAC + AOP remplaçables | D20: Oui | E20: Oui | F20: Non | G20: Oui | H20: Non | I20: Oui | J20: Non | K20: Non | L20: ≈1,5 W @ 32 Ω | M20: 429 | N20: DAC/amp portable sur batterie | O20: Élevée | P20: https://xduoo.net/preview/xd05-bal2 | Q20: Charnu, doux, puissant, plutôt sombre | R20: Casques gourmands / tweak AOP | S20: 8 | T20: Reader | U20: 45184 | V20: 4 | W20: https://headfonics.com/?s=xDuoo+XD05+BAL+2 | X20: High-power battery portable DAC/amp
A21: Dethonray | B21: Pegasus SG1 | C21: Architecture propriétaire Dethonray | D21: Oui | E21: Oui | F21: Oui | G21: Oui | H21: Non | I21: Non | J21: Non | K21: Non | L21: À confirmer | M21: 351 | N21: Récepteur Bluetooth DAC/amp | O21: Moyenne | P21: https://www.dethonray.com/products/dac/pegasus-sg1/ | Q21: Charnu, énergique, grave présent, aigu calme | R21: Meilleur cas d’usage: Bluetooth immersif
A22: Shanling | B22: H5 MQA | C22: DAC Shanling / mode lecteur microSD | D22: Oui | E22: Oui | F22: Oui | G22: Oui | H22: Non | I22: Non | J22: Non | K22: Non | L22: ≈840 mW @ 32 Ω (bal.) | M22: 325 | N22: DAC/amp portable sur batterie | O22: Moyenne | P22: https://headfonics.com/shanling-h5-review/ | Q22: Chaud, fluide, grave généreux | R22: Portable autonome et puissant | S22: 8.3 | T22: Reader | U22: 45185 | V22: 4 | W22: https://headfonics.com/?s=Shanling+H5 | X22: Battery portable DAC/amp
A23: xDuoo | B23: POKE II | C23: DAC/amp portable avec EQ grave/aigu | D23: Oui | E23: Oui | F23: Oui | G23: Oui | H23: Non | I23: Non | J23: Non | K23: Non | L23: ≈700 mW @ 32 Ω (bal.) | M23: 343 | N23: DAC/amp portable sur batterie | O23: Moyenne | P23: https://www.headfonia.com/xduoo-poke-ii-review/3/ | Q23: Équilibré, bonne scène, plutôt polyvalent | R23: Portable polyvalent d’ancienne génération | S23: 8.3 | T23: Reader | U23: 44769 | V23: 5 | W23: https://headfonics.com/?s=xDuoo+POKE+II | X23: Battery portable DAC/amp
A24: FiiO | B24: BTR17 | C24: DAC portable + PEQ + mode desktop | D24: Oui | E24: Oui | F24: Oui | G24: Oui | H24: Non | I24: Non | J24: Non | K24: Oui | L24: ≈650 mW (mode desktop) | M24: 199 | N24: Bluetooth DAC/amp | O24: Élevée | P24: https://www.audiophonics.fr/fr/amplificateurs-casque-mobiles/fiio-btr17-noir-p-20087.html | Q24: Neutre, rapide, propre, fonctionnel | R24: Fonctions/BT/PEQ avant signature
A25: FiiO | B25: QX13 | C25: DAC hautes performances + mode desktop + PEQ | D25: Non | E25: Non | F25: Oui | G25: Oui | H25: Non | I25: Non | J25: Non | K25: Oui | L25: Jusqu’à ≈900 mW/canal (desktop) | M25: 199 | N25: Dongle DAC/amp | O25: Moyenne à élevée | P25: https://www.audiophonics.fr/fr/dac-portables-c-6399.html?orderby=price&orderway=desc | Q25: Très propre, détaillé, énergique | R25: Performance/fonctions, pas priorité holographie | S25: 8.5 | T25: Reader | U25: 45892 | V25: 2 | W25: https://headfonics.com/?s=FiiO+QX13 | X25: ES9027SPRO high-end dongle DAC with color display
A26: SMSL | B26: DS20 | C26: Architecture DAC/amp SMSL | D26: Oui | E26: Non | F26: Oui | G26: Oui | H26: Non | I26: Non | J26: Non | K26: Non | L26: Élevée / à confirmer | M26: 199 | N26: DAC/amp portable | O26: Moyenne | P26: https://headfonics.com/smsl-ds20-review/ | Q26: Propre, large, résolvant | R26: À écarter si profondeur prioritaire | S26: 8.3 | T26: Reader | U26: 45899 | V26: 2 | W26: https://headfonics.com/?s=SMSL+DS20 | X26: Quad CS43131 portable DAC/amp, up to 500 mW
A27: MUSE HiFi | B27: M5 Ultra | C27: Mode tubes / hybride | D27: Oui | E27: Oui | F27: Oui | G27: Oui | H27: Non | I27: Non | J27: Non | K27: Non | L27: À confirmer | M27: 269 | N27: DAC/amp portable hybride | O27: Moyenne | P27: https://www.headfonia.com/muse-hifi-m5-ultra-review/2/ | Q27: Doux, charnu, tubes plus profonds | R27: Tube accessible mais compromis | S27: 8.1 | T27: Reader | U27: 45800 | V27: 2 | W27: https://headfonics.com/?s=MUSE+HiFi+M5+Ultra | X27: Bluetooth ES9038Q2M tube/solid-state portable DAC/amp
A28: Topping | B28: G5 | C28: NFCA / DAC portable | D28: Oui | E28: Oui | F28: Oui | G28: Oui | H28: Non | I28: Non | J28: Non | K28: Non | L28: Très élevée pour portable | M28: 299 | N28: DAC/amp portable sur batterie | O28: Élevée | P28: https://www.audiosciencereview.com/forum/index.php?threads/topping-g5-review-portable-dac-hp-amp.36542/ | Q28: Très neutre, très propre, très contrôlé | R28: Excellent techniquement mais redondant
A29: Shanling | B29: UA6 | C29: Architecture multi-DAC Cirrus / génération précédente | D29: Oui | E29: Non | F29: Oui | G29: Oui | H29: Non | I29: Non | J29: Non | K29: Non | L29: À confirmer | M29: 179 | N29: Dongle DAC/amp | O29: Moyenne | Q29: Transparent, spacieux, légèrement chaleureux | R29: Ancienne génération intéressante si bon prix
A30: Questyle | B30: M15C | C30: Amplification CMA en mode courant | D30: Non | E30: Non | F30: Oui | G30: Oui | H30: Non | I30: Non | J30: Non | K30: Non | L30: Modérée | M30: 129 | N30: Dongle DAC/amp | O30: Moyenne | Q30: Propre, fluide, légèrement chaleureux | R30: Option Questyle économique | S30: 8 | T30: Reader | U30: 45663 | V30: 3 | W30: https://headfonics.com/?s=Questyle+M15C | X30: Balanced dongle DAC; updated M15 family
A31: iBasso | B31: DC-Tonfa | C31: R-2R entièrement symétrique, 8 canaux / 312 résistances | D31: Non | E31: Non | F31: Oui | G31: Oui | H31: Non | I31: Non | J31: Non | K31: Non | L31: À confirmer | M31: 292 | N31: Dongle DAC/amp R-2R | O31: Faible / provisoire | P31: https://hifigo.com/blogs/news/ibasso-presents-dc-tonfa-24-bit-fully-balanced-r2r-flagship-portable-dac-amp | Q31: Prometteur: texture R-2R + précision iBasso | R31: À surveiller avant achat
A32: Questyle | B32: M18i Max | D32: Oui | E32: Oui | F32: Oui | G32: Oui | H32: Non | I32: Non | J32: Non | K32: Non | M32: 307 | N32: Portable Amp/DAC (Headfonics) | O32: Import Headfonics — à enrichir | P32: https://headfonics.com/category/portable-amps-dacs/ | Q32: À évaluer | R32: À évaluer | S32: 8.7 | T32: Award | U32: 46223 | V32: 1 | W32: https://headfonics.com/?s=Questyle+M18i+Max | X32: ESS ES9219Q wireless portable DAC/amp
A33: AFUL | B33: ICEBORNE | D33: Non | E33: Non | F33: Oui | G33: Oui | H33: Non | I33: Non | J33: Non | K33: Non | M33: 132 | N33: Portable Amp/DAC (Headfonics) | O33: Import Headfonics — à enrichir | P33: https://headfonics.com/category/portable-amps-dacs/ | Q33: À évaluer | R33: À évaluer | S33: 8.3 | T33: Award | U33: 46209 | V33: 1 | W33: https://headfonics.com/?s=AFUL+ICEBORNE | X33: Dual CS43198 dongle DAC, up to 300 mW
A34: Fosi Audio | B34: MD3 | D34: Oui | E34: Non | F34: Oui | G34: Oui | H34: Non | I34: Non | J34: Non | K34: Non | M34: 132 | N34: Portable Amp/DAC (Headfonics) | O34: Import Headfonics — à enrichir | P34: https://headfonics.com/category/portable-amps-dacs/ | Q34: À évaluer | R34: À évaluer | S34: 7.9 | T34: Award | U34: 46207 | V34: 1 | W34: https://headfonics.com/?s=Fosi+Audio+MD3 | X34: MagSafe ES9039Q2M portable DAC/amp, 180 mW
A35: iFi audio | B35: GO link 2 | D35: Non | E35: Non | F35: Oui | G35: Non | H35: Non | I35: Non | J35: Non | K35: Non | M35: 69 | N35: Portable Amp/DAC (Headfonics) | O35: Import Headfonics — à enrichir | P35: https://headfonics.com/category/portable-amps-dacs/ | Q35: À évaluer | R35: À évaluer | S35: 8.1 | T35: Award | U35: 46197 | V35: 1 | W35: https://headfonics.com/?s=iFi+audio+GO+link+2 | X35: Dual ESS dongle DAC, up to 244 mW
A36: MUSE HiFi | B36: M3 Ultra | C36: ES9028Q2M; architecture hybride / tubes | D36: Non | E36: Non | F36: Oui | G36: Oui | H36: Non | I36: Non | J36: Non | K36: Non | M36: 109 | N36: Portable Amp/DAC (Headfonics) | O36: Import Headfonics — à enrichir | P36: https://headfonics.com/category/portable-amps-dacs/ | Q36: À évaluer | R36: À évaluer | S36: 8.3 | T36: Award | U36: 46181 | V36: 1 | W36: https://headfonics.com/?s=MUSE+HiFi+M3+Ultra | X36: ES9028Q2M + dual JAN6418 tube portable amp, 480 mW
A37: xDuoo | B37: Link3 | C37: 2x ES9039Q2M; XMOS XU316 | D37: Non | E37: Non | F37: Oui | G37: Oui | H37: Non | I37: Non | J37: Non | K37: Non | M37: 239 | N37: Portable Amp/DAC (Headfonics) | O37: Import Headfonics — à enrichir | P37: https://headfonics.com/category/portable-amps-dacs/ | Q37: À évaluer | R37: À évaluer | S37: 8.6 | T37: Award | U37: 46178 | V37: 1 | W37: https://headfonics.com/?s=xDuoo+Link3 | X37: Dongle DAC with microSD slot
A38: xDuoo | B38: XP-2 Bal | D38: Oui | E38: Oui | F38: Oui | G38: Oui | H38: Non | I38: Non | J38: Non | K38: Non | M38: 149 | N38: Portable Amp/DAC (Headfonics) | O38: Import Headfonics — à enrichir | P38: https://headfonics.com/category/portable-amps-dacs/ | Q38: À évaluer | R38: À évaluer | S38: 8.4 | T38: Award | U38: 46157 | V38: 1 | W38: https://headfonics.com/?s=xDuoo+XP-2+Bal | X38: Portable DAC/amp, balanced 320 mW, Bluetooth
A39: iBasso | B39: PB6 MACAW | D39: Oui | E39: Non | F39: Oui | G39: Oui | H39: Non | I39: Non | J39: Non | K39: Non | M39: 438 | N39: Portable Amp/DAC (Headfonics) | O39: Import Headfonics — à enrichir | P39: https://headfonics.com/category/portable-amps-dacs/ | Q39: À évaluer | R39: À évaluer | S39: 9 | T39: Award | U39: 46081 | V39: 1 | W39: https://headfonics.com/?s=iBasso+PB6+MACAW | X39: Quad JAN6418 tube portable headphone amplifier, up to 2.3 W
A40: HiBy | B40: W4 | D40: Oui | E40: Oui | F40: Oui | G40: Oui | H40: Non | I40: Non | J40: Non | K40: Non | M40: 87 | N40: Portable Amp/DAC (Headfonics) | O40: Import Headfonics — à enrichir | P40: https://headfonics.com/category/portable-amps-dacs/ | Q40: À évaluer | R40: À évaluer | S40: 8.3 | T40: Award | U40: 46066 | V40: 1 | W40: https://headfonics.com/?s=HiBy+W4 | X40: Bluetooth 5.4 dual-DAC portable amp, up to 475 mW
A41: Questyle | B41: SIGMA Pro | D41: Oui | E41: Oui | F41: Oui | G41: Oui | H41: Non | I41: Oui | J41: Non | K41: Non | M41: 790 | N41: Portable Amp/DAC (Headfonics) | O41: Import Headfonics — à enrichir | P41: https://headfonics.com/category/portable-amps-dacs/ | Q41: À évaluer | R41: À évaluer | S41: 8.6 | T41: Award | U41: 46053 | V41: 1 | W41: https://headfonics.com/?s=Questyle+SIGMA+Pro | X41: Bluetooth-capable Current Mode portable DAC/amp
A42: iBasso | B42: D17 Atheris | D42: Oui | E42: Non | F42: Oui | G42: Oui | H42: Non | I42: Non | J42: Non | K42: Non | M42: 1757 | N42: Portable Amp/DAC (Headfonics) | O42: Import Headfonics — à enrichir | P42: https://headfonics.com/category/portable-amps-dacs/ | Q42: À évaluer | R42: À évaluer | S42: 9 | T42: Reader | U42: 45992 | V42: 1 | W42: https://headfonics.com/?s=iBasso+D17+Atheris | X42: Discrete R2R + 1-bit portable DAC/amp, up to 1.2 W
A43: Cayin | B43: RU3 | D43: Non | E43: Non | F43: Oui | G43: Oui | H43: Non | I43: Non | J43: Non | K43: Oui | M43: 87 | N43: Portable Amp/DAC (Headfonics) | O43: Import Headfonics — à enrichir | P43: https://headfonics.com/category/portable-amps-dacs/ | Q43: À évaluer | R43: À évaluer | S43: 8.2 | T43: Reader | U43: 45990 | V43: 1 | W43: https://headfonics.com/?s=Cayin+RU3 | X43: ES9069Q dongle DAC, app integration, up to 560 mW
A44: FiiO | B44: SNOWSKY Tiny | D44: Non | E44: Non | F44: Oui | G44: Selon variante | H44: Non | I44: Non | J44: Non | K44: Oui | M44: 19 | N44: Portable Amp/DAC (Headfonics) | O44: Import Headfonics — à enrichir | P44: https://headfonics.com/category/portable-amps-dacs/ | Q44: À évaluer | R44: À évaluer | S44: 8.1 | T44: Reader | U44: 45989 | V44: 1 | W44: https://headfonics.com/?s=FiiO+SNOWSKY+Tiny | X44: Affordable dongle DAC, PCM384/DSD256, 10-band PEQ
A45: Khadas | B45: Tea Pro | D45: Oui | E45: Oui | F45: Oui | G45: Oui | H45: Non | I45: Non | J45: Non | K45: Oui | M45: 175 | N45: Portable Amp/DAC (Headfonics) | O45: Import Headfonics — à enrichir | P45: https://headfonics.com/category/portable-amps-dacs/ | Q45: À évaluer | R45: À évaluer | S45: 8.1 | T45: Reader | U45: 45965 | V45: 1 | W45: https://headfonics.com/?s=Khadas+Tea+Pro | X45: Wireless ES9039Q2M magnetic portable DAC/amp
A46: ddHiFi | B46: TC44Grip | C46: 2x CS43198; 2x SGM8262-2 | D46: Non | E46: Non | F46: Oui | G46: Oui | H46: Non | I46: Non | J46: Non | K46: Non | M46: 159 | N46: Portable Amp/DAC (Headfonics) | O46: Import Headfonics — à enrichir | P46: https://headfonics.com/category/portable-amps-dacs/ | Q46: À évaluer | R46: À évaluer | S46: 7.7 | T46: Reader | U46: 45964 | V46: 1 | W46: https://headfonics.com/?s=ddHiFi+TC44Grip | X46: Dual CS43198 smartphone-mounted dongle DAC, 330 mW
A47: ddHiFi | B47: TC44 Pro E3 | C47: 2x CS43198; sorties 3.5/4.4 mm | D47: Non | E47: Non | F47: Oui | G47: Oui | H47: Non | I47: Non | J47: Non | K47: Non | M47: 104.9 | N47: Portable Amp/DAC (Headfonics) | O47: Import Headfonics — à enrichir | P47: https://headfonics.com/category/portable-amps-dacs/ | Q47: À évaluer | R47: À évaluer | S47: 7.9 | T47: Reader | U47: 45945 | V47: 1 | W47: https://headfonics.com/?s=ddHiFi+TC44+Pro+E3 | X47: Dual CS43198 dongle DAC, up to 510 mW
A48: xDuoo | B48: Link10 | C48: 2x CS43131; jusqu’à 2x300 mW @ 32Ω | D48: Non | E48: Non | F48: Oui | G48: Oui | H48: Non | I48: Non | J48: Non | K48: Non | M48: 109 | N48: Portable Amp/DAC (Headfonics) | O48: Import Headfonics — à enrichir | P48: https://headfonics.com/category/portable-amps-dacs/page/2/ | Q48: À évaluer | R48: À évaluer | S48: 7.7 | T48: Reader | U48: 45931 | V48: 2 | W48: https://headfonics.com/?s=xDuoo+Link10 | X48: Dual CS43131 USB DAC/amp, up to 300 mW
A49: FiiO | B49: JIEZI | D49: Non | E49: Non | F49: Selon variante | G49: Selon variante | H49: Non | I49: Non | J49: Non | K49: Oui | M49: 11 | N49: Portable Amp/DAC (Headfonics) | O49: Import Headfonics — à enrichir | P49: https://headfonics.com/category/portable-amps-dacs/page/2/ | Q49: À évaluer | R49: À évaluer | S49: 7.4 | T49: Reader | U49: 45927 | V49: 2 | W49: https://headfonics.com/?s=FiiO+JIEZI | X49: Affordable 4.4 mm dongle DAC with 10-band PEQ
A50: FiiO | B50: SNOWSKY Melody | D50: Non | E50: Non | F50: Oui | G50: Oui | H50: Non | I50: Non | J50: Non | K50: Oui | M50: 35 | N50: Portable Amp/DAC (Headfonics) | O50: Import Headfonics — à enrichir | P50: https://headfonics.com/category/portable-amps-dacs/page/2/ | Q50: À évaluer | R50: À évaluer | S50: 7.7 | T50: Reader | U50: 45913 | V50: 2 | W50: https://headfonics.com/?s=FiiO+SNOWSKY+Melody | X50: Dual CS43131 wood-design dongle DAC, 250 mW
A51: xDuoo | B51: XD05 Basic2 | C51: CS43131; Bluetooth 5.4; PCM 32/384; DSD256 | D51: Oui | E51: Oui | F51: Non | G51: Non | H51: Non | I51: Oui | J51: Non | K51: Non | M51: 299 | N51: Portable Amp/DAC (Headfonics) | O51: Import Headfonics — à enrichir | P51: https://headfonics.com/category/portable-amps-dacs/page/2/ | Q51: À évaluer | R51: À évaluer | S51: 8.3 | T51: Reader | U51: 45889 | V51: 2 | W51: https://headfonics.com/?s=xDuoo+XD05+Basic2 | X51: CS43131 portable DAC/amp, 750 mW, swappable op-amps, wireless
A52: iBasso | B52: Nunchaku | C52: 2x CS43198; FPGA; amplification tube/transistor | D52: Non | E52: Non | F52: Oui | G52: Oui | H52: Non | I52: Non | J52: Non | K52: Non | M52: 299 | N52: Portable Amp/DAC (Headfonics) | O52: Import Headfonics — à enrichir | P52: https://headfonics.com/category/portable-amps-dacs/page/2/ | Q52: À évaluer | R52: À évaluer | S52: 8.6 | T52: Reader | U52: 45864 | V52: 2 | W52: https://headfonics.com/?s=iBasso+Nunchaku | X52: Portable DAC/amp; Headfonics category entry added after older cache snapshots
A53: NiPO | B53: A100 | D53: Oui | E53: Non | F53: Oui | G53: Oui | H53: Non | I53: Non | J53: Non | K53: Non | M53: 351 | N53: Portable Amp/DAC (Headfonics) | O53: Import Headfonics — à enrichir | P53: https://headfonics.com/category/portable-amps-dacs/page/2/ | Q53: À évaluer | R53: À évaluer | S53: 8 | T53: Reader | U53: 45859 | V53: 2 | W53: https://headfonics.com/?s=NiPO+A100 | X53: ES9039Q2M portable DAC/amp, up to 550 mW
A54: ddHiFi | B54: TC44Pro M3 | D54: Non | E54: Non | F54: Oui | G54: Oui | H54: Non | I54: Non | J54: Non | K54: Non | M54: 79 | N54: Portable Amp/DAC (Headfonics) | O54: Import Headfonics — à enrichir | P54: https://headfonics.com/category/portable-amps-dacs/page/2/ | Q54: À évaluer | R54: À évaluer | S54: 8 | T54: Reader | U54: 45852 | V54: 2 | W54: https://headfonics.com/?s=ddHiFi+TC44Pro+M3 | X54: Dual CS43198 dongle DAC, up to 120 mW balanced
A55: Cayin | B55: RU9 | D55: Oui | E55: Oui | F55: Oui | G55: Oui | H55: Non | I55: Non | J55: Non | K55: Non | M55: 438 | N55: Portable Amp/DAC (Headfonics) | O55: Import Headfonics — à enrichir | P55: https://headfonics.com/category/portable-amps-dacs/page/2/ | Q55: À évaluer | R55: À évaluer | S55: 8.6 | T55: Reader | U55: 45850 | V55: 2 | W55: https://headfonics.com/?s=Cayin+RU9 | X55: Tube/solid-state USB DAC/amp, up to 1 W
A56: Shanling | B56: UP6 | C56: 2x ES9069Q; 2x SGM8262; Bluetooth 5.2 | D56: Oui | E56: Oui | F56: Oui | G56: Oui | H56: Non | I56: Non | J56: Non | K56: Oui | M56: 189 | N56: Portable Amp/DAC (Headfonics) | O56: Import Headfonics — à enrichir | P56: https://headfonics.com/category/portable-amps-dacs/page/2/ | Q56: À évaluer | R56: À évaluer | S56: 8.4 | T56: Reader | U56: 45847 | V56: 2 | W56: https://headfonics.com/?s=Shanling+UP6 | X56: Dual ES9069Q Bluetooth DAC/amp with LDAC/aptX
A57: Questyle | B57: M18i | D57: Oui | E57: Oui | F57: Oui | G57: Oui | H57: Non | I57: Non | J57: Non | K57: Non | M57: 307 | N57: Portable Amp/DAC (Headfonics) | O57: Import Headfonics — à enrichir | P57: https://headfonics.com/category/portable-amps-dacs/page/2/ | Q57: À évaluer | R57: À évaluer | S57: 8.3 | T57: Reader | U57: 45798 | V57: 2 | W57: https://headfonics.com/?s=Questyle+M18i | X57: ES9219Q wireless dongle DAC with Current Mode amplification
A58: FiiO | B58: RR11 | D58: Oui | E58: Non | F58: Oui | G58: Non | H58: Non | I58: Non | J58: Non | K58: Non | M58: 53 | N58: Portable Amp/DAC (Headfonics) | O58: Import Headfonics — à enrichir | P58: https://headfonics.com/category/portable-amps-dacs/page/2/ | Q58: À évaluer | R58: À évaluer | S58: 7.7 | T58: Reader | U58: 45787 | V58: 2 | W58: https://headfonics.com/?s=FiiO+RR11 | X58: Portable FM radio with dongle functionality
A59: EarMen | B59: L-Amp | D59: Non | E59: Non | F59: Oui | G59: Oui | H59: Non | I59: Non | J59: Non | K59: Non | M59: 351 | N59: Portable Amp/DAC (Headfonics) | O59: Import Headfonics — à enrichir | P59: https://headfonics.com/category/portable-amps-dacs/page/2/ | Q59: À évaluer | R59: À évaluer | S59: 8.6 | T59: Reader | U59: 45770 | V59: 2 | W59: https://headfonics.com/?s=EarMen+L-Amp | X59: Dual JAN6418 NOS tube portable headphone amplifier/DAC
A60: FiiO | B60: SNOWSKY RETRO NANO | D60: Oui | E60: Oui | F60: Oui | G60: Oui | H60: Non | I60: Non | J60: Non | K60: Oui | M60: 53 | N60: Portable Amp/DAC (Headfonics) | O60: Import Headfonics — à enrichir | P60: https://headfonics.com/category/portable-amps-dacs/page/2/ | Q60: À évaluer | R60: À évaluer | S60: 8.1 | T60: Reader | U60: 45745 | V60: 2 | W60: https://headfonics.com/?s=FiiO+SNOWSKY+RETRO+NANO | X60: Self-powered Bluetooth dongle DAC, up to 220 mW
A61: Cayin | B61: C9ii | D61: Oui | E61: Non | F61: Oui | G61: Oui | H61: Non | I61: Non | J61: Non | K61: Non | M61: 2108 | N61: Portable Amp/DAC (Headfonics) | O61: Import Headfonics — à enrichir | P61: https://headfonics.com/category/portable-amps-dacs/page/2/ | Q61: À évaluer | R61: À évaluer | S61: 9.1 | T61: Reader | U61: 45735 | V61: 2 | W61: https://headfonics.com/?s=Cayin+C9ii | X61: Solid-state / Gen 5 Nutube portable headphone amplifier
A62: ddHiFi | B62: TC35M2 | D62: Non | E62: Non | F62: Oui | G62: Non | H62: Non | I62: Non | J62: Non | K62: Non | M62: 32 | N62: Portable Amp/DAC (Headfonics) | O62: Import Headfonics — à enrichir | P62: https://headfonics.com/category/portable-amps-dacs/page/2/ | Q62: À évaluer | R62: À évaluer | S62: 7.9 | T62: Reader | U62: 45691 | V62: 2 | W62: https://headfonics.com/?s=ddHiFi+TC35M2 | X62: Tiny 384 kHz USB-C DAC to 3.5 mm converter
A63: iFi audio | B63: GO link Max | D63: Non | E63: Non | F63: Oui | G63: Oui | H63: Non | I63: Non | J63: Non | K63: Non | M63: 69 | N63: Portable Amp/DAC (Headfonics) | O63: Import Headfonics — à enrichir | P63: https://headfonics.com/category/portable-amps-dacs/page/2/ | Q63: À évaluer | R63: À évaluer | S63: 7.8 | T63: Reader | U63: 45672 | V63: 2 | W63: https://headfonics.com/?s=iFi+audio+GO+link+Max | X63: Compact DSD256-capable dongle DAC
A64: Heartfield | B64: R1 | D64: Non | E64: Non | F64: Oui | G64: Oui | H64: Non | I64: Non | J64: Non | K64: Non | M64: 140 | N64: Portable Amp/DAC (Headfonics) | O64: Import Headfonics — à enrichir | P64: https://headfonics.com/category/portable-amps-dacs/page/2/ | Q64: À évaluer | R64: À évaluer | S64: 7.7 | T64: Reader | U64: 45665 | V64: 2 | W64: https://headfonics.com/?s=Heartfield+R1 | X64: 64-resistor R2R balanced dongle DAC
A65: iBasso | B65: PB5 Osprey | D65: Oui | E65: Non | F65: Oui | G65: Oui | H65: Non | I65: Non | J65: Non | K65: Non | M65: 1317 | N65: Portable Amp/DAC (Headfonics) | O65: Import Headfonics — à enrichir | P65: https://headfonics.com/category/portable-amps-dacs/page/3/ | Q65: À évaluer | R65: À évaluer | S65: 9 | T65: Reader | U65: 45647 | V65: 3 | W65: https://headfonics.com/?s=iBasso+PB5+Osprey | X65: Dual Nutube 6P1 portable headphone amplifier, up to 1.7 W
A66: FiiO | B66: KA15 | C66: 2x CS43198; 2x SGM8262 | D66: Non | E66: Non | F66: Oui | G66: Oui | H66: Non | I66: Non | J66: Non | K66: Oui | M66: 109 | N66: Portable Amp/DAC (Headfonics) | O66: Import Headfonics — à enrichir | P66: https://headfonics.com/category/portable-amps-dacs/page/3/ | Q66: À évaluer | R66: À évaluer | S66: 8.1 | T66: Reader | U66: 45619 | V66: 3 | W66: https://headfonics.com/?s=FiiO+KA15 | X66: Dual CS43198 dongle DAC, up to 500 mW
A67: TempoTec | B67: Sonata BHD Pro | D67: Non | E67: Non | F67: Oui | G67: Oui | H67: Non | I67: Non | J67: Non | K67: Non | M67: 61 | N67: Portable Amp/DAC (Headfonics) | O67: Import Headfonics — à enrichir | P67: https://headfonics.com/category/portable-amps-dacs/page/3/ | Q67: À évaluer | R67: À évaluer | S67: 7 | T67: Reader | U67: 45609 | V67: 3 | W67: https://headfonics.com/?s=TempoTec+Sonata+BHD+Pro | X67: Dual CS43131 dongle DAC, up to 280 mW
A68: iBasso | B68: D16 Taipan | C68: DAC 1-bit discret; FPGA; Class A | D68: Oui | E68: Non | F68: Oui | G68: Oui | H68: Non | I68: Non | J68: Non | K68: Non | M68: 1490 | N68: Portable Amp/DAC (Headfonics) | O68: Import Headfonics — à enrichir | P68: https://headfonics.com/category/portable-amps-dacs/page/3/ | Q68: À évaluer | R68: À évaluer | S68: 8.7 | T68: Reader | U68: 45591 | V68: 3 | W68: https://headfonics.com/?s=iBasso+D16+Taipan | X68: Discrete 1-bit DAC + Super Class A amp, up to 1.125 W
A69: 7Hz | B69: Artemis39 | C69: ES9039Q2M; Bluetooth; batterie 1100 mAh | D69: Oui | E69: Oui | F69: Oui | G69: Oui | H69: Non | I69: Non | J69: Non | K69: Non | M69: 149 | N69: Portable Amp/DAC (Headfonics) | O69: Import Headfonics — à enrichir | P69: https://headfonics.com/category/portable-amps-dacs/page/3/ | Q69: À évaluer | R69: À évaluer | S69: 8 | T69: Reader | U69: 45567 | V69: 3 | W69: https://headfonics.com/?s=7Hz+Artemis39 | X69: Wireless ES9039Q2M dongle DAC, LDAC, up to 405 mW
A70: SMSL | B70: D10 | D70: Non | E70: Non | F70: Oui | G70: Oui | H70: Non | I70: Non | J70: Non | K70: Non | M70: 62 | N70: Portable Amp/DAC (Headfonics) | O70: Import Headfonics — à enrichir | P70: https://headfonics.com/category/portable-amps-dacs/page/3/ | Q70: À évaluer | R70: À évaluer | S70: 8.1 | T70: Reader | U70: 45555 | V70: 3 | W70: https://headfonics.com/?s=SMSL+D10 | X70: Dual CS43131 balanced dongle DAC, up to 500 mW
A71: FiiO | B71: JA11 | D71: Non | E71: Non | F71: Oui | G71: Non | H71: Non | I71: Non | J71: Non | K71: Oui | M71: 13 | N71: Portable Amp/DAC (Headfonics) | O71: Import Headfonics — à enrichir | P71: https://headfonics.com/category/portable-amps-dacs/page/3/ | Q71: À évaluer | R71: À évaluer | S71: 7.5 | T71: Reader | U71: 45513 | V71: 3 | W71: https://headfonics.com/?s=FiiO+JA11 | X71: Portable dongle DAC/amp
A72: Shanling | B72: H2 | D72: Oui | E72: Oui | F72: Oui | G72: Oui | H72: Non | I72: Non | J72: Non | K72: Non | M72: 149 | N72: Portable Amp/DAC (Headfonics) | O72: Import Headfonics — à enrichir | P72: https://headfonics.com/category/portable-amps-dacs/page/3/ | Q72: À évaluer | R72: À évaluer | S72: 8.1 | T72: Reader | U72: 45509 | V72: 3 | W72: https://headfonics.com/?s=Shanling+H2 | X72: CS43198 portable DAC/headphone amp
A73: LETSHUOER | B73: DT03 | D73: Non | E73: Non | F73: Oui | G73: Oui | H73: Non | I73: Non | J73: Non | K73: Non | M73: 87 | N73: Portable Amp/DAC (Headfonics) | O73: Import Headfonics — à enrichir | P73: https://headfonics.com/category/portable-amps-dacs/page/3/ | Q73: À évaluer | R73: À évaluer | S73: 7.8 | T73: Reader | U73: 45495 | V73: 3 | W73: https://headfonics.com/?s=LETSHUOER+DT03 | X73: Portable dongle DAC/amp
A74: Kiwi Ears | B74: Allegro | D74: Non | E74: Non | F74: Oui | G74: Oui | H74: Non | I74: Non | J74: Non | K74: Non | M74: 53 | N74: Portable Amp/DAC (Headfonics) | O74: Import Headfonics — à enrichir | P74: https://headfonics.com/category/portable-amps-dacs/page/3/ | Q74: À évaluer | R74: À évaluer | S74: 7.7 | T74: Reader | U74: 45476 | V74: 3 | W74: https://headfonics.com/?s=Kiwi+Ears+Allegro | X74: Portable dongle DAC/amp
A75: Hidizs | B75: S8 Pro Robin | C75: 2x CS43131; 160+160 mW @ 32Ω | D75: Non | E75: Non | F75: Oui | G75: Oui | H75: Non | I75: Non | J75: Non | K75: Non | M75: 69.52 | N75: Portable Amp/DAC (Headfonics) | O75: Import Headfonics — à enrichir | P75: https://headfonics.com/category/portable-amps-dacs/page/3/ | Q75: À évaluer | R75: À évaluer | S75: 8 | T75: Reader | U75: 45471 | V75: 3 | W75: https://headfonics.com/?s=Hidizs+S8+Pro+Robin | X75: Portable dongle DAC/amp
A76: iFi audio | B76: GO bar Kensei | C76: XMOS; K2HD; PCM 32/384; DSD256 | D76: Non | E76: Non | F76: Oui | G76: Oui | H76: Non | I76: Non | J76: Non | K76: Non | M76: 449 | N76: Portable Amp/DAC (Headfonics) | O76: Import Headfonics — à enrichir | P76: https://headfonics.com/category/portable-amps-dacs/page/3/ | Q76: À évaluer | R76: À évaluer | S76: 8.1 | T76: Reader | U76: 45465 | V76: 3 | W76: https://headfonics.com/?s=iFi+audio+GO+bar+Kensei | X76: Portable dongle DAC/amp
A77: ONIX | B77: Mystic XP1 | D77: Oui | E77: Oui | F77: Oui | G77: Oui | H77: Non | I77: Oui | J77: Non | K77: Non | M77: 1317 | N77: Portable Amp/DAC (Headfonics) | O77: Import Headfonics — à enrichir | P77: https://headfonics.com/category/portable-amps-dacs/page/3/ | Q77: À évaluer | R77: À évaluer | S77: 8.7 | T77: Reader | U77: 45439 | V77: 3 | W77: https://headfonics.com/?s=ONIX+Mystic+XP1 | X77: Portable amplifier/DAC
A78: Shanling | B78: UA4 | C78: ES9069Q; PCM 32/768; DSD512 | D78: Non | E78: Non | F78: Oui | G78: Oui | H78: Non | I78: Non | J78: Non | K78: Non | M78: 99 | N78: Portable Amp/DAC (Headfonics) | O78: Import Headfonics — à enrichir | P78: https://headfonics.com/category/portable-amps-dacs/page/3/ | Q78: À évaluer | R78: À évaluer | S78: 7.5 | T78: Reader | U78: 45425 | V78: 3 | W78: https://headfonics.com/?s=Shanling+UA4 | X78: Portable dongle DAC/amp
A79: FiiO | B79: KA11 | D79: Non | E79: Non | F79: Oui | G79: Non | H79: Non | I79: Non | J79: Non | K79: Non | M79: 26 | N79: Portable Amp/DAC (Headfonics) | O79: Import Headfonics — à enrichir | P79: https://headfonics.com/category/portable-amps-dacs/page/3/ | Q79: À évaluer | R79: À évaluer | T79: Reader (non relevé) | U79: 45418 | V79: 3 | W79: https://headfonics.com/?s=FiiO+KA11 | X79: Portable dongle DAC/amp
A80: FiiO | B80: KA17 | C80: 2x ES9069Q; THX AAA 78+; XMOS XU316 | D80: Non | E80: Non | F80: Oui | G80: Oui | H80: Non | I80: Non | J80: Non | K80: Oui | M80: 159 | N80: Portable Amp/DAC (Headfonics) | O80: Import Headfonics — à enrichir | P80: https://headfonics.com/category/portable-amps-dacs/page/3/ | Q80: À évaluer | R80: À évaluer | T80: Reader (non relevé) | U80: 45409 | V80: 3 | W80: https://headfonics.com/?s=FiiO+KA17 | X80: Portable dongle DAC/amp
A81: Colorfly | B81: CDA-M2 | D81: Non | E81: Non | F81: Oui | G81: Oui | H81: Non | I81: Non | J81: Non | K81: Non | M81: 140 | N81: Portable Amp/DAC (Headfonics) | O81: Import Headfonics — à enrichir | P81: https://headfonics.com/category/portable-amps-dacs/page/3/ | Q81: À évaluer | R81: À évaluer | S81: 8 | T81: Reader | U81: 45408 | V81: 3 | W81: https://headfonics.com/?s=Colorfly+CDA-M2 | X81: Portable dongle DAC/amp
A82: ddHiFi | B82: TC44Pro E2 | C82: 2x CS43131; 4.4 mm; USB-C ou Lightning | D82: Non | E82: Non | F82: Non | G82: Oui | H82: Non | I82: Non | J82: Non | K82: Non | M82: 79 | N82: Portable Amp/DAC (Headfonics) | O82: Import Headfonics — à enrichir | P82: https://headfonics.com/category/portable-amps-dacs/page/4/ | Q82: À évaluer | R82: À évaluer | S82: 8 | T82: Reader | U82: 45394 | V82: 4 | W82: https://headfonics.com/?s=ddHiFi+TC44Pro+E2 | X82: Portable dongle DAC/amp
A83: Hidizs | B83: SD2 | D83: Non | E83: Non | F83: Oui | G83: Non | H83: Non | I83: Non | J83: Non | K83: Non | M83: 44 | N83: Portable Amp/DAC (Headfonics) | O83: Import Headfonics — à enrichir | P83: https://headfonics.com/category/portable-amps-dacs/page/4/ | Q83: À évaluer | R83: À évaluer | S83: 7.8 | T83: Reader | U83: 45359 | V83: 4 | W83: https://headfonics.com/?s=Hidizs+SD2 | X83: Portable dongle DAC/amp
A84: Colorfly | B84: CDA-M1P | D84: Non | E84: Non | F84: Oui | G84: Oui | H84: Non | I84: Non | J84: Non | K84: Non | M84: 69 | N84: Portable Amp/DAC (Headfonics) | O84: Import Headfonics — à enrichir | P84: https://headfonics.com/category/portable-amps-dacs/page/4/ | Q84: À évaluer | R84: À évaluer | S84: 8.2 | T84: Reader | U84: 45350 | V84: 4 | W84: https://headfonics.com/?s=Colorfly+CDA-M1P | X84: Portable dongle DAC/amp
A85: FiiO | B85: Q15 | D85: Oui | E85: Oui | F85: Oui | G85: Oui | H85: Non | I85: Non | J85: Non | K85: Oui | M85: 351 | N85: Portable Amp/DAC (Headfonics) | O85: Import Headfonics — à enrichir | P85: https://headfonics.com/category/portable-amps-dacs/page/4/ | Q85: À évaluer | R85: À évaluer | T85: Reader (non relevé) | U85: 45339 | V85: 4 | W85: https://headfonics.com/?s=FiiO+Q15 | X85: Portable DAC/amp
A86: iFi audio | B86: iDSD Diablo 2 | D86: Oui | E86: Oui | F86: Non | G86: Oui | H86: Non | I86: Oui | J86: Non | K86: Non | M86: 1141 | N86: Portable Amp/DAC (Headfonics) | O86: Import Headfonics — à enrichir | P86: https://headfonics.com/category/portable-amps-dacs/page/4/ | Q86: À évaluer | R86: À évaluer | S86: 8.8 | T86: Reader | U86: 45318 | V86: 4 | W86: https://headfonics.com/?s=iFi+audio+iDSD+Diablo+2 | X86: Transportable/portable DAC/amp
A87: ddHiFi | B87: TC35Pro Eye2 & Mountain2 | D87: Non | E87: Non | F87: Oui | G87: Non | H87: Non | I87: Non | J87: Non | K87: Non | M87: 62 | N87: Portable Amp/DAC (Headfonics) | O87: Import Headfonics — à enrichir | P87: https://headfonics.com/category/portable-amps-dacs/page/4/ | Q87: À évaluer | R87: À évaluer | S87: 7.9 | T87: Reader | U87: 45294 | V87: 4 | W87: https://headfonics.com/?s=ddHiFi+TC35Pro+Eye2+%26+Mountain2 | X87: Portable USB DAC adapters
A88: Shanling | B88: UA1 Plus | D88: Non | E88: Non | F88: Oui | G88: Non | H88: Non | I88: Non | J88: Non | K88: Non | M88: 43 | N88: Portable Amp/DAC (Headfonics) | O88: Import Headfonics — à enrichir | P88: https://headfonics.com/category/portable-amps-dacs/page/4/ | Q88: À évaluer | R88: À évaluer | S88: 8 | T88: Reader | U88: 45290 | V88: 4 | W88: https://headfonics.com/?s=Shanling+UA1+Plus | X88: Portable dongle DAC/amp
A89: iFi audio | B89: hip-dac 3 | C89: Burr-Brown; XMOS; symétrique | D89: Oui | E89: Non | F89: Oui | G89: Oui | H89: Non | I89: Non | J89: Non | K89: Non | M89: 199 | N89: Portable Amp/DAC (Headfonics) | O89: Import Headfonics — à enrichir | P89: https://headfonics.com/category/portable-amps-dacs/page/4/ | Q89: À évaluer | R89: À évaluer | S89: 8.1 | T89: Reader | U89: 45271 | V89: 4 | W89: https://headfonics.com/?s=iFi+audio+hip-dac+3 | X89: Battery portable DAC/amp
A90: Hidizs | B90: S9 Pro Plus Martha | C90: ES9038Q2M; symétrique | D90: Non | E90: Non | F90: Oui | G90: Oui | H90: Non | I90: Non | J90: Non | K90: Non | M90: 85 | N90: Portable Amp/DAC (Headfonics) | O90: Import Headfonics — à enrichir | P90: https://headfonics.com/category/portable-amps-dacs/page/4/ | Q90: À évaluer | R90: À évaluer | S90: 8.1 | T90: Reader | U90: 45264 | V90: 4 | W90: https://headfonics.com/?s=Hidizs+S9+Pro+Plus+Martha | X90: Portable dongle DAC/amp
A91: xDuoo | B91: XD05 Pro | C91: ES9039SPRO; XMOS XU316; modules remplaçables | D91: Oui | E91: Oui | F91: Non | G91: Oui | H91: Non | I91: Oui | J91: Non | K91: Non | M91: 749 | N91: Portable Amp/DAC (Headfonics) | O91: Import Headfonics — à enrichir | P91: https://headfonics.com/category/portable-amps-dacs/page/4/ | Q91: À évaluer | R91: À évaluer | S91: 8.7 | T91: Reader | U91: 45250 | V91: 4 | W91: https://headfonics.com/?s=xDuoo+XD05+Pro | X91: Modular transportable DAC/amp
A92: FiiO | B92: KA13 | D92: Non | E92: Non | F92: Oui | G92: Oui | H92: Non | I92: Non | J92: Non | K92: Non | M92: 79 | N92: Portable Amp/DAC (Headfonics) | O92: Import Headfonics — à enrichir | P92: https://headfonics.com/category/portable-amps-dacs/page/4/ | Q92: À évaluer | R92: À évaluer | T92: Reader (non relevé) | U92: 45234 | V92: 4 | W92: https://headfonics.com/?s=FiiO+KA13 | X92: Portable dongle DAC/amp
A93: Audirect | B93: Beam 4 | D93: Oui | E93: Non | F93: Oui | G93: Oui | H93: Non | I93: Non | J93: Non | K93: Non | M93: 211 | N93: Portable Amp/DAC (Headfonics) | O93: Import Headfonics — à enrichir | P93: https://headfonics.com/category/portable-amps-dacs/page/4/ | Q93: À évaluer | R93: À évaluer | S93: 8 | T93: Reader | U93: 45231 | V93: 4 | W93: https://headfonics.com/?s=Audirect+Beam+4 | X93: Portable DAC/amp
A94: ddHiFi | B94: TC44Pro | D94: Non | E94: Non | F94: Non | G94: Oui | H94: Non | I94: Non | J94: Non | K94: Non | M94: 70 | N94: Portable Amp/DAC (Headfonics) | O94: Import Headfonics — à enrichir | P94: https://headfonics.com/category/portable-amps-dacs/page/4/ | Q94: À évaluer | R94: À évaluer | S94: 8.2 | T94: Reader | U94: 45229 | V94: 4 | W94: https://headfonics.com/?s=ddHiFi+TC44Pro | X94: Portable dongle DAC/amp
A95: Moondrop | B95: Dawn Pro | D95: Non | E95: Non | F95: Oui | G95: Oui | H95: Non | I95: Non | J95: Non | K95: Non | M95: 44 | N95: Portable Amp/DAC (Headfonics) | O95: Import Headfonics — à enrichir | P95: https://headfonics.com/category/portable-amps-dacs/page/4/ | Q95: À évaluer | R95: À évaluer | S95: 7.7 | T95: Reader | U95: 45219 | V95: 4 | W95: https://headfonics.com/?s=Moondrop+Dawn+Pro | X95: Portable dongle DAC/amp
A96: Moondrop | B96: MoonRiver 2: Ti | D96: Non | E96: Non | F96: Oui | G96: Oui | H96: Non | I96: Non | J96: Non | K96: Non | M96: 167 | N96: Portable Amp/DAC (Headfonics) | O96: Import Headfonics — à enrichir | P96: https://headfonics.com/category/portable-amps-dacs/page/4/ | Q96: À évaluer | R96: À évaluer | T96: Reader (non relevé) | U96: 45163 | V96: 4 | W96: https://headfonics.com/?s=Moondrop+MoonRiver+2%3A+Ti | X96: Portable dongle DAC/amp
A97: HiBy | B97: FC6 | D97: Non | E97: Non | F97: Oui | G97: Non | H97: Non | I97: Non | J97: Non | K97: Non | M97: 263 | N97: Portable Amp/DAC (Headfonics) | O97: Import Headfonics — à enrichir | P97: https://headfonics.com/category/portable-amps-dacs/page/4/ | Q97: À évaluer | R97: À évaluer | T97: Reader (non relevé) | U97: 45124 | V97: 4 | W97: https://headfonics.com/?s=HiBy+FC6 | X97: Portable dongle DAC/amp
A98: ddHiFi | B98: TC35C | D98: Non | E98: Non | F98: Oui | G98: Non | H98: Non | I98: Non | J98: Non | K98: Non | M98: 43 | N98: Portable Amp/DAC (Headfonics) | O98: Import Headfonics — à enrichir | P98: https://headfonics.com/category/portable-amps-dacs/page/4/ | Q98: À évaluer | R98: À évaluer | S98: 7.9 | T98: Reader | U98: 45114 | V98: 4 | W98: https://headfonics.com/?s=ddHiFi+TC35C | X98: Portable USB DAC adapter
A99: FiiO | B99: KA5 | D99: Non | E99: Non | F99: Oui | G99: Oui | H99: Non | I99: Non | J99: Non | K99: Non | M99: 129 | N99: Portable Amp/DAC (Headfonics) | O99: Import Headfonics — à enrichir | P99: https://headfonics.com/category/portable-amps-dacs/page/5/ | Q99: À évaluer | R99: À évaluer | T99: Reader (non relevé) | U99: 45103 | V99: 5 | W99: https://headfonics.com/?s=FiiO+KA5 | X99: Portable dongle DAC/amp
A100: FiiO | B100: Q11 | D100: Oui | E100: Non | F100: Oui | G100: Oui | H100: Non | I100: Non | J100: Non | K100: Non | M100: 79 | N100: Portable Amp/DAC (Headfonics) | O100: Import Headfonics — à enrichir | P100: https://headfonics.com/category/portable-amps-dacs/page/5/ | Q100: À évaluer | R100: À évaluer | T100: Reader (non relevé) | U100: 45073 | V100: 5 | W100: https://headfonics.com/?s=FiiO+Q11 | X100: Battery portable DAC/amp
A101: iFi audio | B101: UNO | D101: Non | E101: Non | F101: Oui | G101: Non | H101: Non | I101: Non | J101: Non | K101: Non | M101: 69 | N101: Portable Amp/DAC (Headfonics) | O101: Import Headfonics — à enrichir | P101: https://headfonics.com/category/portable-amps-dacs/page/5/ | Q101: À évaluer | R101: À évaluer | S101: 8.3 | T101: Reader | U101: 45066 | V101: 5 | W101: https://headfonics.com/?s=iFi+audio+UNO | X101: Portable/desktop USB DAC/amp
...

Sheet Sources technique
A1: Traçabilité de la vérification des colonnes D à K de « Technique & sources »
A2: Une ligne par produit et par champ renseigné. Vérification unitaire du 2026-08-10 : URL réellement ouverte + citation verbatim ayant servi de preuve. Depuis la reprise du 2026-08-10, la feuille contient aussi les cellules conclues par défaut : la citation indique alors explicitement « Aucune mention de … dans la source produit consultée » et l'URL est celle de la source ouverte pour ce produit. Ces lignes relèvent de la règle « non mentionné = Non » et non d'une attestation directe.
A4: Ligne | B4: Marque | C4: Modèle | D4: Champ | E4: Valeur retenue | F4: URL source | G4: Citation verbatim | H4: Date vérif.
A5: 6 | B5: Cayin | C5: N7 | D5: Batterie | E5: Oui | F5: https://hifigo.com/products/cayin-n7 | G5: Cayin N7 houses a large 9000mAh battery pack that provides a battery back of anywhere between 6 to 10 hours. | H5: 2026-08-10
A6: 6 | B6: Cayin | C6: N7 | D6: Bluetooth | E6: Oui | F6: https://hifigo.com/products/cayin-n7 | G6: Cayin N7 also has high-resolution two-way Bluetooth connectivity with class-leading LDAC, UAT, AAC, and SBC transmission protocols. | H6: 2026-08-10
A7: 6 | B7: Cayin | C7: N7 | D7: 3.5mm | E7: Oui | F7: https://headfonics.com/cayin-n7-review/ | G7: You get 4 ports, 2 x 4.4mm balanced for PO and LO, and 2 x 3.5mm SE for PO and LO. | H7: 2026-08-10
A8: 6 | B8: Cayin | C8: N7 | D8: 4.4mm | E8: Oui | F8: https://headfonics.com/cayin-n7-review/ | G8: You get 4 ports, 2 x 4.4mm balanced for PO and LO, and 2 x 3.5mm SE for PO and LO. | H8: 2026-08-10
A9: 6 | B9: Cayin | C9: N7 | D9: 2.5mm | E9: Non | F9: https://www.ecoustics.com/reviews/cayin-n7/ | G9: a pair of 2.5mm adapters for 3.5mm and 4.4mm ports (since the N7 does not have a 2.5mm port) | H9: 2026-08-10
A10: 6 | B10: Cayin | C10: N7 | D10: 6.35mm | E10: Non | F10: https://headfonics.com/cayin-n7-review/ | G10: You get 4 ports, 2 x 4.4mm balanced for PO and LO, and 2 x 3.5mm SE for PO and LO. | H10: 2026-08-10
A11: 6 | B11: Cayin | C11: N7 | D11: XLR | E11: Non | F11: https://headfonics.com/cayin-n7-review/ | G11: You get 4 ports, 2 x 4.4mm balanced for PO and LO, and 2 x 3.5mm SE for PO and LO. | H11: 2026-08-10
